Workbook

Sheet Bldg C 12WLOA
A1: # | B1: MEETING AGENDA
A2: A | B2: MEETING DETAILS
B3: MEETING. | E3: PRODUCTION
B4: WEEK NO. | E4: =WEEKNUM(E6) -> 9
B5: SECTION | E5: C
B6: DATE | E6: 46078
B7: TIME | E7: 0.4375
B8: LOCATION | E8: Building C : R005
B9: PURPOSE | E9: - To support and protect the Production Plan - To strive for improved Production Plan stability and predictability.
B10: NEXT MEETING | E10: =E6+7 -> 46085
A12: B | B12: STAKEHOLDERS | C12: Org. | D12: In Attendance | E12: Name | F12: Column1
B13: =IF(ISBLANK(E13), "", INDEX(OWNER_LIST[Role], MATCH(E13,OWNER_LIST[Owner Name], 0))) -> Project Manager (PM) | C13: =IF(ISBLANK(E13), "", INDEX(OWNER_LIST[Owner ORG], MATCH(E13,OWNER_LIST[Owner Name], 0))) -> RPN | D13: Yes | E13: Lorenzo Barnini
B14: =IF(ISBLANK(E14), "", INDEX(OWNER_LIST[Role], MATCH(E14,OWNER_LIST[Owner Name], 0))) -> Construction Manager | C14: =IF(ISBLANK(E14), "", INDEX(OWNER_LIST[Owner ORG], MATCH(E14,OWNER_LIST[Owner Name], 0))) -> RPN | D14: Yes | E14: Matteo Naldi
B15: =IF(ISBLANK(E15), "", INDEX(OWNER_LIST[Role], MATCH(E15,OWNER_LIST[Owner Name], 0))) -> Cost Control Manager | C15: =IF(ISBLANK(E15), "", INDEX(OWNER_LIST[Owner ORG], MATCH(E15,OWNER_LIST[Owner Name], 0))) -> RPN | D15: No | E15: Jessica Donatelli
B16: =IF(ISBLANK(E16), "", INDEX(OWNER_LIST[Role], MATCH(E16,OWNER_LIST[Owner Name], 0))) -> Engineering Chief & Move Manager | C16: =IF(ISBLANK(E16), "", INDEX(OWNER_LIST[Owner ORG], MATCH(E16,OWNER_LIST[Owner Name], 0))) -> RPN | D16: Yes | E16: Federica Brunone
B17: =IF(ISBLANK(E17), "", INDEX(OWNER_LIST[Role], MATCH(E17,OWNER_LIST[Owner Name], 0))) -> Arch Design Specialist | C17: =IF(ISBLANK(E17), "", INDEX(OWNER_LIST[Owner ORG], MATCH(E17,OWNER_LIST[Owner Name], 0))) -> RPN | D17: No | E17: Chiara Re Depaolini
B18: =IF(ISBLANK(E18), "", INDEX(OWNER_LIST[Role], MATCH(E18,OWNER_LIST[Owner Name], 0))) -> Schedule Manager | C18: =IF(ISBLANK(E18), "", INDEX(OWNER_LIST[Owner ORG], MATCH(E18,OWNER_LIST[Owner Name], 0))) -> RPN | D18: Yes | E18: Simone Conti
B19: =IF(ISBLANK(E19), "", INDEX(OWNER_LIST[Role], MATCH(E19,OWNER_LIST[Owner Name], 0))) -> Move Specialist / Doc Controller | C19: =IF(ISBLANK(E19), "", INDEX(OWNER_LIST[Owner ORG], MATCH(E19,OWNER_LIST[Owner Name], 0))) -> RPN | D19: No | E19: Martina Maffioletti
B20: =IF(ISBLANK(E20), "", INDEX(OWNER_LIST[Role], MATCH(E20,OWNER_LIST[Owner Name], 0))) -> Electrical Engineer | C20: =IF(ISBLANK(E20), "", INDEX(OWNER_LIST[Owner ORG], MATCH(E20,OWNER_LIST[Owner Name], 0))) -> RPN | D20: Yes | E20: Hacir Degirmencioglu
B21: =IF(ISBLANK(E21), "", INDEX(OWNER_LIST[Role], MATCH(E21,OWNER_LIST[Owner Name], 0))) -> Deputy Quality Manager | C21: =IF(ISBLANK(E21), "", INDEX(OWNER_LIST[Owner ORG], MATCH(E21,OWNER_LIST[Owner Name], 0))) -> RPN | D21: Yes | E21: Leonardo Valentinotti
B22: =IF(ISBLANK(E22), "", INDEX(OWNER_LIST[Role], MATCH(E22,OWNER_LIST[Owner Name], 0))) -> HSE & Security Manager | C22: =IF(ISBLANK(E22), "", INDEX(OWNER_LIST[Owner ORG], MATCH(E22,OWNER_LIST[Owner Name], 0))) -> RPN | D22: Yes | E22: MariaCristina Menozzi
B23: =IF(ISBLANK(E23), "", INDEX(OWNER_LIST[Role], MATCH(E23,OWNER_LIST[Owner Name], 0))) -> Architectural Manager | C23: =IF(ISBLANK(E23), "", INDEX(OWNER_LIST[Owner ORG], MATCH(E23,OWNER_LIST[Owner Name], 0))) -> SHP | D23: Yes | E23: Zeynep Onen
B24: =IF(ISBLANK(E24), "", INDEX(OWNER_LIST[Role], MATCH(E24,OWNER_LIST[Owner Name], 0))) -> Chief Design and Construction | C24: =IF(ISBLANK(E24), "", INDEX(OWNER_LIST[Owner ORG], MATCH(E24,OWNER_LIST[Owner Name], 0))) -> SHP | D24: Yes | E24: Neil Bradley
... B35: =IF(ISBLANK(E35), "", INDEX(OWNER_LIST[Role], MATCH(E35,OWNER_LIST[Owner Name], 0))) -> Quality Manager | C35: =IF(ISBLANK(E35), "", INDEX(OWNER_LIST[Owner ORG], MATCH(E35,OWNER_LIST[Owner Name], 0))) -> SHP | D35: Yes | E35: Didier Dequatre
A37: C1 | B37: MEETING TOPIC | C37: ACTION - INFO | D37: STATUS | E37: DESCRIPTION - INFORMATION LOG | F37: ACTION REQUIRED | G37: PRIORITY | H37: DUE DATE | I37: OWNER ORG. | J37: OWNER NAME 1 | K37: OWNER NAME 2 | L37: DISCIPLINE | M37: DATE LOGGED | N37: DATE CLOSED | O37: ESCALATE | P37: Note | Q37: Row_PM | R37: Notify_PM | S37: Condition_PM | T37: ROW | U37: Email_Name_1 | V37: Email_Name_2 | W37: SECTION | X37: Nonull
A38: C_1 | B38: HEALTH & SAFETY | X38: =IF( OR( AND( NOT(ISBLANK(C_1[[#This Row],[DESCRIPTION - INFORMATION LOG]])), C_1[[#This Row],[DESCRIPTION - INFORMATION LOG]] <> "DESCRIPTION - INFORMATION LOG" ), NOT(ISBLANK(C_1[[#This Row],[ACTION REQUIRED]])) ), "Y", "N" ) -> N
A39: HSE | B39: Fire closure between Bldg C and AC - Level 4 & 5 | D39: CLOSED | E39: Permenent FR glazed door instaled at level 4 and 5 are not closing properly | F39: 07.01: RPN to repair the locks. | G39: TOP | H39: 46050 | I39: {=IFERROR(_xlfn.TEXTJOIN(" / ", TRUE, IF(OWNER_LIST[Owner Name]=C_1[[#This Row],[OWNER NAME 1]], OWNER_LIST[Owner ORG], ""), IF(OWNER_LIST[Owner Name]=C_1[[#This Row],[OWNER NAME 2]], OWNER_LIST[Owner ORG], "")), "")} -> RPN | J39: Matteo Naldi | R39: =_xlfn.CONCAT(C_1[[#This Row],[ESCALATE]], "-",C_1[[#This Row],[Row_PM]]) -> - | S39: =_xlfn.CONCAT(C_1[[#This Row],[ESCALATE]], "-",C_1[[#This Row],[Notify_PM]]) -> -- | T39: =ROW() -> 39 | U39: =IF(C_1[[#This Row],[OWNER NAME 1]] = "", "", IF(_xlfn.XLOOKUP(C_1[[#This Row],[OWNER NAME 1]],OWNER_LIST[Owner Name], OWNER_LIST[Email], "") = "", "", _xlfn.XLOOKUP(C_1[[#This Row],[OWNER NAME 1]], OWNER_LIST[Owner Name], OWNER_LIST[Email], ""))) -> matteo.naldi@cmbcarpi.it | V39: =IF(C_1[[#This Row],[OWNER NAME 2]] = "", "", IF(_xlfn.XLOOKUP(C_1[[#This Row],[OWNER NAME 2]],OWNER_LIST[Owner Name], OWNER_LIST[Email], "") = "", "", _xlfn.XLOOKUP(C_1[[#This Row],[OWNER NAME 2]], OWNER_LIST[Owner Name], OWNER_LIST[Email], ""))) | W39: =$A$37 -> C1 | X39: =IF( OR( AND( NOT(ISBLANK(C_1[[#This Row],[DESCRIPTION - INFORMATION LOG]])), C_1[[#This Row],[DESCRIPTION - INFORMATION LOG]] <> "DESCRIPTION - INFORMATION LOG" ), NOT(ISBLANK(C_1[[#This Row],[ACTION REQUIRED]])) ), "Y", "N" ) -> Y
I40: {=IFERROR(_xlfn.TEXTJOIN(" / ", TRUE, IF(OWNER_LIST[Owner Name]=C_1[[#This Row],[OWNER NAME 1]], OWNER_LIST[Owner ORG], ""), IF(OWNER_LIST[Owner Name]=C_1[[#This Row],[OWNER NAME 2]], OWNER_LIST[Owner ORG], "")), "")} | R40: =_xlfn.CONCAT(C_1[[#This Row],[ESCALATE]], "-",C_1[[#This Row],[Row_PM]]) -> - | S40: =_xlfn.CONCAT(C_1[[#This Row],[ESCALATE]], "-",C_1[[#This Row],[Notify_PM]]) -> -- | T40: =ROW() -> 40 | U40: =IF(C_1[[#This Row],[OWNER NAME 1]] = "", "", IF(_xlfn.XLOOKUP(C_1[[#This Row],[OWNER NAME 1]],OWNER_LIST[Owner Name], OWNER_LIST[Email], "") = "", "", _xlfn.XLOOKUP(C_1[[#This Row],[OWNER NAME 1]], OWNER_LIST[Owner Name], OWNER_LIST[Email], ""))) | V40: =IF(C_1[[#This Row],[OWNER NAME 2]] = "", "", IF(_xlfn.XLOOKUP(C_1[[#This Row],[OWNER NAME 2]],OWNER_LIST[Owner Name], OWNER_LIST[Email], "") = "", "", _xlfn.XLOOKUP(C_1[[#This Row],[OWNER NAME 2]], OWNER_LIST[Owner Name], OWNER_LIST[Email], ""))) | W40: =$A$37 -> C1 | X40: =IF( OR( AND( NOT(ISBLANK(C_1[[#This Row],[DESCRIPTION - INFORMATION LOG]])), C_1[[#This Row],[DESCRIPTION - INFORMATION LOG]] <> "DESCRIPTION - INFORMATION LOG" ), NOT(ISBLANK(C_1[[#This Row],[ACTION REQUIRED]])) ), "Y", "N" ) -> N
A41: C_2 | B41: PRODUCTION | X41: =IF( OR( AND( NOT(ISBLANK(C_1[[#This Row],[DESCRIPTION - INFORMATION LOG]])), C_1[[#This Row],[DESCRIPTION - INFORMATION LOG]] <> "DESCRIPTION - INFORMATION LOG" ), NOT(ISBLANK(C_1[[#This Row],[ACTION REQUIRED]])) ), "Y", "N" ) -> N
A42: GENERAL | B42: SUBSTANTIAL COMPLETION | C42: INFO | D42: OPEN | E42: 18.02: Substantial completion is pending availability of EGGTELSA manpower on site 04.03 | F42: 25.02: Official S.C. 24.04 (no exclusion) 04.03: RPN to confirm which areas can be delivered on 24.04. | G42: High | H42: 46087 | I42: {=IFERROR(_xlfn.TEXTJOIN(" / ", TRUE, IF(OWNER_LIST[Owner Name]=C_1[[#This Row],[OWNER NAME 1]], OWNER_LIST[Owner ORG], ""), IF(OWNER_LIST[Owner Name]=C_1[[#This Row],[OWNER NAME 2]], OWNER_LIST[Owner ORG], "")), "")} -> RPN | J42: Simone Conti | R42: =_xlfn.CONCAT(C_1[[#This Row],[ESCALATE]], "-",C_1[[#This Row],[Row_PM]]) -> - | S42: =_xlfn.CONCAT(C_1[[#This Row],[ESCALATE]], "-",C_1[[#This Row],[Notify_PM]]) -> -- | T42: =ROW() -> 42 | U42: =IF(C_1[[#This Row],[OWNER NAME 1]] = "", "", IF(_xlfn.XLOOKUP(C_1[[#This Row],[OWNER NAME 1]],OWNER_LIST[Owner Name], OWNER_LIST[Email], "") = "", "", _xlfn.XLOOKUP(C_1[[#This Row],[OWNER NAME 1]], OWNER_LIST[Owner Name], OWNER_LIST[Email], ""))) -> simone.conti@cmbcarpi.it | V42: =IF(C_1[[#This Row],[OWNER NAME 2]] = "", "", IF(_xlfn.XLOOKUP(C_1[[#This Row],[OWNER NAME 2]],OWNER_LIST[Owner Name], OWNER_LIST[Email], "") = "", "", _xlfn.XLOOKUP(C_1[[#This Row],[OWNER NAME 2]], OWNER_LIST[Owner Name], OWNER_LIST[Email], ""))) | W42: =$A$37 -> C1 | X42: =IF( OR( AND( NOT(ISBLANK(C_1[[#This Row],[DESCRIPTION - INFORMATION LOG]])), C_1[[#This Row],[DESCRIPTION - INFORMATION LOG]] <> "DESCRIPTION - INFORMATION LOG" ), NOT(ISBLANK(C_1[[#This Row],[ACTION REQUIRED]])) ), "Y", "N" ) -> Y
A43: GENERAL | B43: SUBSTANTIAL COMPLETION | C43: INFO | D43: OPEN | E43: 07.05: Program have been updated with new S.C 16.12 TIA to 16.12 due to VAR 576 C6 / PRESS BAR / COUNCIL CHAMBER - NCF 334 salle C6 (see details bellow) - NCF 367 fire enclosure (see details bellow) | F43: 14.05: Complete the works by the end of July 05.11: RPN to update board | G43: High | I43: {=IFERROR(_xlfn.TEXTJOIN(" / ", TRUE, IF(OWNER_LIST[Owner Name]=C_1[[#This Row],[OWNER NAME 1]], OWNER_LIST[Owner ORG], ""), IF(OWNER_LIST[Owner Name]=C_1[[#This Row],[OWNER NAME 2]], OWNER_LIST[Owner ORG], "")), "")} | R43: =_xlfn.CONCAT(C_1[[#This Row],[ESCALATE]], "-",C_1[[#This Row],[Row_PM]]) -> - | S43: =_xlfn.CONCAT(C_1[[#This Row],[ESCALATE]], "-",C_1[[#This Row],[Notify_PM]]) -> -- | T43: =ROW() -> 43 | U43: =IF(C_1[[#This Row],[OWNER NAME 1]] = "", "", IF(_xlfn.XLOOKUP(C_1[[#This Row],[OWNER NAME 1]],OWNER_LIST[Owner Name], OWNER_LIST[Email], "") = "", "", _xlfn.XLOOKUP(C_1[[#This Row],[OWNER NAME 1]], OWNER_LIST[Owner Name], OWNER_LIST[Email], ""))) | V43: =IF(C_1[[#This Row],[OWNER NAME 2]] = "", "", IF(_xlfn.XLOOKUP(C_1[[#This Row],[OWNER NAME 2]],OWNER_LIST[Owner Name], OWNER_LIST[Email], "") = "", "", _xlfn.XLOOKUP(C_1[[#This Row],[OWNER NAME 2]], OWNER_LIST[Owner Name], OWNER_LIST[Email], ""))) | W43: =$A$37 -> C1 | X43: =IF( OR( AND( NOT(ISBLANK(C_1[[#This Row],[DESCRIPTION - INFORMATION LOG]])), C_1[[#This Row],[DESCRIPTION - INFORMATION LOG]] <> "DESCRIPTION - INFORMATION LOG" ), NOT(ISBLANK(C_1[[#This Row],[ACTION REQUIRED]])) ), "Y", "N" ) -> Y
A44: GENERAL | B44: PPC | C44: INFO | D44: OPEN | E44: 0.6 | F44: 22.10: Blocking topic: - Lack of resources (EGGTELSA LB2/ Council chamber) - EGGTELSA have 25# on site (C + B + S2) - 8 to 10 peoples missing - Electrical instalation at LB2 - EGL | G44: Low | I44: {=IFERROR(_xlfn.TEXTJOIN(" / ", TRUE, IF(OWNER_LIST[Owner Name]=C_1[[#This Row],[OWNER NAME 1]], OWNER_LIST[Owner ORG], ""), IF(OWNER_LIST[Owner Name]=C_1[[#This Row],[OWNER NAME 2]], OWNER_LIST[Owner ORG], "")), "")} | R44: =_xlfn.CONCAT(C_1[[#This Row],[ESCALATE]], "-",C_1[[#This Row],[Row_PM]]) -> - | S44: =_xlfn.CONCAT(C_1[[#This Row],[ESCALATE]], "-",C_1[[#This Row],[Notify_PM]]) -> -- | T44: =ROW() -> 44 | U44: =IF(C_1[[#This Row],[OWNER NAME 1]] = "", "", IF(_xlfn.XLOOKUP(C_1[[#This Row],[OWNER NAME 1]],OWNER_LIST[Owner Name], OWNER_LIST[Email], "") = "", "", _xlfn.XLOOKUP(C_1[[#This Row],[OWNER NAME 1]], OWNER_LIST[Owner Name], OWNER_LIST[Email], ""))) | V44: =IF(C_1[[#This Row],[OWNER NAME 2]] = "", "", IF(_xlfn.XLOOKUP(C_1[[#This Row],[OWNER NAME 2]],OWNER_LIST[Owner Name], OWNER_LIST[Email], "") = "", "", _xlfn.XLOOKUP(C_1[[#This Row],[OWNER NAME 2]], OWNER_LIST[Owner Name], OWNER_LIST[Email], ""))) | W44: =$A$37 -> C1 | X44: =IF( OR( AND( NOT(ISBLANK(C_1[[#This Row],[DESCRIPTION - INFORMATION LOG]])), C_1[[#This Row],[DESCRIPTION - INFORMATION LOG]] <> "DESCRIPTION - INFORMATION LOG" ), NOT(ISBLANK(C_1[[#This Row],[ACTION REQUIRED]])) ), "Y", "N" ) -> Y
A45: GENERAL | B45: POLICE DU FEU | C45: INFO | D45: OPEN | E45: 21.01: Planed 14.04 | G45: Medium | I45: {=IFERROR(_xlfn.TEXTJOIN(" / ", TRUE, IF(OWNER_LIST[Owner Name]=C_1[[#This Row],[OWNER NAME 1]], OWNER_LIST[Owner ORG], ""), IF(OWNER_LIST[Owner Name]=C_1[[#This Row],[OWNER NAME 2]], OWNER_LIST[Owner ORG], "")), "")} | R45: =_xlfn.CONCAT(C_1[[#This Row],[ESCALATE]], "-",C_1[[#This Row],[Row_PM]]) -> - | S45: =_xlfn.CONCAT(C_1[[#This Row],[ESCALATE]], "-",C_1[[#This Row],[Notify_PM]]) -> -- | T45: =ROW() -> 45 | U45: =IF(C_1[[#This Row],[OWNER NAME 1]] = "", "", IF(_xlfn.XLOOKUP(C_1[[#This Row],[OWNER NAME 1]],OWNER_LIST[Owner Name], OWNER_LIST[Email], "") = "", "", _xlfn.XLOOKUP(C_1[[#This Row],[OWNER NAME 1]], OWNER_LIST[Owner Name], OWNER_LIST[Email], ""))) | V45: =IF(C_1[[#This Row],[OWNER NAME 2]] = "", "", IF(_xlfn.XLOOKUP(C_1[[#This Row],[OWNER NAME 2]],OWNER_LIST[Owner Name], OWNER_LIST[Email], "") = "", "", _xlfn.XLOOKUP(C_1[[#This Row],[OWNER NAME 2]], OWNER_LIST[Owner Name], OWNER_LIST[Email], ""))) | W45: =$A$37 -> C1 | X45: =IF( OR( AND( NOT(ISBLANK(C_1[[#This Row],[DESCRIPTION - INFORMATION LOG]])), C_1[[#This Row],[DESCRIPTION - INFORMATION LOG]] <> "DESCRIPTION - INFORMATION LOG" ), NOT(ISBLANK(C_1[[#This Row],[ACTION REQUIRED]])) ), "Y", "N" ) -> Y
A46: GENERAL | B46: WINDOWS - NCF 382 (A-AB-C) | C46: ACTION | D46: OPEN | E46: 18.02: New quality topic has been issued concerning windows NCF 18.02: Powder coating is cracking. 24.02: NCF 382 has been raised +/- 40 windows afected. 25.02: Supplier visited site | F46: 25.02: RPN to organize site inspection with Manufacturer. +/- 03.03. | G46: TOP | H46: 46080 | I46: {=IFERROR(_xlfn.TEXTJOIN(" / ", TRUE, IF(OWNER_LIST[Owner Name]=C_1[[#This Row],[OWNER NAME 1]], OWNER_LIST[Owner ORG], ""), IF(OWNER_LIST[Owner Name]=C_1[[#This Row],[OWNER NAME 2]], OWNER_LIST[Owner ORG], "")), "")} -> RPN / SHP | J46: Davide Cirillo | K46: Didier Dequatre | R46: =_xlfn.CONCAT(C_1[[#This Row],[ESCALATE]], "-",C_1[[#This Row],[Row_PM]]) -> - | S46: =_xlfn.CONCAT(C_1[[#This Row],[ESCALATE]], "-",C_1[[#This Row],[Notify_PM]]) -> -- | T46: =ROW() -> 46 | U46: =IF(C_1[[#This Row],[OWNER NAME 1]] = "", "", IF(_xlfn.XLOOKUP(C_1[[#This Row],[OWNER NAME 1]],OWNER_LIST[Owner Name], OWNER_LIST[Email], "") = "", "", _xlfn.XLOOKUP(C_1[[#This Row],[OWNER NAME 1]], OWNER_LIST[Owner Name], OWNER_LIST[Email], ""))) -> davide.cirillo@cmbcarpi.it | V46: =IF(C_1[[#This Row],[OWNER NAME 2]] = "", "", IF(_xlfn.XLOOKUP(C_1[[#This Row],[OWNER NAME 2]],OWNER_LIST[Owner Name], OWNER_LIST[Email], "") = "", "", _xlfn.XLOOKUP(C_1[[#This Row],[OWNER NAME 2]], OWNER_LIST[Owner Name], OWNER_LIST[Email], ""))) -> didier.dequatre@un.org | W46: =$A$37 -> C1 | X46: =IF( OR( AND( NOT(ISBLANK(C_1[[#This Row],[DESCRIPTION - INFORMATION LOG]])), C_1[[#This Row],[DESCRIPTION - INFORMATION LOG]] <> "DESCRIPTION - INFORMATION LOG" ), NOT(ISBLANK(C_1[[#This Row],[ACTION REQUIRED]])) ), "Y", "N" ) -> Y
A47: DESIGN | B47: Phase 6 dwg As build dwg | C47: INFO | D47: OPEN | E47: 28.01: +/- 100 Phase 6 dwg with R&R status 16.02: As built dwg list has been submitted | F47: 04/03: SHP to assess | G47: Medium | H47: 46094 | I47: {=IFERROR(_xlfn.TEXTJOIN(" / ", TRUE, IF(OWNER_LIST[Owner Name]=C_1[[#This Row],[OWNER NAME 1]], OWNER_LIST[Owner ORG], ""), IF(OWNER_LIST[Owner Name]=C_1[[#This Row],[OWNER NAME 2]], OWNER_LIST[Owner ORG], "")), "")} -> SHP / SHP | J47: Donatella Rocca | K47: Jean-Mathieu Ferre | R47: =_xlfn.CONCAT(C_1[[#This Row],[ESCALATE]], "-",C_1[[#This Row],[Row_PM]]) -> - | S47: =_xlfn.CONCAT(C_1[[#This Row],[ESCALATE]], "-",C_1[[#This Row],[Notify_PM]]) -> -- | T47: =ROW() -> 47 | U47: =IF(C_1[[#This Row],[OWNER NAME 1]] = "", "", IF(_xlfn.XLOOKUP(C_1[[#This Row],[OWNER NAME 1]],OWNER_LIST[Owner Name], OWNER_LIST[Email], "") = "", "", _xlfn.XLOOKUP(C_1[[#This Row],[OWNER NAME 1]], OWNER_LIST[Owner Name], OWNER_LIST[Email], ""))) -> donatella.rocca@un.org | V47: =IF(C_1[[#This Row],[OWNER NAME 2]] = "", "", IF(_xlfn.XLOOKUP(C_1[[#This Row],[OWNER NAME 2]],OWNER_LIST[Owner Name], OWNER_LIST[Email], "") = "", "", _xlfn.XLOOKUP(C_1[[#This Row],[OWNER NAME 2]], OWNER_LIST[Owner Name], OWNER_LIST[Email], ""))) -> jean.ferre@un.org | W47: =$A$37 -> C1 | X47: =IF( OR( AND( NOT(ISBLANK(C_1[[#This Row],[DESCRIPTION - INFORMATION LOG]])), C_1[[#This Row],[DESCRIPTION - INFORMATION LOG]] <> "DESCRIPTION - INFORMATION LOG" ), NOT(ISBLANK(C_1[[#This Row],[ACTION REQUIRED]])) ), "Y", "N" ) -> Y
A48: GENERAL | B48: TCI - Follow-Up | C48: INFO | D48: OPEN | E48: 17.09: TCI pending RPN = 92 SOMBP = 0 SHP =1 | G48: Low | H48: 45811 | I48: {=IFERROR(_xlfn.TEXTJOIN(" / ", TRUE, IF(OWNER_LIST[Owner Name]=C_1[[#This Row],[OWNER NAME 1]], OWNER_LIST[Owner ORG], ""), IF(OWNER_LIST[Owner Name]=C_1[[#This Row],[OWNER NAME 2]], OWNER_LIST[Owner ORG], "")), "")} -> RPN | J48: Martina Maffioletti | R48: =_xlfn.CONCAT(C_1[[#This Row],[ESCALATE]], "-",C_1[[#This Row],[Row_PM]]) -> - | S48: =_xlfn.CONCAT(C_1[[#This Row],[ESCALATE]], "-",C_1[[#This Row],[Notify_PM]]) -> -- | T48: =ROW() -> 48 | U48: =IF(C_1[[#This Row],[OWNER NAME 1]] = "", "", IF(_xlfn.XLOOKUP(C_1[[#This Row],[OWNER NAME 1]],OWNER_LIST[Owner Name], OWNER_LIST[Email], "") = "", "", _xlfn.XLOOKUP(C_1[[#This Row],[OWNER NAME 1]], OWNER_LIST[Owner Name], OWNER_LIST[Email], ""))) -> martina.maffioletti@rpn-sa.ch | V48: =IF(C_1[[#This Row],[OWNER NAME 2]] = "", "", IF(_xlfn.XLOOKUP(C_1[[#This Row],[OWNER NAME 2]],OWNER_LIST[Owner Name], OWNER_LIST[Email], "") = "", "", _xlfn.XLOOKUP(C_1[[#This Row],[OWNER NAME 2]], OWNER_LIST[Owner Name], OWNER_LIST[Email], ""))) | W48: =$A$37 -> C1 | X48: =IF( OR( AND( NOT(ISBLANK(C_1[[#This Row],[DESCRIPTION - INFORMATION LOG]])), C_1[[#This Row],[DESCRIPTION - INFORMATION LOG]] <> "DESCRIPTION - INFORMATION LOG" ), NOT(ISBLANK(C_1[[#This Row],[ACTION REQUIRED]])) ), "Y", "N" ) -> Y
A49: GENERAL | B49: EGGTELSA | C49: ACTION | D49: OPEN | E49: EGGTELSA complains about 11 new INS / VAR impacting Substatial completion | F49: 28.01: RPN to present a syntesis of issues and impact on delay | G49: TOP | H49: 46057 | I49: {=IFERROR(_xlfn.TEXTJOIN(" / ", TRUE, IF(OWNER_LIST[Owner Name]=C_1[[#This Row],[OWNER NAME 1]], OWNER_LIST[Owner ORG], ""), IF(OWNER_LIST[Owner Name]=C_1[[#This Row],[OWNER NAME 2]], OWNER_LIST[Owner ORG], "")), "")} -> RPN | J49: Matteo Naldi | R49: =_xlfn.CONCAT(C_1[[#This Row],[ESCALATE]], "-",C_1[[#This Row],[Row_PM]]) -> - | S49: =_xlfn.CONCAT(C_1[[#This Row],[ESCALATE]], "-",C_1[[#This Row],[Notify_PM]]) -> -- | T49: =ROW() -> 49 | U49: =IF(C_1[[#This Row],[OWNER NAME 1]] = "", "", IF(_xlfn.XLOOKUP(C_1[[#This Row],[OWNER NAME 1]],OWNER_LIST[Owner Name], OWNER_LIST[Email], "") = "", "", _xlfn.XLOOKUP(C_1[[#This Row],[OWNER NAME 1]], OWNER_LIST[Owner Name], OWNER_LIST[Email], ""))) -> matteo.naldi@cmbcarpi.it | V49: =IF(C_1[[#This Row],[OWNER NAME 2]] = "", "", IF(_xlfn.XLOOKUP(C_1[[#This Row],[OWNER NAME 2]],OWNER_LIST[Owner Name], OWNER_LIST[Email], "") = "", "", _xlfn.XLOOKUP(C_1[[#This Row],[OWNER NAME 2]], OWNER_LIST[Owner Name], OWNER_LIST[Email], ""))) | W49: =$A$37 -> C1 | X49: =IF( OR( AND( NOT(ISBLANK(C_1[[#This Row],[DESCRIPTION - INFORMATION LOG]])), C_1[[#This Row],[DESCRIPTION - INFORMATION LOG]] <> "DESCRIPTION - INFORMATION LOG" ), NOT(ISBLANK(C_1[[#This Row],[ACTION REQUIRED]])) ), "Y", "N" ) -> Y
A50: GENERAL | B50: FIRE MATRIX | C50: INFO | D50: OPEN | E50: 03.12: meeting took place SBIS/ ENERGY MANAGEMENT 03.12: EGGTELSA needs 2month of works after Fire Matrix is approved 09.12: ENERGY MANAGEMENT provided info, pending SBIS 07.01: Fire Matrix have been uploaded on Pmweb, MEP approved as noted 14.01: Approved as noted (some doors missing) 17.02: FIRE MATRIX has been uploaded 21.02: phase.14 comments have been Uploaded. Status R&R (Minor comments, Technical issues are approved) | F50: 21.01: RPN/ SBIS to update per comments 28.01: RPN to submit 11.02: RPN to submit on 11.02 18.02: SOMBP/ SHP to update 23.02: RPN to assess +/- 05.03 | G50: TOP | H50: 46086 | I50: {=IFERROR(_xlfn.TEXTJOIN(" / ", TRUE, IF(OWNER_LIST[Owner Name]=C_1[[#This Row],[OWNER NAME 1]], OWNER_LIST[Owner ORG], ""), IF(OWNER_LIST[Owner Name]=C_1[[#This Row],[OWNER NAME 2]], OWNER_LIST[Owner ORG], "")), "")} -> RPN | J50: Federica Brunone | R50: =_xlfn.CONCAT(C_1[[#This Row],[ESCALATE]], "-",C_1[[#This Row],[Row_PM]]) -> - | S50: =_xlfn.CONCAT(C_1[[#This Row],[ESCALATE]], "-",C_1[[#This Row],[Notify_PM]]) -> -- | T50: =ROW() -> 50 | U50: =IF(C_1[[#This Row],[OWNER NAME 1]] = "", "", IF(_xlfn.XLOOKUP(C_1[[#This Row],[OWNER NAME 1]],OWNER_LIST[Owner Name], OWNER_LIST[Email], "") = "", "", _xlfn.XLOOKUP(C_1[[#This Row],[OWNER NAME 1]], OWNER_LIST[Owner Name], OWNER_LIST[Email], ""))) -> federica.brunone@cmbcarpi.it | V50: =IF(C_1[[#This Row],[OWNER NAME 2]] = "", "", IF(_xlfn.XLOOKUP(C_1[[#This Row],[OWNER NAME 2]],OWNER_LIST[Owner Name], OWNER_LIST[Email], "") = "", "", _xlfn.XLOOKUP(C_1[[#This Row],[OWNER NAME 2]], OWNER_LIST[Owner Name], OWNER_LIST[Email], ""))) | W50: =$A$37 -> C1 | X50: =IF( OR( AND( NOT(ISBLANK(C_1[[#This Row],[DESCRIPTION - INFORMATION LOG]])), C_1[[#This Row],[DESCRIPTION - INFORMATION LOG]] <> "DESCRIPTION - INFORMATION LOG" ), NOT(ISBLANK(C_1[[#This Row],[ACTION REQUIRED]])) ), "Y", "N" ) -> Y
A51: GENERAL | B51: FIRE HOSES | C51: ACTION | D51: OPEN | E51: 18.02: RPN instructed to PXT to reinstalled Fire hoses at Level 1 & 2 | F51: 18.02: Fire hoses to be T&C + certified PXT to submit report | G51: High | H51: 46142 | I51: {=IFERROR(_xlfn.TEXTJOIN(" / ", TRUE, IF(OWNER_LIST[Owner Name]=C_1[[#This Row],[OWNER NAME 1]], OWNER_LIST[Owner ORG], ""), IF(OWNER_LIST[Owner Name]=C_1[[#This Row],[OWNER NAME 2]], OWNER_LIST[Owner ORG], "")), "")} -> RPN / RPN | J51: Martina Maffioletti | K51: Amos Anderini | R51: =_xlfn.CONCAT(C_1[[#This Row],[ESCALATE]], "-",C_1[[#This Row],[Row_PM]]) -> - | S51: =_xlfn.CONCAT(C_1[[#This Row],[ESCALATE]], "-",C_1[[#This Row],[Notify_PM]]) -> -- | T51: =ROW() -> 51 | U51: =IF(C_1[[#This Row],[OWNER NAME 1]] = "", "", IF(_xlfn.XLOOKUP(C_1[[#This Row],[OWNER NAME 1]],OWNER_LIST[Owner Name], OWNER_LIST[Email], "") = "", "", _xlfn.XLOOKUP(C_1[[#This Row],[OWNER NAME 1]], OWNER_LIST[Owner Name], OWNER_LIST[Email], ""))) -> martina.maffioletti@rpn-sa.ch | V51: =IF(C_1[[#This Row],[OWNER NAME 2]] = "", "", IF(_xlfn.XLOOKUP(C_1[[#This Row],[OWNER NAME 2]],OWNER_LIST[Owner Name], OWNER_LIST[Email], "") = "", "", _xlfn.XLOOKUP(C_1[[#This Row],[OWNER NAME 2]], OWNER_LIST[Owner Name], OWNER_LIST[Email], ""))) -> amos.anderini@rpn-sa.ch | W51: =$A$37 -> C1 | X51: =IF( OR( AND( NOT(ISBLANK(C_1[[#This Row],[DESCRIPTION - INFORMATION LOG]])), C_1[[#This Row],[DESCRIPTION - INFORMATION LOG]] <> "DESCRIPTION - INFORMATION LOG" ), NOT(ISBLANK(C_1[[#This Row],[ACTION REQUIRED]])) ), "Y", "N" ) -> Y
A52: GENERAL | B52: FIRE FIGHTER ROUTE - INS 421 - VAR 536 | C52: ACTION | D52: OPEN | E52: 23.12: Step 4 has been submitted. 28.01: RPN planned completion of works by begining of march. | F52: 21.01: RPN to plan execution in AC and S1 | G52: High | H52: 46061 | I52: {=IFERROR(_xlfn.TEXTJOIN(" / ", TRUE, IF(OWNER_LIST[Owner Name]=C_1[[#This Row],[OWNER NAME 1]], OWNER_LIST[Owner ORG], ""), IF(OWNER_LIST[Owner Name]=C_1[[#This Row],[OWNER NAME 2]], OWNER_LIST[Owner ORG], "")), "")} -> RPN | J52: Matteo Naldi | R52: =_xlfn.CONCAT(C_1[[#This Row],[ESCALATE]], "-",C_1[[#This Row],[Row_PM]]) -> - | S52: =_xlfn.CONCAT(C_1[[#This Row],[ESCALATE]], "-",C_1[[#This Row],[Notify_PM]]) -> -- | T52: =ROW() -> 52 | U52: =IF(C_1[[#This Row],[OWNER NAME 1]] = "", "", IF(_xlfn.XLOOKUP(C_1[[#This Row],[OWNER NAME 1]],OWNER_LIST[Owner Name], OWNER_LIST[Email], "") = "", "", _xlfn.XLOOKUP(C_1[[#This Row],[OWNER NAME 1]], OWNER_LIST[Owner Name], OWNER_LIST[Email], ""))) -> matteo.naldi@cmbcarpi.it | V52: =IF(C_1[[#This Row],[OWNER NAME 2]] = "", "", IF(_xlfn.XLOOKUP(C_1[[#This Row],[OWNER NAME 2]],OWNER_LIST[Owner Name], OWNER_LIST[Email], "") = "", "", _xlfn.XLOOKUP(C_1[[#This Row],[OWNER NAME 2]], OWNER_LIST[Owner Name], OWNER_LIST[Email], ""))) | W52: =$A$37 -> C1 | X52: =IF( OR( AND( NOT(ISBLANK(C_1[[#This Row],[DESCRIPTION - INFORMATION LOG]])), C_1[[#This Row],[DESCRIPTION - INFORMATION LOG]] <> "DESCRIPTION - INFORMATION LOG" ), NOT(ISBLANK(C_1[[#This Row],[ACTION REQUIRED]])) ), "Y", "N" ) -> Y
A53: GENERAL | B53: VIGANO - Wooden Doors - Windows frame - Furnitures | C53: INFO | D53: OPEN | E53: 07.01: Windows frame to be completed by 19 of Jan 07.01: metal door to be delivered in January Acosutic doors in Febrary Wooden door delivery in March 21.01: VIGANO is back on site, window installation on going. EGGTELSA delayed by 1week 04.03: Doors delivery per VIGANO programme out of RPN control | F53: 18.02: Priorities : - A.13 (high risk) - CAR @LB01 - Salle C6 interpretor booth (Acoustic test) - UNTV (Acoustic test) - Corridors @ L05-L04-L03... - Offices & other rooms @ L05-L04-L03... - Salon Tcheque, Council chamber | G53: TOP | H53: 46086 | I53: {=IFERROR(_xlfn.TEXTJOIN(" / ", TRUE, IF(OWNER_LIST[Owner Name]=C_1[[#This Row],[OWNER NAME 1]], OWNER_LIST[Owner ORG], ""), IF(OWNER_LIST[Owner Name]=C_1[[#This Row],[OWNER NAME 2]], OWNER_LIST[Owner ORG], "")), "")} -> RPN / RPN | J53: Matteo Naldi | K53: Lorenzo Barnini | R53: =_xlfn.CONCAT(C_1[[#This Row],[ESCALATE]], "-",C_1[[#This Row],[Row_PM]]) -> - | S53: =_xlfn.CONCAT(C_1[[#This Row],[ESCALATE]], "-",C_1[[#This Row],[Notify_PM]]) -> -- | T53: =ROW() -> 53 | U53: =IF(C_1[[#This Row],[OWNER NAME 1]] = "", "", IF(_xlfn.XLOOKUP(C_1[[#This Row],[OWNER NAME 1]],OWNER_LIST[Owner Name], OWNER_LIST[Email], "") = "", "", _xlfn.XLOOKUP(C_1[[#This Row],[OWNER NAME 1]], OWNER_LIST[Owner Name], OWNER_LIST[Email], ""))) -> matteo.naldi@cmbcarpi.it | V53: =IF(C_1[[#This Row],[OWNER NAME 2]] = "", "", IF(_xlfn.XLOOKUP(C_1[[#This Row],[OWNER NAME 2]],OWNER_LIST[Owner Name], OWNER_LIST[Email], "") = "", "", _xlfn.XLOOKUP(C_1[[#This Row],[OWNER NAME 2]], OWNER_LIST[Owner Name], OWNER_LIST[Email], ""))) -> lorenzo.barnini@cmbcarpi.it | W53: =$A$37 -> C1 | X53: =IF( OR( AND( NOT(ISBLANK(C_1[[#This Row],[DESCRIPTION - INFORMATION LOG]])), C_1[[#This Row],[DESCRIPTION - INFORMATION LOG]] <> "DESCRIPTION - INFORMATION LOG" ), NOT(ISBLANK(C_1[[#This Row],[ACTION REQUIRED]])) ), "Y", "N" ) -> Y
A54: GENERAL | B54: LIFTS - Planning | C54: ACTION | D54: OPEN | E54: 02.10: INTERCOM to be GRANDSTREAM as approved on dwg. 26.11: EGL confirm T&C of lift 6 by end of February 07.01: EGL will be back on site 26.01. works to be completed mid of February. 04.03: RPN has been out of site for 2 weeks | F54: 03.09: SHP to comment 10.09: RPN to submit platform dwg 24.09: Preparatory works to start 02.10 07.01: RPN to update planning | G54: High | H54: 45932 | I54: {=IFERROR(_xlfn.TEXTJOIN(" / ", TRUE, IF(OWNER_LIST[Owner Name]=C_1[[#This Row],[OWNER NAME 1]], OWNER_LIST[Owner ORG], ""), IF(OWNER_LIST[Owner Name]=C_1[[#This Row],[OWNER NAME 2]], OWNER_LIST[Owner ORG], "")), "")} -> RPN | J54: Gianluca Crippa | R54: =_xlfn.CONCAT(C_1[[#This Row],[ESCALATE]], "-",C_1[[#This Row],[Row_PM]]) -> - | S54: =_xlfn.CONCAT(C_1[[#This Row],[ESCALATE]], "-",C_1[[#This Row],[Notify_PM]]) -> -- | T54: =ROW() -> 54 | U54: =IF(C_1[[#This Row],[OWNER NAME 1]] = "", "", IF(_xlfn.XLOOKUP(C_1[[#This Row],[OWNER NAME 1]],OWNER_LIST[Owner Name], OWNER_LIST[Email], "") = "", "", _xlfn.XLOOKUP(C_1[[#This Row],[OWNER NAME 1]], OWNER_LIST[Owner Name], OWNER_LIST[Email], ""))) -> gianluca.crippa@rpn-sa.ch | V54: =IF(C_1[[#This Row],[OWNER NAME 2]] = "", "", IF(_xlfn.XLOOKUP(C_1[[#This Row],[OWNER NAME 2]],OWNER_LIST[Owner Name], OWNER_LIST[Email], "") = "", "", _xlfn.XLOOKUP(C_1[[#This Row],[OWNER NAME 2]], OWNER_LIST[Owner Name], OWNER_LIST[Email], ""))) | W54: =$A$37 -> C1 | X54: =IF( OR( AND( NOT(ISBLANK(C_1[[#This Row],[DESCRIPTION - INFORMATION LOG]])), C_1[[#This Row],[DESCRIPTION - INFORMATION LOG]] <> "DESCRIPTION - INFORMATION LOG" ), NOT(ISBLANK(C_1[[#This Row],[ACTION REQUIRED]])) ), "Y", "N" ) -> Y
A55: LIFTS | B55: LIFT 5, 6, 23, Platform C6, C5 | C55: ACTION | D55: OPEN | E55: 17.12: Lift 6 strip out completed 14.01: instalation to start 26.01 26.01: MAS has been R&R | F55: 28.01: Works started. Material for lift has been received. 11.02: RPN to check if Platform C5 is working | G55: TOP | H55: 46071 | I55: {=IFERROR(_xlfn.TEXTJOIN(" / ", TRUE, IF(OWNER_LIST[Owner Name]=C_1[[#This Row],[OWNER NAME 1]], OWNER_LIST[Owner ORG], ""), IF(OWNER_LIST[Owner Name]=C_1[[#This Row],[OWNER NAME 2]], OWNER_LIST[Owner ORG], "")), "")} -> RPN | J55: Matteo Naldi | R55: =_xlfn.CONCAT(C_1[[#This Row],[ESCALATE]], "-",C_1[[#This Row],[Row_PM]]) -> - | S55: =_xlfn.CONCAT(C_1[[#This Row],[ESCALATE]], "-",C_1[[#This Row],[Notify_PM]]) -> -- | T55: =ROW() -> 55 | U55: =IF(C_1[[#This Row],[OWNER NAME 1]] = "", "", IF(_xlfn.XLOOKUP(C_1[[#This Row],[OWNER NAME 1]],OWNER_LIST[Owner Name], OWNER_LIST[Email], "") = "", "", _xlfn.XLOOKUP(C_1[[#This Row],[OWNER NAME 1]], OWNER_LIST[Owner Name], OWNER_LIST[Email], ""))) -> matteo.naldi@cmbcarpi.it | V55: =IF(C_1[[#This Row],[OWNER NAME 2]] = "", "", IF(_xlfn.XLOOKUP(C_1[[#This Row],[OWNER NAME 2]],OWNER_LIST[Owner Name], OWNER_LIST[Email], "") = "", "", _xlfn.XLOOKUP(C_1[[#This Row],[OWNER NAME 2]], OWNER_LIST[Owner Name], OWNER_LIST[Email], ""))) | W55: =$A$37 -> C1 | X55: =IF( OR( AND( NOT(ISBLANK(C_1[[#This Row],[DESCRIPTION - INFORMATION LOG]])), C_1[[#This Row],[DESCRIPTION - INFORMATION LOG]] <> "DESCRIPTION - INFORMATION LOG" ), NOT(ISBLANK(C_1[[#This Row],[ACTION REQUIRED]])) ), "Y", "N" ) -> Y
A56: EMERGENCY LIGHT | B56: VAR 221 | C56: ACTION | D56: OPEN | E56: 26.11: VAR was determined in summer 2024 Battery (Coffret Aprotec) have not been ordered (6 weeks lead time) No time impact will be accepted 19.01: EGGTELSA is anylising qty issues 04.02: RPN submitted comments 09.02: G&T submitted assessment | F56: 04.02: G&T to assess 11.02: RPN to assess, 4 irelevant elements in balance. SHP to issue step 4 | G56: TOP | H56: 46064 | I56: {=IFERROR(_xlfn.TEXTJOIN(" / ", TRUE, IF(OWNER_LIST[Owner Name]=C_1[[#This Row],[OWNER NAME 1]], OWNER_LIST[Owner ORG], ""), IF(OWNER_LIST[Owner Name]=C_1[[#This Row],[OWNER NAME 2]], OWNER_LIST[Owner ORG], "")), "")} -> G&T | J56: Clare O'Malley | R56: =_xlfn.CONCAT(C_1[[#This Row],[ESCALATE]], "-",C_1[[#This Row],[Row_PM]]) -> - | S56: =_xlfn.CONCAT(C_1[[#This Row],[ESCALATE]], "-",C_1[[#This Row],[Notify_PM]]) -> -- | T56: =ROW() -> 56 | U56: =IF(C_1[[#This Row],[OWNER NAME 1]] = "", "", IF(_xlfn.XLOOKUP(C_1[[#This Row],[OWNER NAME 1]],OWNER_LIST[Owner Name], OWNER_LIST[Email], "") = "", "", _xlfn.XLOOKUP(C_1[[#This Row],[OWNER NAME 1]], OWNER_LIST[Owner Name], OWNER_LIST[Email], ""))) -> c.omalley@gardiner.com | V56: =IF(C_1[[#This Row],[OWNER NAME 2]] = "", "", IF(_xlfn.XLOOKUP(C_1[[#This Row],[OWNER NAME 2]],OWNER_LIST[Owner Name], OWNER_LIST[Email], "") = "", "", _xlfn.XLOOKUP(C_1[[#This Row],[OWNER NAME 2]], OWNER_LIST[Owner Name], OWNER_LIST[Email], ""))) | W56: =$A$37 -> C1 | X56: =IF( OR( AND( NOT(ISBLANK(C_1[[#This Row],[DESCRIPTION - INFORMATION LOG]])), C_1[[#This Row],[DESCRIPTION - INFORMATION LOG]] <> "DESCRIPTION - INFORMATION LOG" ), NOT(ISBLANK(C_1[[#This Row],[ACTION REQUIRED]])) ), "Y", "N" ) -> Y
A57: FIRE CURTAINS | B57: FIRE CURTAINS (8#) - OIBT | C57: ACTION | D57: OPEN | E57: 26.11: Fire curtains (8#) are critical for OIBT (linked to UPS) 07.01: Fire curtains installation to start 12.01 14.01: Fire curtains have not been delivered 11.02: Installation started at salon tcheque 18.02: other Fire curtain to be delivered 02.03. 2 days of work per curtain x 2 teams 04.03: to arrvie 05.03 | F57: 14.01: RPN to confirm delivery of fire curtains 21.01: RPN to confirm delivery of fire curtains 11.02: All curtain to be delivered 02.03 - RPN to confirm planning | G57: High | H57: 46050 | I57: {=IFERROR(_xlfn.TEXTJOIN(" / ", TRUE, IF(OWNER_LIST[Owner Name]=C_1[[#This Row],[OWNER NAME 1]], OWNER_LIST[Owner ORG], ""), IF(OWNER_LIST[Owner Name]=C_1[[#This Row],[OWNER NAME 2]], OWNER_LIST[Owner ORG], "")), "")} -> RPN / RPN | J57: Matteo Naldi | K57: Simone Conti | R57: =_xlfn.CONCAT(C_1[[#This Row],[ESCALATE]], "-",C_1[[#This Row],[Row_PM]]) -> - | S57: =_xlfn.CONCAT(C_1[[#This Row],[ESCALATE]], "-",C_1[[#This Row],[Notify_PM]]) -> -- | T57: =ROW() -> 57 | U57: =IF(C_1[[#This Row],[OWNER NAME 1]] = "", "", IF(_xlfn.XLOOKUP(C_1[[#This Row],[OWNER NAME 1]],OWNER_LIST[Owner Name], OWNER_LIST[Email], "") = "", "", _xlfn.XLOOKUP(C_1[[#This Row],[OWNER NAME 1]], OWNER_LIST[Owner Name], OWNER_LIST[Email], ""))) -> matteo.naldi@cmbcarpi.it | V57: =IF(C_1[[#This Row],[OWNER NAME 2]] = "", "", IF(_xlfn.XLOOKUP(C_1[[#This Row],[OWNER NAME 2]],OWNER_LIST[Owner Name], OWNER_LIST[Email], "") = "", "", _xlfn.XLOOKUP(C_1[[#This Row],[OWNER NAME 2]], OWNER_LIST[Owner Name], OWNER_LIST[Email], ""))) -> simone.conti@cmbcarpi.it | W57: =$A$37 -> C1 | X57: =IF( OR( AND( NOT(ISBLANK(C_1[[#This Row],[DESCRIPTION - INFORMATION LOG]])), C_1[[#This Row],[DESCRIPTION - INFORMATION LOG]] <> "DESCRIPTION - INFORMATION LOG" ), NOT(ISBLANK(C_1[[#This Row],[ACTION REQUIRED]])) ), "Y", "N" ) -> Y
A58: L05-L03 | B58: Displays in meeting rooms - VAR 478 | C58: ACTION | D58: OPEN | E58: 25.02: IT works to be completed. 25.02: some TV to be delivered. 04.03: | F58: 25.02: VAR 478 to be updated (TV size 65" = 75") 04.03: SHP to issue Revised step 4 - G&T to assess | G58: High | H58: 46087 | I58: {=IFERROR(_xlfn.TEXTJOIN(" / ", TRUE, IF(OWNER_LIST[Owner Name]=C_1[[#This Row],[OWNER NAME 1]], OWNER_LIST[Owner ORG], ""), IF(OWNER_LIST[Owner Name]=C_1[[#This Row],[OWNER NAME 2]], OWNER_LIST[Owner ORG], "")), "")} -> G&T | J58: Clare O'Malley | R58: =_xlfn.CONCAT(C_1[[#This Row],[ESCALATE]], "-",C_1[[#This Row],[Row_PM]]) -> - | S58: =_xlfn.CONCAT(C_1[[#This Row],[ESCALATE]], "-",C_1[[#This Row],[Notify_PM]]) -> -- | T58: =ROW() -> 58 | U58: =IF(C_1[[#This Row],[OWNER NAME 1]] = "", "", IF(_xlfn.XLOOKUP(C_1[[#This Row],[OWNER NAME 1]],OWNER_LIST[Owner Name], OWNER_LIST[Email], "") = "", "", _xlfn.XLOOKUP(C_1[[#This Row],[OWNER NAME 1]], OWNER_LIST[Owner Name], OWNER_LIST[Email], ""))) -> c.omalley@gardiner.com | V58: =IF(C_1[[#This Row],[OWNER NAME 2]] = "", "", IF(_xlfn.XLOOKUP(C_1[[#This Row],[OWNER NAME 2]],OWNER_LIST[Owner Name], OWNER_LIST[Email], "") = "", "", _xlfn.XLOOKUP(C_1[[#This Row],[OWNER NAME 2]], OWNER_LIST[Owner Name], OWNER_LIST[Email], ""))) | W58: =$A$37 -> C1 | X58: =IF( OR( AND( NOT(ISBLANK(C_1[[#This Row],[DESCRIPTION - INFORMATION LOG]])), C_1[[#This Row],[DESCRIPTION - INFORMATION LOG]] <> "DESCRIPTION - INFORMATION LOG" ), NOT(ISBLANK(C_1[[#This Row],[ACTION REQUIRED]])) ), "Y", "N" ) -> Y
A59: L05 | B59: WIFI | C59: ACTION | D59: OPEN | E59: 30.09: Subcontractor is comming twice a year on site. mitigation action have been required following physical site survey. | F59: 30.09: Based on predictive site survey status R&R. New simulation to be run. 10.11: RPN consultant to run physical survey together with ICTS and modify WAPS configuration on the spots until the physical survey is agreed. | G59: High | H59: 45940 | I59: {=IFERROR(_xlfn.TEXTJOIN(" / ", TRUE, IF(OWNER_LIST[Owner Name]=C_1[[#This Row],[OWNER NAME 1]], OWNER_LIST[Owner ORG], ""), IF(OWNER_LIST[Owner Name]=C_1[[#This Row],[OWNER NAME 2]], OWNER_LIST[Owner ORG], "")), "")} -> SHP / SHP | J59: Dragos Ionescu | K59: Jean-Mathieu Ferre | R59: =_xlfn.CONCAT(C_1[[#This Row],[ESCALATE]], "-",C_1[[#This Row],[Row_PM]]) -> - | S59: =_xlfn.CONCAT(C_1[[#This Row],[ESCALATE]], "-",C_1[[#This Row],[Notify_PM]]) -> -- | T59: =ROW() -> 59 | U59: =IF(C_1[[#This Row],[OWNER NAME 1]] = "", "", IF(_xlfn.XLOOKUP(C_1[[#This Row],[OWNER NAME 1]],OWNER_LIST[Owner Name], OWNER_LIST[Email], "") = "", "", _xlfn.XLOOKUP(C_1[[#This Row],[OWNER NAME 1]], OWNER_LIST[Owner Name], OWNER_LIST[Email], ""))) -> ionescud@un.org | V59: =IF(C_1[[#This Row],[OWNER NAME 2]] = "", "", IF(_xlfn.XLOOKUP(C_1[[#This Row],[OWNER NAME 2]],OWNER_LIST[Owner Name], OWNER_LIST[Email], "") = "", "", _xlfn.XLOOKUP(C_1[[#This Row],[OWNER NAME 2]], OWNER_LIST[Owner Name], OWNER_LIST[Email], ""))) -> jean.ferre@un.org | W59: =$A$37 -> C1 | X59: =IF( OR( AND( NOT(ISBLANK(C_1[[#This Row],[DESCRIPTION - INFORMATION LOG]])), C_1[[#This Row],[DESCRIPTION - INFORMATION LOG]] <> "DESCRIPTION - INFORMATION LOG" ), NOT(ISBLANK(C_1[[#This Row],[ACTION REQUIRED]])) ), "Y", "N" ) -> Y
A60: L04 | B60: MEETING ROOM L05 - VAR 659 - Obsolete luminaires | C60: ACTION | D60: OPEN | E60: 25.02: MAS of new Luminaires to be approved 04.03: | F60: 04.03: SOMBP/ SHP to assess is luminaire can be descoped 09.03: SOMBP to issue VAR to descope luminaire | G60: High | H60: 46079 | I60: {=IFERROR(_xlfn.TEXTJOIN(" / ", TRUE, IF(OWNER_LIST[Owner Name]=C_1[[#This Row],[OWNER NAME 1]], OWNER_LIST[Owner ORG], ""), IF(OWNER_LIST[Owner Name]=C_1[[#This Row],[OWNER NAME 2]], OWNER_LIST[Owner ORG], "")), "")} -> SOMBP | J60: Cedric Erard | R60: =_xlfn.CONCAT(C_1[[#This Row],[ESCALATE]], "-",C_1[[#This Row],[Row_PM]]) -> - | S60: =_xlfn.CONCAT(C_1[[#This Row],[ESCALATE]], "-",C_1[[#This Row],[Notify_PM]]) -> -- | T60: =ROW() -> 60 | U60: =IF(C_1[[#This Row],[OWNER NAME 1]] = "", "", IF(_xlfn.XLOOKUP(C_1[[#This Row],[OWNER NAME 1]],OWNER_LIST[Owner Name], OWNER_LIST[Email], "") = "", "", _xlfn.XLOOKUP(C_1[[#This Row],[OWNER NAME 1]], OWNER_LIST[Owner Name], OWNER_LIST[Email], ""))) -> ce@erard.biz | V60: =IF(C_1[[#This Row],[OWNER NAME 2]] = "", "", IF(_xlfn.XLOOKUP(C_1[[#This Row],[OWNER NAME 2]],OWNER_LIST[Owner Name], OWNER_LIST[Email], "") = "", "", _xlfn.XLOOKUP(C_1[[#This Row],[OWNER NAME 2]], OWNER_LIST[Owner Name], OWNER_LIST[Email], ""))) | W60: =$A$37 -> C1 | X60: =IF( OR( AND( NOT(ISBLANK(C_1[[#This Row],[DESCRIPTION - INFORMATION LOG]])), C_1[[#This Row],[DESCRIPTION - INFORMATION LOG]] <> "DESCRIPTION - INFORMATION LOG" ), NOT(ISBLANK(C_1[[#This Row],[ACTION REQUIRED]])) ), "Y", "N" ) -> Y
A61: L01 | B61: SALON TCHEQUE - Works | C61: INFO | D61: OPEN | E61: 07.01: Existing panel can be maintained EGGTELSA is working in the BOH area 14.01: Fire curtains have not been received as planned. 04.02: Activities are longer than expected. 18.02: Fire curtains has been installed | G61: TOP | H61: 46063 | I61: {=IFERROR(_xlfn.TEXTJOIN(" / ", TRUE, IF(OWNER_LIST[Owner Name]=C_1[[#This Row],[OWNER NAME 1]], OWNER_LIST[Owner ORG], ""), IF(OWNER_LIST[Owner Name]=C_1[[#This Row],[OWNER NAME 2]], OWNER_LIST[Owner ORG], "")), "")} -> RPN | J61: Matteo Naldi | R61: =_xlfn.CONCAT(C_1[[#This Row],[ESCALATE]], "-",C_1[[#This Row],[Row_PM]]) -> - | S61: =_xlfn.CONCAT(C_1[[#This Row],[ESCALATE]], "-",C_1[[#This Row],[Notify_PM]]) -> -- | T61: =ROW() -> 61 | U61: =IF(C_1[[#This Row],[OWNER NAME 1]] = "", "", IF(_xlfn.XLOOKUP(C_1[[#This Row],[OWNER NAME 1]],OWNER_LIST[Owner Name], OWNER_LIST[Email], "") = "", "", _xlfn.XLOOKUP(C_1[[#This Row],[OWNER NAME 1]], OWNER_LIST[Owner Name], OWNER_LIST[Email], ""))) -> matteo.naldi@cmbcarpi.it | V61: =IF(C_1[[#This Row],[OWNER NAME 2]] = "", "", IF(_xlfn.XLOOKUP(C_1[[#This Row],[OWNER NAME 2]],OWNER_LIST[Owner Name], OWNER_LIST[Email], "") = "", "", _xlfn.XLOOKUP(C_1[[#This Row],[OWNER NAME 2]], OWNER_LIST[Owner Name], OWNER_LIST[Email], ""))) | W61: =$A$37 -> C1 | X61: =IF( OR( AND( NOT(ISBLANK(C_1[[#This Row],[DESCRIPTION - INFORMATION LOG]])), C_1[[#This Row],[DESCRIPTION - INFORMATION LOG]] <> "DESCRIPTION - INFORMATION LOG" ), NOT(ISBLANK(C_1[[#This Row],[ACTION REQUIRED]])) ), "Y", "N" ) -> Y
A62: L01 | B62: SALON TCHEQUE - Back door entrance @L02 | C62: ACTION | D62: OPEN | E62: 23.02: Back door is an emergency exit. See VIGANO above | G62: High | H62: 46101 | I62: {=IFERROR(_xlfn.TEXTJOIN(" / ", TRUE, IF(OWNER_LIST[Owner Name]=C_1[[#This Row],[OWNER NAME 1]], OWNER_LIST[Owner ORG], ""), IF(OWNER_LIST[Owner Name]=C_1[[#This Row],[OWNER NAME 2]], OWNER_LIST[Owner ORG], "")), "")} -> RPN | J62: Matteo Naldi | R62: =_xlfn.CONCAT(C_1[[#This Row],[ESCALATE]], "-",C_1[[#This Row],[Row_PM]]) -> - | S62: =_xlfn.CONCAT(C_1[[#This Row],[ESCALATE]], "-",C_1[[#This Row],[Notify_PM]]) -> -- | T62: =ROW() -> 62 | U62: =IF(C_1[[#This Row],[OWNER NAME 1]] = "", "", IF(_xlfn.XLOOKUP(C_1[[#This Row],[OWNER NAME 1]],OWNER_LIST[Owner Name], OWNER_LIST[Email], "") = "", "", _xlfn.XLOOKUP(C_1[[#This Row],[OWNER NAME 1]], OWNER_LIST[Owner Name], OWNER_LIST[Email], ""))) -> matteo.naldi@cmbcarpi.it | V62: =IF(C_1[[#This Row],[OWNER NAME 2]] = "", "", IF(_xlfn.XLOOKUP(C_1[[#This Row],[OWNER NAME 2]],OWNER_LIST[Owner Name], OWNER_LIST[Email], "") = "", "", _xlfn.XLOOKUP(C_1[[#This Row],[OWNER NAME 2]], OWNER_LIST[Owner Name], OWNER_LIST[Email], ""))) | W62: =$A$37 -> C1 | X62: =IF( OR( AND( NOT(ISBLANK(C_1[[#This Row],[DESCRIPTION - INFORMATION LOG]])), C_1[[#This Row],[DESCRIPTION - INFORMATION LOG]] <> "DESCRIPTION - INFORMATION LOG" ), NOT(ISBLANK(C_1[[#This Row],[ACTION REQUIRED]])) ), "Y", "N" ) -> Y
A63: L01 | B63: SALON TCHEQUE - Temporary protection | C63: INFO | D63: OPEN | E63: 28.01: All protection to furnitures ansd floor have been removed 24.02: Protection have been installed | F63: 28.01: RPN to clean and protect | G63: High | H63: 46101 | I63: {=IFERROR(_xlfn.TEXTJOIN(" / ", TRUE, IF(OWNER_LIST[Owner Name]=C_1[[#This Row],[OWNER NAME 1]], OWNER_LIST[Owner ORG], ""), IF(OWNER_LIST[Owner Name]=C_1[[#This Row],[OWNER NAME 2]], OWNER_LIST[Owner ORG], "")), "")} -> RPN | J63: Matteo Naldi | R63: =_xlfn.CONCAT(C_1[[#This Row],[ESCALATE]], "-",C_1[[#This Row],[Row_PM]]) -> - | S63: =_xlfn.CONCAT(C_1[[#This Row],[ESCALATE]], "-",C_1[[#This Row],[Notify_PM]]) -> -- | T63: =ROW() -> 63 | U63: =IF(C_1[[#This Row],[OWNER NAME 1]] = "", "", IF(_xlfn.XLOOKUP(C_1[[#This Row],[OWNER NAME 1]],OWNER_LIST[Owner Name], OWNER_LIST[Email], "") = "", "", _xlfn.XLOOKUP(C_1[[#This Row],[OWNER NAME 1]], OWNER_LIST[Owner Name], OWNER_LIST[Email], ""))) -> matteo.naldi@cmbcarpi.it | V63: =IF(C_1[[#This Row],[OWNER NAME 2]] = "", "", IF(_xlfn.XLOOKUP(C_1[[#This Row],[OWNER NAME 2]],OWNER_LIST[Owner Name], OWNER_LIST[Email], "") = "", "", _xlfn.XLOOKUP(C_1[[#This Row],[OWNER NAME 2]], OWNER_LIST[Owner Name], OWNER_LIST[Email], ""))) | W63: =$A$37 -> C1 | X63: =IF( OR( AND( NOT(ISBLANK(C_1[[#This Row],[DESCRIPTION - INFORMATION LOG]])), C_1[[#This Row],[DESCRIPTION - INFORMATION LOG]] <> "DESCRIPTION - INFORMATION LOG" ), NOT(ISBLANK(C_1[[#This Row],[ACTION REQUIRED]])) ), "Y", "N" ) -> Y
A64: L01 | B64: SALON TCHEQUE - Relamping | C64: ACTION | D64: OPEN | E64: 23.02: Light Tº are diferent (new and old) | F64: 23.02: SHP to raise TCI | G64: High | H64: 46078 | I64: {=IFERROR(_xlfn.TEXTJOIN(" / ", TRUE, IF(OWNER_LIST[Owner Name]=C_1[[#This Row],[OWNER NAME 1]], OWNER_LIST[Owner ORG], ""), IF(OWNER_LIST[Owner Name]=C_1[[#This Row],[OWNER NAME 2]], OWNER_LIST[Owner ORG], "")), "")} -> SHP | J64: Maximilien Montanaro | R64: =_xlfn.CONCAT(C_1[[#This Row],[ESCALATE]], "-",C_1[[#This Row],[Row_PM]]) -> - | S64: =_xlfn.CONCAT(C_1[[#This Row],[ESCALATE]], "-",C_1[[#This Row],[Notify_PM]]) -> -- | T64: =ROW() -> 64 | U64: =IF(C_1[[#This Row],[OWNER NAME 1]] = "", "", IF(_xlfn.XLOOKUP(C_1[[#This Row],[OWNER NAME 1]],OWNER_LIST[Owner Name], OWNER_LIST[Email], "") = "", "", _xlfn.XLOOKUP(C_1[[#This Row],[OWNER NAME 1]], OWNER_LIST[Owner Name], OWNER_LIST[Email], ""))) -> maximilien.montanaro@un.org | V64: =IF(C_1[[#This Row],[OWNER NAME 2]] = "", "", IF(_xlfn.XLOOKUP(C_1[[#This Row],[OWNER NAME 2]],OWNER_LIST[Owner Name], OWNER_LIST[Email], "") = "", "", _xlfn.XLOOKUP(C_1[[#This Row],[OWNER NAME 2]], OWNER_LIST[Owner Name], OWNER_LIST[Email], ""))) | W64: =$A$37 -> C1 | X64: =IF( OR( AND( NOT(ISBLANK(C_1[[#This Row],[DESCRIPTION - INFORMATION LOG]])), C_1[[#This Row],[DESCRIPTION - INFORMATION LOG]] <> "DESCRIPTION - INFORMATION LOG" ), NOT(ISBLANK(C_1[[#This Row],[ACTION REQUIRED]])) ), "Y", "N" ) -> Y
A65: L01 | B65: SALON FRANCAIS - Wall mounted lighting | C65: ACTION | D65: OPEN | E65: Check if wall mounted lights are in good conditions. 30.10: Assessment was partially made on site, 2 glass broken. | F65: 30.09: Works to be assessed during site visit 03.11: Condition report to be checked, (=> NCF / INS?) Second assessment to be run | G65: Medium | H65: 45966 | I65: {=IFERROR(_xlfn.TEXTJOIN(" / ", TRUE, IF(OWNER_LIST[Owner Name]=C_1[[#This Row],[OWNER NAME 1]], OWNER_LIST[Owner ORG], ""), IF(OWNER_LIST[Owner Name]=C_1[[#This Row],[OWNER NAME 2]], OWNER_LIST[Owner ORG], "")), "")} -> SHP / RPN | J65: Maximilien Montanaro | K65: Matteo Naldi | R65: =_xlfn.CONCAT(C_1[[#This Row],[ESCALATE]], "-",C_1[[#This Row],[Row_PM]]) -> - | S65: =_xlfn.CONCAT(C_1[[#This Row],[ESCALATE]], "-",C_1[[#This Row],[Notify_PM]]) -> -- | T65: =ROW() -> 65 | U65: =IF(C_1[[#This Row],[OWNER NAME 1]] = "", "", IF(_xlfn.XLOOKUP(C_1[[#This Row],[OWNER NAME 1]],OWNER_LIST[Owner Name], OWNER_LIST[Email], "") = "", "", _xlfn.XLOOKUP(C_1[[#This Row],[OWNER NAME 1]], OWNER_LIST[Owner Name], OWNER_LIST[Email], ""))) -> maximilien.montanaro@un.org | V65: =IF(C_1[[#This Row],[OWNER NAME 2]] = "", "", IF(_xlfn.XLOOKUP(C_1[[#This Row],[OWNER NAME 2]],OWNER_LIST[Owner Name], OWNER_LIST[Email], "") = "", "", _xlfn.XLOOKUP(C_1[[#This Row],[OWNER NAME 2]], OWNER_LIST[Owner Name], OWNER_LIST[Email], ""))) -> matteo.naldi@cmbcarpi.it | W65: =$A$37 -> C1 | X65: =IF( OR( AND( NOT(ISBLANK(C_1[[#This Row],[DESCRIPTION - INFORMATION LOG]])), C_1[[#This Row],[DESCRIPTION - INFORMATION LOG]] <> "DESCRIPTION - INFORMATION LOG" ), NOT(ISBLANK(C_1[[#This Row],[ACTION REQUIRED]])) ), "Y", "N" ) -> Y
A66: L01 | B66: SALON FRANCAIS - Damaged carpet | C66: ACTION | D66: OPEN | E66: 23.07: FLORENZ RAMSI will inspect on 07.08. 03.09: RPN received MOS from FLORENZ RAMSI 25.02: Carpet is back on site | F66: 30.04: RPN to propose a solution for reparation. + liaise with heritage specialist 03.09: RPN to submit MOS 25.02: Carpet to be inspected | G66: Low | H66: 46086 | I66: {=IFERROR(_xlfn.TEXTJOIN(" / ", TRUE, IF(OWNER_LIST[Owner Name]=C_1[[#This Row],[OWNER NAME 1]], OWNER_LIST[Owner ORG], ""), IF(OWNER_LIST[Owner Name]=C_1[[#This Row],[OWNER NAME 2]], OWNER_LIST[Owner ORG], "")), "")} -> SHP / SHP | J66: Maximilien Montanaro | K66: Andrea Hoffman | R66: =_xlfn.CONCAT(C_1[[#This Row],[ESCALATE]], "-",C_1[[#This Row],[Row_PM]]) -> - | S66: =_xlfn.CONCAT(C_1[[#This Row],[ESCALATE]], "-",C_1[[#This Row],[Notify_PM]]) -> -- | T66: =ROW() -> 66 | U66: =IF(C_1[[#This Row],[OWNER NAME 1]] = "", "", IF(_xlfn.XLOOKUP(C_1[[#This Row],[OWNER NAME 1]],OWNER_LIST[Owner Name], OWNER_LIST[Email], "") = "", "", _xlfn.XLOOKUP(C_1[[#This Row],[OWNER NAME 1]], OWNER_LIST[Owner Name], OWNER_LIST[Email], ""))) -> maximilien.montanaro@un.org | V66: =IF(C_1[[#This Row],[OWNER NAME 2]] = "", "", IF(_xlfn.XLOOKUP(C_1[[#This Row],[OWNER NAME 2]],OWNER_LIST[Owner Name], OWNER_LIST[Email], "") = "", "", _xlfn.XLOOKUP(C_1[[#This Row],[OWNER NAME 2]], OWNER_LIST[Owner Name], OWNER_LIST[Email], ""))) -> ahoffmann@hoffmannart.ch | W66: =$A$37 -> C1 | X66: =IF( OR( AND( NOT(ISBLANK(C_1[[#This Row],[DESCRIPTION - INFORMATION LOG]])), C_1[[#This Row],[DESCRIPTION - INFORMATION LOG]] <> "DESCRIPTION - INFORMATION LOG" ), NOT(ISBLANK(C_1[[#This Row],[ACTION REQUIRED]])) ), "Y", "N" ) -> Y
A67: L01 | B67: SALLE 1 - Relamping | C67: ACTION | D67: OPEN | E67: 21.01: Refer to MEP MoM. 28.01: recabling is ongoing. 28.01: 2 lamps went missing during the works (not produced any more) 18.02: MAS has been submitted (4000K) | F67: 09.03: RPN to proceed | G67: High | H67: 46097 | I67: {=IFERROR(_xlfn.TEXTJOIN(" / ", TRUE, IF(OWNER_LIST[Owner Name]=C_1[[#This Row],[OWNER NAME 1]], OWNER_LIST[Owner ORG], ""), IF(OWNER_LIST[Owner Name]=C_1[[#This Row],[OWNER NAME 2]], OWNER_LIST[Owner ORG], "")), "")} -> RPN | J67: Matteo Naldi | R67: =_xlfn.CONCAT(C_1[[#This Row],[ESCALATE]], "-",C_1[[#This Row],[Row_PM]]) -> - | S67: =_xlfn.CONCAT(C_1[[#This Row],[ESCALATE]], "-",C_1[[#This Row],[Notify_PM]]) -> -- | T67: =ROW() -> 67 | U67: =IF(C_1[[#This Row],[OWNER NAME 1]] = "", "", IF(_xlfn.XLOOKUP(C_1[[#This Row],[OWNER NAME 1]],OWNER_LIST[Owner Name], OWNER_LIST[Email], "") = "", "", _xlfn.XLOOKUP(C_1[[#This Row],[OWNER NAME 1]], OWNER_LIST[Owner Name], OWNER_LIST[Email], ""))) -> matteo.naldi@cmbcarpi.it | V67: =IF(C_1[[#This Row],[OWNER NAME 2]] = "", "", IF(_xlfn.XLOOKUP(C_1[[#This Row],[OWNER NAME 2]],OWNER_LIST[Owner Name], OWNER_LIST[Email], "") = "", "", _xlfn.XLOOKUP(C_1[[#This Row],[OWNER NAME 2]], OWNER_LIST[Owner Name], OWNER_LIST[Email], ""))) | W67: =$A$37 -> C1 | X67: =IF( OR( AND( NOT(ISBLANK(C_1[[#This Row],[DESCRIPTION - INFORMATION LOG]])), C_1[[#This Row],[DESCRIPTION - INFORMATION LOG]] <> "DESCRIPTION - INFORMATION LOG" ), NOT(ISBLANK(C_1[[#This Row],[ACTION REQUIRED]])) ), "Y", "N" ) -> Y
A68: L01 | B68: SALLE 1 - NCF 380 Conditions AV equipment | C68: ACTION | D68: OPEN | E68: 17.02: NCF 380 Salle 1 AV equipment conditions | F68: 23.02: RPN to assess | G68: Medium | H68: 46078 | I68: {=IFERROR(_xlfn.TEXTJOIN(" / ", TRUE, IF(OWNER_LIST[Owner Name]=C_1[[#This Row],[OWNER NAME 1]], OWNER_LIST[Owner ORG], ""), IF(OWNER_LIST[Owner Name]=C_1[[#This Row],[OWNER NAME 2]], OWNER_LIST[Owner ORG], "")), "")} -> RPN / RPN | J68: Davide Cirillo | K68: Matteo Naldi | R68: =_xlfn.CONCAT(C_1[[#This Row],[ESCALATE]], "-",C_1[[#This Row],[Row_PM]]) -> - | S68: =_xlfn.CONCAT(C_1[[#This Row],[ESCALATE]], "-",C_1[[#This Row],[Notify_PM]]) -> -- | T68: =ROW() -> 68 | U68: =IF(C_1[[#This Row],[OWNER NAME 1]] = "", "", IF(_xlfn.XLOOKUP(C_1[[#This Row],[OWNER NAME 1]],OWNER_LIST[Owner Name], OWNER_LIST[Email], "") = "", "", _xlfn.XLOOKUP(C_1[[#This Row],[OWNER NAME 1]], OWNER_LIST[Owner Name], OWNER_LIST[Email], ""))) -> davide.cirillo@cmbcarpi.it | V68: =IF(C_1[[#This Row],[OWNER NAME 2]] = "", "", IF(_xlfn.XLOOKUP(C_1[[#This Row],[OWNER NAME 2]],OWNER_LIST[Owner Name], OWNER_LIST[Email], "") = "", "", _xlfn.XLOOKUP(C_1[[#This Row],[OWNER NAME 2]], OWNER_LIST[Owner Name], OWNER_LIST[Email], ""))) -> matteo.naldi@cmbcarpi.it | W68: =$A$37 -> C1 | X68: =IF( OR( AND( NOT(ISBLANK(C_1[[#This Row],[DESCRIPTION - INFORMATION LOG]])), C_1[[#This Row],[DESCRIPTION - INFORMATION LOG]] <> "DESCRIPTION - INFORMATION LOG" ), NOT(ISBLANK(C_1[[#This Row],[ACTION REQUIRED]])) ), "Y", "N" ) -> Y
A69: L01 | B69: COUNCIL CHAMBER - VAR 473 L02 SAS to council chamber | C69: ACTION | D69: OPEN | E69: 03.10: SHP issued VAR Step 3 Rev 4 (painting of ceiling + emergency light product change) 15.10: RPN submitted updated cost proposal. 22.10: Ceiling have been removed, 1 ventilation duct have been found that do no comply with actual standard. SHP requested dwg to FMS. 29.10: SHP will not instruct RPN to duct the plenum | F69: 22.10: SHP to assess 29.10: RPN to issue an RFI for formal confirmation | G69: High | R69: =_xlfn.CONCAT(C_1[[#This Row],[ESCALATE]], "-",C_1[[#This Row],[Row_PM]]) -> - | S69: =_xlfn.CONCAT(C_1[[#This Row],[ESCALATE]], "-",C_1[[#This Row],[Notify_PM]]) -> -- | T69: =ROW() -> 69 | U69: =IF(C_1[[#This Row],[OWNER NAME 1]] = "", "", IF(_xlfn.XLOOKUP(C_1[[#This Row],[OWNER NAME 1]],OWNER_LIST[Owner Name], OWNER_LIST[Email], "") = "", "", _xlfn.XLOOKUP(C_1[[#This Row],[OWNER NAME 1]], OWNER_LIST[Owner Name], OWNER_LIST[Email], ""))) | V69: =IF(C_1[[#This Row],[OWNER NAME 2]] = "", "", IF(_xlfn.XLOOKUP(C_1[[#This Row],[OWNER NAME 2]],OWNER_LIST[Owner Name], OWNER_LIST[Email], "") = "", "", _xlfn.XLOOKUP(C_1[[#This Row],[OWNER NAME 2]], OWNER_LIST[Owner Name], OWNER_LIST[Email], ""))) | W69: =$A$37 -> C1 | X69: =IF( OR( AND( NOT(ISBLANK(C_1[[#This Row],[DESCRIPTION - INFORMATION LOG]])), C_1[[#This Row],[DESCRIPTION - INFORMATION LOG]] <> "DESCRIPTION - INFORMATION LOG" ), NOT(ISBLANK(C_1[[#This Row],[ACTION REQUIRED]])) ), "Y", "N" ) -> Y
A70: L02 | B70: SAS to COUNCIL CHAMBER - VAR 570 - LED to be integrated on the top of the frame | C70: ACTION | D70: OPEN | E70: 22.10: RPN is reviewing with EGGTELSA. 10.11: Both SAS ceiling will be demolished (repainted in RAL), Walls to be repaired in false marble (D-PT-11). Doors with vision panels to receive D-PT-11 on coursive side, RAL 8008 on the SAS side. Handle and kick plate to be preserved. Oculus to be same size, centered. 28.01: All cost agreed 09.02: VAR step 1 has been issued 16.02: Step 3 has been issued | F70: 09.02: RPN to issue step 2 23.02: RPN to issue commercial proposal | G70: TOP | H70: 46076 | I70: {=IFERROR(_xlfn.TEXTJOIN(" / ", TRUE, IF(OWNER_LIST[Owner Name]=C_1[[#This Row],[OWNER NAME 1]], OWNER_LIST[Owner ORG], ""), IF(OWNER_LIST[Owner Name]=C_1[[#This Row],[OWNER NAME 2]], OWNER_LIST[Owner ORG], "")), "")} -> RPN | J70: Jessica Donatelli | R70: =_xlfn.CONCAT(C_1[[#This Row],[ESCALATE]], "-",C_1[[#This Row],[Row_PM]]) -> - | S70: =_xlfn.CONCAT(C_1[[#This Row],[ESCALATE]], "-",C_1[[#This Row],[Notify_PM]]) -> -- | T70: =ROW() -> 70 | U70: =IF(C_1[[#This Row],[OWNER NAME 1]] = "", "", IF(_xlfn.XLOOKUP(C_1[[#This Row],[OWNER NAME 1]],OWNER_LIST[Owner Name], OWNER_LIST[Email], "") = "", "", _xlfn.XLOOKUP(C_1[[#This Row],[OWNER NAME 1]], OWNER_LIST[Owner Name], OWNER_LIST[Email], ""))) -> jessica.donatelli@cmbcarpi.it | V70: =IF(C_1[[#This Row],[OWNER NAME 2]] = "", "", IF(_xlfn.XLOOKUP(C_1[[#This Row],[OWNER NAME 2]],OWNER_LIST[Owner Name], OWNER_LIST[Email], "") = "", "", _xlfn.XLOOKUP(C_1[[#This Row],[OWNER NAME 2]], OWNER_LIST[Owner Name], OWNER_LIST[Email], ""))) | W70: =$A$37 -> C1 | X70: =IF( OR( AND( NOT(ISBLANK(C_1[[#This Row],[DESCRIPTION - INFORMATION LOG]])), C_1[[#This Row],[DESCRIPTION - INFORMATION LOG]] <> "DESCRIPTION - INFORMATION LOG" ), NOT(ISBLANK(C_1[[#This Row],[ACTION REQUIRED]])) ), "Y", "N" ) -> Y
A71: L01 | B71: COUNCIL CHAMBER - VAR 625 - Electrical panel F15 | C71: INFO | D71: OPEN | E71: 14.01: AV issues to me moved to VAR 628 19.01: No issue on F15 panel due to AV equipments. 21.01: Panel will be delivered 10.02 28.01: Installation has not started. 1 month lost. 11.02: No blocking point. Missing manpower (agreement with RPN not found). Cabling to be completed before moving the tables (3P is blocked). | F71: 25.02: Works ongoing 04.03: Final Inspection is planned for week 09.03 09.03: RPN to confirm readiness | G71: High | H71: 46087 | I71: {=IFERROR(_xlfn.TEXTJOIN(" / ", TRUE, IF(OWNER_LIST[Owner Name]=C_1[[#This Row],[OWNER NAME 1]], OWNER_LIST[Owner ORG], ""), IF(OWNER_LIST[Owner Name]=C_1[[#This Row],[OWNER NAME 2]], OWNER_LIST[Owner ORG], "")), "")} -> RPN / RPN | J71: Hacir Degirmencioglu | K71: Matteo Naldi | R71: =_xlfn.CONCAT(C_1[[#This Row],[ESCALATE]], "-",C_1[[#This Row],[Row_PM]]) -> - | S71: =_xlfn.CONCAT(C_1[[#This Row],[ESCALATE]], "-",C_1[[#This Row],[Notify_PM]]) -> -- | T71: =ROW() -> 71 | U71: =IF(C_1[[#This Row],[OWNER NAME 1]] = "", "", IF(_xlfn.XLOOKUP(C_1[[#This Row],[OWNER NAME 1]],OWNER_LIST[Owner Name], OWNER_LIST[Email], "") = "", "", _xlfn.XLOOKUP(C_1[[#This Row],[OWNER NAME 1]], OWNER_LIST[Owner Name], OWNER_LIST[Email], ""))) -> hacir.degirmencioglu@rpn-sa.ch | V71: =IF(C_1[[#This Row],[OWNER NAME 2]] = "", "", IF(_xlfn.XLOOKUP(C_1[[#This Row],[OWNER NAME 2]],OWNER_LIST[Owner Name], OWNER_LIST[Email], "") = "", "", _xlfn.XLOOKUP(C_1[[#This Row],[OWNER NAME 2]], OWNER_LIST[Owner Name], OWNER_LIST[Email], ""))) -> matteo.naldi@cmbcarpi.it | W71: =$A$37 -> C1 | X71: =IF( OR( AND( NOT(ISBLANK(C_1[[#This Row],[DESCRIPTION - INFORMATION LOG]])), C_1[[#This Row],[DESCRIPTION - INFORMATION LOG]] <> "DESCRIPTION - INFORMATION LOG" ), NOT(ISBLANK(C_1[[#This Row],[ACTION REQUIRED]])) ), "Y", "N" ) -> Y
A72: L01 | B72: COUNCIL CHAMBER - Interpretor booth | C72: ACTION | D72: OPEN | E72: Perforation for new equipments to be confirmed on site Site visit has been runed | F72: 30.09: Works to be assessed during site visit (26.11) 08.12: SHP to issue sketch, RPN to prepare mockup (with tape as in previous sections) 23.02: If few sockets are missing, RPN to submit daywork RFI | G72: Medium | H72: 46027 | I72: {=IFERROR(_xlfn.TEXTJOIN(" / ", TRUE, IF(OWNER_LIST[Owner Name]=C_1[[#This Row],[OWNER NAME 1]], OWNER_LIST[Owner ORG], ""), IF(OWNER_LIST[Owner Name]=C_1[[#This Row],[OWNER NAME 2]], OWNER_LIST[Owner ORG], "")), "")} -> RPN | J72: Federica Brunone | R72: =_xlfn.CONCAT(C_1[[#This Row],[ESCALATE]], "-",C_1[[#This Row],[Row_PM]]) -> - | S72: =_xlfn.CONCAT(C_1[[#This Row],[ESCALATE]], "-",C_1[[#This Row],[Notify_PM]]) -> -- | T72: =ROW() -> 72 | U72: =IF(C_1[[#This Row],[OWNER NAME 1]] = "", "", IF(_xlfn.XLOOKUP(C_1[[#This Row],[OWNER NAME 1]],OWNER_LIST[Owner Name], OWNER_LIST[Email], "") = "", "", _xlfn.XLOOKUP(C_1[[#This Row],[OWNER NAME 1]], OWNER_LIST[Owner Name], OWNER_LIST[Email], ""))) -> federica.brunone@cmbcarpi.it | V72: =IF(C_1[[#This Row],[OWNER NAME 2]] = "", "", IF(_xlfn.XLOOKUP(C_1[[#This Row],[OWNER NAME 2]],OWNER_LIST[Owner Name], OWNER_LIST[Email], "") = "", "", _xlfn.XLOOKUP(C_1[[#This Row],[OWNER NAME 2]], OWNER_LIST[Owner Name], OWNER_LIST[Email], ""))) | W72: =$A$37 -> C1 | X72: =IF( OR( AND( NOT(ISBLANK(C_1[[#This Row],[DESCRIPTION - INFORMATION LOG]])), C_1[[#This Row],[DESCRIPTION - INFORMATION LOG]] <> "DESCRIPTION - INFORMATION LOG" ), NOT(ISBLANK(C_1[[#This Row],[ACTION REQUIRED]])) ), "Y", "N" ) -> Y
A73: L01 | B73: COUNCIL CHAMBER - WINDOW MOTORIZATION | C73: INFO | D73: OPEN | E73: 30.09: Upper windows have already been motorized. 19.11: delivery by mid january 28.01: Motors have been received 04.03: All motors have been installed. Upper part to be tested | F73: 04.03: RPN to confirm installation | G73: Low | H73: 46066 | I73: {=IFERROR(_xlfn.TEXTJOIN(" / ", TRUE, IF(OWNER_LIST[Owner Name]=C_1[[#This Row],[OWNER NAME 1]], OWNER_LIST[Owner ORG], ""), IF(OWNER_LIST[Owner Name]=C_1[[#This Row],[OWNER NAME 2]], OWNER_LIST[Owner ORG], "")), "")} -> RPN | J73: Matteo Naldi | R73: =_xlfn.CONCAT(C_1[[#This Row],[ESCALATE]], "-",C_1[[#This Row],[Row_PM]]) -> - | S73: =_xlfn.CONCAT(C_1[[#This Row],[ESCALATE]], "-",C_1[[#This Row],[Notify_PM]]) -> -- | T73: =ROW() -> 73 | U73: =IF(C_1[[#This Row],[OWNER NAME 1]] = "", "", IF(_xlfn.XLOOKUP(C_1[[#This Row],[OWNER NAME 1]],OWNER_LIST[Owner Name], OWNER_LIST[Email], "") = "", "", _xlfn.XLOOKUP(C_1[[#This Row],[OWNER NAME 1]], OWNER_LIST[Owner Name], OWNER_LIST[Email], ""))) -> matteo.naldi@cmbcarpi.it | V73: =IF(C_1[[#This Row],[OWNER NAME 2]] = "", "", IF(_xlfn.XLOOKUP(C_1[[#This Row],[OWNER NAME 2]],OWNER_LIST[Owner Name], OWNER_LIST[Email], "") = "", "", _xlfn.XLOOKUP(C_1[[#This Row],[OWNER NAME 2]], OWNER_LIST[Owner Name], OWNER_LIST[Email], ""))) | W73: =$A$37 -> C1 | X73: =IF( OR( AND( NOT(ISBLANK(C_1[[#This Row],[DESCRIPTION - INFORMATION LOG]])), C_1[[#This Row],[DESCRIPTION - INFORMATION LOG]] <> "DESCRIPTION - INFORMATION LOG" ), NOT(ISBLANK(C_1[[#This Row],[ACTION REQUIRED]])) ), "Y", "N" ) -> Y
A74: L01 | B74: COUNCIL CHAMBER - TELEVIC inventory | C74: INFO | D74: OPEN | E74: 17.11: RPN have submitted the TELEVIC inventory, 20251117_SOMBP_SMW_TA - OVERALL TELEVIC INVENTORY 16.01: Comments issued on Bluebeam | F74: 19.01: SHP/SOMBP to share comments 19.01: RPN to rebuild spare parts inventory | G74: Medium | H74: 46055 | I74: {=IFERROR(_xlfn.TEXTJOIN(" / ", TRUE, IF(OWNER_LIST[Owner Name]=C_1[[#This Row],[OWNER NAME 1]], OWNER_LIST[Owner ORG], ""), IF(OWNER_LIST[Owner Name]=C_1[[#This Row],[OWNER NAME 2]], OWNER_LIST[Owner ORG], "")), "")} -> RPN | J74: Federica Brunone | R74: =_xlfn.CONCAT(C_1[[#This Row],[ESCALATE]], "-",C_1[[#This Row],[Row_PM]]) -> - | S74: =_xlfn.CONCAT(C_1[[#This Row],[ESCALATE]], "-",C_1[[#This Row],[Notify_PM]]) -> -- | T74: =ROW() -> 74 | U74: =IF(C_1[[#This Row],[OWNER NAME 1]] = "", "", IF(_xlfn.XLOOKUP(C_1[[#This Row],[OWNER NAME 1]],OWNER_LIST[Owner Name], OWNER_LIST[Email], "") = "", "", _xlfn.XLOOKUP(C_1[[#This Row],[OWNER NAME 1]], OWNER_LIST[Owner Name], OWNER_LIST[Email], ""))) -> federica.brunone@cmbcarpi.it | V74: =IF(C_1[[#This Row],[OWNER NAME 2]] = "", "", IF(_xlfn.XLOOKUP(C_1[[#This Row],[OWNER NAME 2]],OWNER_LIST[Owner Name], OWNER_LIST[Email], "") = "", "", _xlfn.XLOOKUP(C_1[[#This Row],[OWNER NAME 2]], OWNER_LIST[Owner Name], OWNER_LIST[Email], ""))) | W74: =$A$37 -> C1 | X74: =IF( OR( AND( NOT(ISBLANK(C_1[[#This Row],[DESCRIPTION - INFORMATION LOG]])), C_1[[#This Row],[DESCRIPTION - INFORMATION LOG]] <> "DESCRIPTION - INFORMATION LOG" ), NOT(ISBLANK(C_1[[#This Row],[ACTION REQUIRED]])) ), "Y", "N" ) -> Y
A75: L01 | B75: COUNCIL CHAMBER - CHAIRS VAR 40 | C75: ACTION | D75: OPEN | E75: Some chairs to be repaired 28.01: Assessment have been done | F75: 28.01: refurbishment is ongoing | G75: Low | H75: 45994 | I75: {=IFERROR(_xlfn.TEXTJOIN(" / ", TRUE, IF(OWNER_LIST[Owner Name]=C_1[[#This Row],[OWNER NAME 1]], OWNER_LIST[Owner ORG], ""), IF(OWNER_LIST[Owner Name]=C_1[[#This Row],[OWNER NAME 2]], OWNER_LIST[Owner ORG], "")), "")} -> RPN / SHP | J75: Martina Maffioletti | K75: Andrea Hoffman | R75: =_xlfn.CONCAT(C_1[[#This Row],[ESCALATE]], "-",C_1[[#This Row],[Row_PM]]) -> - | S75: =_xlfn.CONCAT(C_1[[#This Row],[ESCALATE]], "-",C_1[[#This Row],[Notify_PM]]) -> -- | T75: =ROW() -> 75 | U75: =IF(C_1[[#This Row],[OWNER NAME 1]] = "", "", IF(_xlfn.XLOOKUP(C_1[[#This Row],[OWNER NAME 1]],OWNER_LIST[Owner Name], OWNER_LIST[Email], "") = "", "", _xlfn.XLOOKUP(C_1[[#This Row],[OWNER NAME 1]], OWNER_LIST[Owner Name], OWNER_LIST[Email], ""))) -> martina.maffioletti@rpn-sa.ch | V75: =IF(C_1[[#This Row],[OWNER NAME 2]] = "", "", IF(_xlfn.XLOOKUP(C_1[[#This Row],[OWNER NAME 2]],OWNER_LIST[Owner Name], OWNER_LIST[Email], "") = "", "", _xlfn.XLOOKUP(C_1[[#This Row],[OWNER NAME 2]], OWNER_LIST[Owner Name], OWNER_LIST[Email], ""))) -> ahoffmann@hoffmannart.ch | W75: =$A$37 -> C1 | X75: =IF( OR( AND( NOT(ISBLANK(C_1[[#This Row],[DESCRIPTION - INFORMATION LOG]])), C_1[[#This Row],[DESCRIPTION - INFORMATION LOG]] <> "DESCRIPTION - INFORMATION LOG" ), NOT(ISBLANK(C_1[[#This Row],[ACTION REQUIRED]])) ), "Y", "N" ) -> Y
A76: L01 | B76: COUNCIL CHAMBER - Accessibility tables | C76: INFO | D76: OPEN | E76: 15.12: tables to be modified for PMR 07.01: Table modification to be made on site 21.01: reposition by 16.02, adaptation by end of February 23.02: Works on going | G76: Medium | H76: 45994 | I76: {=IFERROR(_xlfn.TEXTJOIN(" / ", TRUE, IF(OWNER_LIST[Owner Name]=C_1[[#This Row],[OWNER NAME 1]], OWNER_LIST[Owner ORG], ""), IF(OWNER_LIST[Owner Name]=C_1[[#This Row],[OWNER NAME 2]], OWNER_LIST[Owner ORG], "")), "")} -> RPN / RPN | J76: Martina Maffioletti | K76: Matteo Naldi | R76: =_xlfn.CONCAT(C_1[[#This Row],[ESCALATE]], "-",C_1[[#This Row],[Row_PM]]) -> - | S76: =_xlfn.CONCAT(C_1[[#This Row],[ESCALATE]], "-",C_1[[#This Row],[Notify_PM]]) -> -- | T76: =ROW() -> 76 | U76: =IF(C_1[[#This Row],[OWNER NAME 1]] = "", "", IF(_xlfn.XLOOKUP(C_1[[#This Row],[OWNER NAME 1]],OWNER_LIST[Owner Name], OWNER_LIST[Email], "") = "", "", _xlfn.XLOOKUP(C_1[[#This Row],[OWNER NAME 1]], OWNER_LIST[Owner Name], OWNER_LIST[Email], ""))) -> martina.maffioletti@rpn-sa.ch | V76: =IF(C_1[[#This Row],[OWNER NAME 2]] = "", "", IF(_xlfn.XLOOKUP(C_1[[#This Row],[OWNER NAME 2]],OWNER_LIST[Owner Name], OWNER_LIST[Email], "") = "", "", _xlfn.XLOOKUP(C_1[[#This Row],[OWNER NAME 2]], OWNER_LIST[Owner Name], OWNER_LIST[Email], ""))) -> matteo.naldi@cmbcarpi.it | W76: =$A$37 -> C1 | X76: =IF( OR( AND( NOT(ISBLANK(C_1[[#This Row],[DESCRIPTION - INFORMATION LOG]])), C_1[[#This Row],[DESCRIPTION - INFORMATION LOG]] <> "DESCRIPTION - INFORMATION LOG" ), NOT(ISBLANK(C_1[[#This Row],[ACTION REQUIRED]])) ), "Y", "N" ) -> Y
A77: L01 | B77: COUNCIL CHAMBER - Temporary protection | C77: INFO | D77: OPEN | E77: 28.01: All protection to furnitures ansd floor have been removed 18.02: Protection has not be reinstalled | G77: Medium | H77: 45994 | I77: {=IFERROR(_xlfn.TEXTJOIN(" / ", TRUE, IF(OWNER_LIST[Owner Name]=C_1[[#This Row],[OWNER NAME 1]], OWNER_LIST[Owner ORG], ""), IF(OWNER_LIST[Owner Name]=C_1[[#This Row],[OWNER NAME 2]], OWNER_LIST[Owner ORG], "")), "")} -> RPN | K77: Matteo Naldi | R77: =_xlfn.CONCAT(C_1[[#This Row],[ESCALATE]], "-",C_1[[#This Row],[Row_PM]]) -> - | S77: =_xlfn.CONCAT(C_1[[#This Row],[ESCALATE]], "-",C_1[[#This Row],[Notify_PM]]) -> -- | T77: =ROW() -> 77 | U77: =IF(C_1[[#This Row],[OWNER NAME 1]] = "", "", IF(_xlfn.XLOOKUP(C_1[[#This Row],[OWNER NAME 1]],OWNER_LIST[Owner Name], OWNER_LIST[Email], "") = "", "", _xlfn.XLOOKUP(C_1[[#This Row],[OWNER NAME 1]], OWNER_LIST[Owner Name], OWNER_LIST[Email], ""))) | V77: =IF(C_1[[#This Row],[OWNER NAME 2]] = "", "", IF(_xlfn.XLOOKUP(C_1[[#This Row],[OWNER NAME 2]],OWNER_LIST[Owner Name], OWNER_LIST[Email], "") = "", "", _xlfn.XLOOKUP(C_1[[#This Row],[OWNER NAME 2]], OWNER_LIST[Owner Name], OWNER_LIST[Email], ""))) -> matteo.naldi@cmbcarpi.it | W77: =$A$37 -> C1 | X77: =IF( OR( AND( NOT(ISBLANK(C_1[[#This Row],[DESCRIPTION - INFORMATION LOG]])), C_1[[#This Row],[DESCRIPTION - INFORMATION LOG]] <> "DESCRIPTION - INFORMATION LOG" ), NOT(ISBLANK(C_1[[#This Row],[ACTION REQUIRED]])) ), "Y", "N" ) -> Y
A78: L01 | B78: COUNCIL CHAMBER - VAR 399 Balustrade to coursive | C78: ACTION | D78: OPEN | E78: 04.02: RPN propose solution C from the VAR. 09.02: Site visite is scheduled 10.02. 11.02: Handrail do not comply with SIA standard. | F78: 04.02: RPN to confirm (refer to technical solution applied in Hall 14 mezzanine) 16.02: SOMBP to draft INS with improved design. 04.03: RPN subcontractor to assess about feasability | G78: TOP | H78: 46087 | I78: {=IFERROR(_xlfn.TEXTJOIN(" / ", TRUE, IF(OWNER_LIST[Owner Name]=C_1[[#This Row],[OWNER NAME 1]], OWNER_LIST[Owner ORG], ""), IF(OWNER_LIST[Owner Name]=C_1[[#This Row],[OWNER NAME 2]], OWNER_LIST[Owner ORG], "")), "")} -> RPN / SOMBP | J78: Chiara Re Depaolini | K78: Lucille Treille de Grandsaigne | R78: =_xlfn.CONCAT(C_1[[#This Row],[ESCALATE]], "-",C_1[[#This Row],[Row_PM]]) -> - | S78: =_xlfn.CONCAT(C_1[[#This Row],[ESCALATE]], "-",C_1[[#This Row],[Notify_PM]]) -> -- | T78: =ROW() -> 78 | U78: =IF(C_1[[#This Row],[OWNER NAME 1]] = "", "", IF(_xlfn.XLOOKUP(C_1[[#This Row],[OWNER NAME 1]],OWNER_LIST[Owner Name], OWNER_LIST[Email], "") = "", "", _xlfn.XLOOKUP(C_1[[#This Row],[OWNER NAME 1]], OWNER_LIST[Owner Name], OWNER_LIST[Email], ""))) -> chiara.redepaolini@rpn-sa.ch | V78: =IF(C_1[[#This Row],[OWNER NAME 2]] = "", "", IF(_xlfn.XLOOKUP(C_1[[#This Row],[OWNER NAME 2]],OWNER_LIST[Owner Name], OWNER_LIST[Email], "") = "", "", _xlfn.XLOOKUP(C_1[[#This Row],[OWNER NAME 2]], OWNER_LIST[Owner Name], OWNER_LIST[Email], ""))) -> lucille.treilledegrandsaigne@burckhardt.swiss | W78: =$A$37 -> C1 | X78: =IF( OR( AND( NOT(ISBLANK(C_1[[#This Row],[DESCRIPTION - INFORMATION LOG]])), C_1[[#This Row],[DESCRIPTION - INFORMATION LOG]] <> "DESCRIPTION - INFORMATION LOG" ), NOT(ISBLANK(C_1[[#This Row],[ACTION REQUIRED]])) ), "Y", "N" ) -> Y
A79: L01 | B79: COUNCIL CHAMBER - VAR 539 conference door | C79: ACTION | D79: OPEN | E79: 04.03: VAR 539 step 3 Rev1 is under signature 06.03: Step 3 rev 1 has been issued 09.03: Access control is being installed on both side of the door | F79: 23.02: SHP to update VAR 539 including Council chamber doors 0903: SHP to assess | G79: High | H79: 46101 | I79: {=IFERROR(_xlfn.TEXTJOIN(" / ", TRUE, IF(OWNER_LIST[Owner Name]=C_1[[#This Row],[OWNER NAME 1]], OWNER_LIST[Owner ORG], ""), IF(OWNER_LIST[Owner Name]=C_1[[#This Row],[OWNER NAME 2]], OWNER_LIST[Owner ORG], "")), "")} -> SHP | J79: Maximilien Montanaro | R79: =_xlfn.CONCAT(C_1[[#This Row],[ESCALATE]], "-",C_1[[#This Row],[Row_PM]]) -> - | S79: =_xlfn.CONCAT(C_1[[#This Row],[ESCALATE]], "-",C_1[[#This Row],[Notify_PM]]) -> -- | T79: =ROW() -> 79 | U79: =IF(C_1[[#This Row],[OWNER NAME 1]] = "", "", IF(_xlfn.XLOOKUP(C_1[[#This Row],[OWNER NAME 1]],OWNER_LIST[Owner Name], OWNER_LIST[Email], "") = "", "", _xlfn.XLOOKUP(C_1[[#This Row],[OWNER NAME 1]], OWNER_LIST[Owner Name], OWNER_LIST[Email], ""))) -> maximilien.montanaro@un.org | V79: =IF(C_1[[#This Row],[OWNER NAME 2]] = "", "", IF(_xlfn.XLOOKUP(C_1[[#This Row],[OWNER NAME 2]],OWNER_LIST[Owner Name], OWNER_LIST[Email], "") = "", "", _xlfn.XLOOKUP(C_1[[#This Row],[OWNER NAME 2]], OWNER_LIST[Owner Name], OWNER_LIST[Email], ""))) | W79: =$A$37 -> C1 | X79: =IF( OR( AND( NOT(ISBLANK(C_1[[#This Row],[DESCRIPTION - INFORMATION LOG]])), C_1[[#This Row],[DESCRIPTION - INFORMATION LOG]] <> "DESCRIPTION - INFORMATION LOG" ), NOT(ISBLANK(C_1[[#This Row],[ACTION REQUIRED]])) ), "Y", "N" ) -> Y
A80: L01 | B80: COUNCIL CHAMBER - LED Wall ventilation issue | C80: ACTION | D80: OPEN | E80: 26.02: Casing as been supplied w/o required perforations. 04.03: Re-ordering the case may impact S.C. 04.03 COUNCIL CHAMBER is needed in June | F80: 26.02: RPN to reject delivery/ submit manufacturer warranties | G80: High | H80: 46087 | I80: {=IFERROR(_xlfn.TEXTJOIN(" / ", TRUE, IF(OWNER_LIST[Owner Name]=C_1[[#This Row],[OWNER NAME 1]], OWNER_LIST[Owner ORG], ""), IF(OWNER_LIST[Owner Name]=C_1[[#This Row],[OWNER NAME 2]], OWNER_LIST[Owner ORG], "")), "")} -> RPN / RPN | J80: Federica Brunone | K80: Matteo Naldi | R80: =_xlfn.CONCAT(C_1[[#This Row],[ESCALATE]], "-",C_1[[#This Row],[Row_PM]]) -> - | S80: =_xlfn.CONCAT(C_1[[#This Row],[ESCALATE]], "-",C_1[[#This Row],[Notify_PM]]) -> -- | T80: =ROW() -> 80 | U80: =IF(C_1[[#This Row],[OWNER NAME 1]] = "", "", IF(_xlfn.XLOOKUP(C_1[[#This Row],[OWNER NAME 1]],OWNER_LIST[Owner Name], OWNER_LIST[Email], "") = "", "", _xlfn.XLOOKUP(C_1[[#This Row],[OWNER NAME 1]], OWNER_LIST[Owner Name], OWNER_LIST[Email], ""))) -> federica.brunone@cmbcarpi.it | V80: =IF(C_1[[#This Row],[OWNER NAME 2]] = "", "", IF(_xlfn.XLOOKUP(C_1[[#This Row],[OWNER NAME 2]],OWNER_LIST[Owner Name], OWNER_LIST[Email], "") = "", "", _xlfn.XLOOKUP(C_1[[#This Row],[OWNER NAME 2]], OWNER_LIST[Owner Name], OWNER_LIST[Email], ""))) -> matteo.naldi@cmbcarpi.it | W80: =$A$37 -> C1 | X80: =IF( OR( AND( NOT(ISBLANK(C_1[[#This Row],[DESCRIPTION - INFORMATION LOG]])), C_1[[#This Row],[DESCRIPTION - INFORMATION LOG]] <> "DESCRIPTION - INFORMATION LOG" ), NOT(ISBLANK(C_1[[#This Row],[ACTION REQUIRED]])) ), "Y", "N" ) -> Y
A81: L01 | B81: NCF 357 - AV cables quality | C81: ACTION | D81: OPEN | F81: 24.11: RPN to comment | G81: High | H81: 45993 | I81: {=IFERROR(_xlfn.TEXTJOIN(" / ", TRUE, IF(OWNER_LIST[Owner Name]=C_1[[#This Row],[OWNER NAME 1]], OWNER_LIST[Owner ORG], ""), IF(OWNER_LIST[Owner Name]=C_1[[#This Row],[OWNER NAME 2]], OWNER_LIST[Owner ORG], "")), "")} -> RPN / SHP | J81: Davide Cirillo | K81: Patrick Vogelsang | R81: =_xlfn.CONCAT(C_1[[#This Row],[ESCALATE]], "-",C_1[[#This Row],[Row_PM]]) -> - | S81: =_xlfn.CONCAT(C_1[[#This Row],[ESCALATE]], "-",C_1[[#This Row],[Notify_PM]]) -> -- | T81: =ROW() -> 81 | U81: =IF(C_1[[#This Row],[OWNER NAME 1]] = "", "", IF(_xlfn.XLOOKUP(C_1[[#This Row],[OWNER NAME 1]],OWNER_LIST[Owner Name], OWNER_LIST[Email], "") = "", "", _xlfn.XLOOKUP(C_1[[#This Row],[OWNER NAME 1]], OWNER_LIST[Owner Name], OWNER_LIST[Email], ""))) -> davide.cirillo@cmbcarpi.it | V81: =IF(C_1[[#This Row],[OWNER NAME 2]] = "", "", IF(_xlfn.XLOOKUP(C_1[[#This Row],[OWNER NAME 2]],OWNER_LIST[Owner Name], OWNER_LIST[Email], "") = "", "", _xlfn.XLOOKUP(C_1[[#This Row],[OWNER NAME 2]], OWNER_LIST[Owner Name], OWNER_LIST[Email], ""))) -> patrick.vogelsang@un.org | W81: =$A$37 -> C1 | X81: =IF( OR( AND( NOT(ISBLANK(C_1[[#This Row],[DESCRIPTION - INFORMATION LOG]])), C_1[[#This Row],[DESCRIPTION - INFORMATION LOG]] <> "DESCRIPTION - INFORMATION LOG" ), NOT(ISBLANK(C_1[[#This Row],[ACTION REQUIRED]])) ), "Y", "N" ) -> Y
A82: L01 | B82: STAIR 6 LIGHTING | C82: ACTION | D82: OPEN | E82: 17.12: installation +/- midle of march 21.01: Delivery by end of February/ begining of march 18.02: Lamps have been delivered, scaffold is under installation 23.02 Scafolds are in place 27.02: Wrong lighting has been sent | F82: 04.03: RPN to issue updated MAS | G82: Medium | H82: 46051 | I82: {=IFERROR(_xlfn.TEXTJOIN(" / ", TRUE, IF(OWNER_LIST[Owner Name]=C_1[[#This Row],[OWNER NAME 1]], OWNER_LIST[Owner ORG], ""), IF(OWNER_LIST[Owner Name]=C_1[[#This Row],[OWNER NAME 2]], OWNER_LIST[Owner ORG], "")), "")} -> RPN | J82: Hacir Degirmencioglu | R82: =_xlfn.CONCAT(C_1[[#This Row],[ESCALATE]], "-",C_1[[#This Row],[Row_PM]]) -> - | S82: =_xlfn.CONCAT(C_1[[#This Row],[ESCALATE]], "-",C_1[[#This Row],[Notify_PM]]) -> -- | T82: =ROW() -> 82 | U82: =IF(C_1[[#This Row],[OWNER NAME 1]] = "", "", IF(_xlfn.XLOOKUP(C_1[[#This Row],[OWNER NAME 1]],OWNER_LIST[Owner Name], OWNER_LIST[Email], "") = "", "", _xlfn.XLOOKUP(C_1[[#This Row],[OWNER NAME 1]], OWNER_LIST[Owner Name], OWNER_LIST[Email], ""))) -> hacir.degirmencioglu@rpn-sa.ch | V82: =IF(C_1[[#This Row],[OWNER NAME 2]] = "", "", IF(_xlfn.XLOOKUP(C_1[[#This Row],[OWNER NAME 2]],OWNER_LIST[Owner Name], OWNER_LIST[Email], "") = "", "", _xlfn.XLOOKUP(C_1[[#This Row],[OWNER NAME 2]], OWNER_LIST[Owner Name], OWNER_LIST[Email], ""))) | W82: =$A$37 -> C1 | X82: =IF( OR( AND( NOT(ISBLANK(C_1[[#This Row],[DESCRIPTION - INFORMATION LOG]])), C_1[[#This Row],[DESCRIPTION - INFORMATION LOG]] <> "DESCRIPTION - INFORMATION LOG" ), NOT(ISBLANK(C_1[[#This Row],[ACTION REQUIRED]])) ), "Y", "N" ) -> Y
A83: L00 | B83: UNTV - Planning | C83: INFO | D83: OPEN | E83: 14.01: Completion of the works by end of February 29.01: Move of equipement from Temporary to new studio: Monday 06.04 WHO/BIT start mid May. (Partial commissioning feasable before move) Move = 2 to 3 days, commissioning = +/- 1week. - 2 weeks move + commissioning - 3 weeks training - 1 week buffer 16.02: Gonogo meeting will take place on 02.04. 1st slot to swap UNTV studio is 07.04 < < 12.05 2nd slot is 13.07 < < Tbc | F83: 26.01: RPN to update planning 18.02: T&C to proceed as planned | G83: High | H83: 46058 | I83: {=IFERROR(_xlfn.TEXTJOIN(" / ", TRUE, IF(OWNER_LIST[Owner Name]=C_1[[#This Row],[OWNER NAME 1]], OWNER_LIST[Owner ORG], ""), IF(OWNER_LIST[Owner Name]=C_1[[#This Row],[OWNER NAME 2]], OWNER_LIST[Owner ORG], "")), "")} -> RPN | J83: Simone Conti | R83: =_xlfn.CONCAT(C_1[[#This Row],[ESCALATE]], "-",C_1[[#This Row],[Row_PM]]) -> - | S83: =_xlfn.CONCAT(C_1[[#This Row],[ESCALATE]], "-",C_1[[#This Row],[Notify_PM]]) -> -- | T83: =ROW() -> 83 | U83: =IF(C_1[[#This Row],[OWNER NAME 1]] = "", "", IF(_xlfn.XLOOKUP(C_1[[#This Row],[OWNER NAME 1]],OWNER_LIST[Owner Name], OWNER_LIST[Email], "") = "", "", _xlfn.XLOOKUP(C_1[[#This Row],[OWNER NAME 1]], OWNER_LIST[Owner Name], OWNER_LIST[Email], ""))) -> simone.conti@cmbcarpi.it | V83: =IF(C_1[[#This Row],[OWNER NAME 2]] = "", "", IF(_xlfn.XLOOKUP(C_1[[#This Row],[OWNER NAME 2]],OWNER_LIST[Owner Name], OWNER_LIST[Email], "") = "", "", _xlfn.XLOOKUP(C_1[[#This Row],[OWNER NAME 2]], OWNER_LIST[Owner Name], OWNER_LIST[Email], ""))) | W83: =$A$37 -> C1 | X83: =IF( OR( AND( NOT(ISBLANK(C_1[[#This Row],[DESCRIPTION - INFORMATION LOG]])), C_1[[#This Row],[DESCRIPTION - INFORMATION LOG]] <> "DESCRIPTION - INFORMATION LOG" ), NOT(ISBLANK(C_1[[#This Row],[ACTION REQUIRED]])) ), "Y", "N" ) -> Y
A84: L00 | B84: UNTV - Security | C84: ACTION | D84: OPEN | E84: 07.11: Sensitive equipment will be soon installed in the studio | F84: 07.11: [Post 12WLA] RPN to enhance security in UNTV as soon equipment will be in place. 17.11: door to dock 5 has not been secured yet. | G84: High | H84: 45973 | I84: {=IFERROR(_xlfn.TEXTJOIN(" / ", TRUE, IF(OWNER_LIST[Owner Name]=C_1[[#This Row],[OWNER NAME 1]], OWNER_LIST[Owner ORG], ""), IF(OWNER_LIST[Owner Name]=C_1[[#This Row],[OWNER NAME 2]], OWNER_LIST[Owner ORG], "")), "")} -> RPN | J84: Matteo Naldi | R84: =_xlfn.CONCAT(C_1[[#This Row],[ESCALATE]], "-",C_1[[#This Row],[Row_PM]]) -> - | S84: =_xlfn.CONCAT(C_1[[#This Row],[ESCALATE]], "-",C_1[[#This Row],[Notify_PM]]) -> -- | T84: =ROW() -> 84 | U84: =IF(C_1[[#This Row],[OWNER NAME 1]] = "", "", IF(_xlfn.XLOOKUP(C_1[[#This Row],[OWNER NAME 1]],OWNER_LIST[Owner Name], OWNER_LIST[Email], "") = "", "", _xlfn.XLOOKUP(C_1[[#This Row],[OWNER NAME 1]], OWNER_LIST[Owner Name], OWNER_LIST[Email], ""))) -> matteo.naldi@cmbcarpi.it | V84: =IF(C_1[[#This Row],[OWNER NAME 2]] = "", "", IF(_xlfn.XLOOKUP(C_1[[#This Row],[OWNER NAME 2]],OWNER_LIST[Owner Name], OWNER_LIST[Email], "") = "", "", _xlfn.XLOOKUP(C_1[[#This Row],[OWNER NAME 2]], OWNER_LIST[Owner Name], OWNER_LIST[Email], ""))) | W84: =$A$37 -> C1 | X84: =IF( OR( AND( NOT(ISBLANK(C_1[[#This Row],[DESCRIPTION - INFORMATION LOG]])), C_1[[#This Row],[DESCRIPTION - INFORMATION LOG]] <> "DESCRIPTION - INFORMATION LOG" ), NOT(ISBLANK(C_1[[#This Row],[ACTION REQUIRED]])) ), "Y", "N" ) -> Y
A85: L00 | B85: UNTV - INS 544 Flash light + PA speaker - RFID 1489 | C85: ACTION | D85: OPEN | E85: 19.11: Flash light / PA speaker missing in Studio 09.01: INS 544 has been submited by SOM 09.01: INS Issued 28.01: Scope is agreed but RPN price is outrageous | F85: 4.02: RPN to revise cost (Engineering) 11.02: EGGTELSA to proceed | G85: TOP | H85: 46057 | I85: {=IFERROR(_xlfn.TEXTJOIN(" / ", TRUE, IF(OWNER_LIST[Owner Name]=C_1[[#This Row],[OWNER NAME 1]], OWNER_LIST[Owner ORG], ""), IF(OWNER_LIST[Owner Name]=C_1[[#This Row],[OWNER NAME 2]], OWNER_LIST[Owner ORG], "")), "")} -> RPN / RPN | J85: Matteo Naldi | K85: Jessica Donatelli | R85: =_xlfn.CONCAT(C_1[[#This Row],[ESCALATE]], "-",C_1[[#This Row],[Row_PM]]) -> - | S85: =_xlfn.CONCAT(C_1[[#This Row],[ESCALATE]], "-",C_1[[#This Row],[Notify_PM]]) -> -- | T85: =ROW() -> 85 | U85: =IF(C_1[[#This Row],[OWNER NAME 1]] = "", "", IF(_xlfn.XLOOKUP(C_1[[#This Row],[OWNER NAME 1]],OWNER_LIST[Owner Name], OWNER_LIST[Email], "") = "", "", _xlfn.XLOOKUP(C_1[[#This Row],[OWNER NAME 1]], OWNER_LIST[Owner Name], OWNER_LIST[Email], ""))) -> matteo.naldi@cmbcarpi.it | V85: =IF(C_1[[#This Row],[OWNER NAME 2]] = "", "", IF(_xlfn.XLOOKUP(C_1[[#This Row],[OWNER NAME 2]],OWNER_LIST[Owner Name], OWNER_LIST[Email], "") = "", "", _xlfn.XLOOKUP(C_1[[#This Row],[OWNER NAME 2]], OWNER_LIST[Owner Name], OWNER_LIST[Email], ""))) -> jessica.donatelli@cmbcarpi.it | W85: =$A$37 -> C1 | X85: =IF( OR( AND( NOT(ISBLANK(C_1[[#This Row],[DESCRIPTION - INFORMATION LOG]])), C_1[[#This Row],[DESCRIPTION - INFORMATION LOG]] <> "DESCRIPTION - INFORMATION LOG" ), NOT(ISBLANK(C_1[[#This Row],[ACTION REQUIRED]])) ), "Y", "N" ) -> Y
A86: L00 | B86: UNTV - Dust in CAR | C86: ACTION | D86: OPEN | E86: 12.02: CAR | F86: 16.02: NCF will be issued regarding dust in CAR | G86: TOP | H86: 46073 | I86: {=IFERROR(_xlfn.TEXTJOIN(" / ", TRUE, IF(OWNER_LIST[Owner Name]=C_1[[#This Row],[OWNER NAME 1]], OWNER_LIST[Owner ORG], ""), IF(OWNER_LIST[Owner Name]=C_1[[#This Row],[OWNER NAME 2]], OWNER_LIST[Owner ORG], "")), "")} -> RPN | J86: Matteo Naldi | R86: =_xlfn.CONCAT(C_1[[#This Row],[ESCALATE]], "-",C_1[[#This Row],[Row_PM]]) -> - | S86: =_xlfn.CONCAT(C_1[[#This Row],[ESCALATE]], "-",C_1[[#This Row],[Notify_PM]]) -> -- | T86: =ROW() -> 86 | U86: =IF(C_1[[#This Row],[OWNER NAME 1]] = "", "", IF(_xlfn.XLOOKUP(C_1[[#This Row],[OWNER NAME 1]],OWNER_LIST[Owner Name], OWNER_LIST[Email], "") = "", "", _xlfn.XLOOKUP(C_1[[#This Row],[OWNER NAME 1]], OWNER_LIST[Owner Name], OWNER_LIST[Email], ""))) -> matteo.naldi@cmbcarpi.it | V86: =IF(C_1[[#This Row],[OWNER NAME 2]] = "", "", IF(_xlfn.XLOOKUP(C_1[[#This Row],[OWNER NAME 2]],OWNER_LIST[Owner Name], OWNER_LIST[Email], "") = "", "", _xlfn.XLOOKUP(C_1[[#This Row],[OWNER NAME 2]], OWNER_LIST[Owner Name], OWNER_LIST[Email], ""))) | W86: =$A$37 -> C1 | X86: =IF( OR( AND( NOT(ISBLANK(C_1[[#This Row],[DESCRIPTION - INFORMATION LOG]])), C_1[[#This Row],[DESCRIPTION - INFORMATION LOG]] <> "DESCRIPTION - INFORMATION LOG" ), NOT(ISBLANK(C_1[[#This Row],[ACTION REQUIRED]])) ), "Y", "N" ) -> Y
A87: L00 | B87: AV display - VAR 490 | C87: ACTION | D87: OPEN | E87: 04.02: SHP to update VAR 490 09.03: Issue with Marble on C6 entrance | F87: 09.02: RPN to submit proposal (Concordia) SHP to revise VAR (2 displays in Bldg.C 46" => 55") 09.03: SHP to assess definitive position | G87: High | H87: 46080 | I87: {=IFERROR(_xlfn.TEXTJOIN(" / ", TRUE, IF(OWNER_LIST[Owner Name]=C_1[[#This Row],[OWNER NAME 1]], OWNER_LIST[Owner ORG], ""), IF(OWNER_LIST[Owner Name]=C_1[[#This Row],[OWNER NAME 2]], OWNER_LIST[Owner ORG], "")), "")} -> SHP / SHP | J87: Maximilien Montanaro | K87: Patrick Vogelsang | R87: =_xlfn.CONCAT(C_1[[#This Row],[ESCALATE]], "-",C_1[[#This Row],[Row_PM]]) -> - | S87: =_xlfn.CONCAT(C_1[[#This Row],[ESCALATE]], "-",C_1[[#This Row],[Notify_PM]]) -> -- | T87: =ROW() -> 87 | U87: =IF(C_1[[#This Row],[OWNER NAME 1]] = "", "", IF(_xlfn.XLOOKUP(C_1[[#This Row],[OWNER NAME 1]],OWNER_LIST[Owner Name], OWNER_LIST[Email], "") = "", "", _xlfn.XLOOKUP(C_1[[#This Row],[OWNER NAME 1]], OWNER_LIST[Owner Name], OWNER_LIST[Email], ""))) -> maximilien.montanaro@un.org | V87: =IF(C_1[[#This Row],[OWNER NAME 2]] = "", "", IF(_xlfn.XLOOKUP(C_1[[#This Row],[OWNER NAME 2]],OWNER_LIST[Owner Name], OWNER_LIST[Email], "") = "", "", _xlfn.XLOOKUP(C_1[[#This Row],[OWNER NAME 2]], OWNER_LIST[Owner Name], OWNER_LIST[Email], ""))) -> patrick.vogelsang@un.org | W87: =$A$37 -> C1 | X87: =IF( OR( AND( NOT(ISBLANK(C_1[[#This Row],[DESCRIPTION - INFORMATION LOG]])), C_1[[#This Row],[DESCRIPTION - INFORMATION LOG]] <> "DESCRIPTION - INFORMATION LOG" ), NOT(ISBLANK(C_1[[#This Row],[ACTION REQUIRED]])) ), "Y", "N" ) -> Y
A88: L00 | B88: PRESS BAR - MEDIA CENTER AREA C.2.3 - VAR 649, (INS 524), 6# Optical Fiber conection | C88: ACTION | D88: OPEN | E88: 10.10: 8 additional BNC sockets to be installed in Press bar Lake side windows 07.11: [Post 12WLA Note] SHP issued draft INS. 10.11: INS have been issued. 25.11: UNIS have approved the proposal as per INS 524. 03.12: RPN submited step 2, VAR requested 21.01: VAR step 1 has been issued 26.01: Step 1 has been submitted 29.01: Step 3 has been issued 11.02: rack for 2 converters to be located boths side of entrance C23 18.02: CDP contract for the broadcast, dwg are required for the IT part | F88: 16.02 RPN to issue commercial proposal 23.02: RPN to issue commercial proposal 04.03: RPN to assess TIA | G88: High | H88: 46055 | I88: {=IFERROR(_xlfn.TEXTJOIN(" / ", TRUE, IF(OWNER_LIST[Owner Name]=C_1[[#This Row],[OWNER NAME 1]], OWNER_LIST[Owner ORG], ""), IF(OWNER_LIST[Owner Name]=C_1[[#This Row],[OWNER NAME 2]], OWNER_LIST[Owner ORG], "")), "")} -> RPN / RPN | J88: Jessica Donatelli | K88: Federica Brunone | R88: =_xlfn.CONCAT(C_1[[#This Row],[ESCALATE]], "-",C_1[[#This Row],[Row_PM]]) -> - | S88: =_xlfn.CONCAT(C_1[[#This Row],[ESCALATE]], "-",C_1[[#This Row],[Notify_PM]]) -> -- | T88: =ROW() -> 88 | U88: =IF(C_1[[#This Row],[OWNER NAME 1]] = "", "", IF(_xlfn.XLOOKUP(C_1[[#This Row],[OWNER NAME 1]],OWNER_LIST[Owner Name], OWNER_LIST[Email], "") = "", "", _xlfn.XLOOKUP(C_1[[#This Row],[OWNER NAME 1]], OWNER_LIST[Owner Name], OWNER_LIST[Email], ""))) -> jessica.donatelli@cmbcarpi.it | V88: =IF(C_1[[#This Row],[OWNER NAME 2]] = "", "", IF(_xlfn.XLOOKUP(C_1[[#This Row],[OWNER NAME 2]],OWNER_LIST[Owner Name], OWNER_LIST[Email], "") = "", "", _xlfn.XLOOKUP(C_1[[#This Row],[OWNER NAME 2]], OWNER_LIST[Owner Name], OWNER_LIST[Email], ""))) -> federica.brunone@cmbcarpi.it | W88: =$A$37 -> C1 | X88: =IF( OR( AND( NOT(ISBLANK(C_1[[#This Row],[DESCRIPTION - INFORMATION LOG]])), C_1[[#This Row],[DESCRIPTION - INFORMATION LOG]] <> "DESCRIPTION - INFORMATION LOG" ), NOT(ISBLANK(C_1[[#This Row],[ACTION REQUIRED]])) ), "Y", "N" ) -> Y
A89: L00 | B89: PRESS BAR - INS 512 TC3-C4-2 storage (VAR Canceled) | C89: ACTION | D89: OPEN | E89: 18.02: Newly build partition to be demolished | F89: 18.02: SHP to review INS, | G89: Medium | H89: 46073 | I89: {=IFERROR(_xlfn.TEXTJOIN(" / ", TRUE, IF(OWNER_LIST[Owner Name]=C_1[[#This Row],[OWNER NAME 1]], OWNER_LIST[Owner ORG], ""), IF(OWNER_LIST[Owner Name]=C_1[[#This Row],[OWNER NAME 2]], OWNER_LIST[Owner ORG], "")), "")} -> SHP | J89: Jean-Mathieu Ferre | R89: =_xlfn.CONCAT(C_1[[#This Row],[ESCALATE]], "-",C_1[[#This Row],[Row_PM]]) -> - | S89: =_xlfn.CONCAT(C_1[[#This Row],[ESCALATE]], "-",C_1[[#This Row],[Notify_PM]]) -> -- | T89: =ROW() -> 89 | U89: =IF(C_1[[#This Row],[OWNER NAME 1]] = "", "", IF(_xlfn.XLOOKUP(C_1[[#This Row],[OWNER NAME 1]],OWNER_LIST[Owner Name], OWNER_LIST[Email], "") = "", "", _xlfn.XLOOKUP(C_1[[#This Row],[OWNER NAME 1]], OWNER_LIST[Owner Name], OWNER_LIST[Email], ""))) -> jean.ferre@un.org | V89: =IF(C_1[[#This Row],[OWNER NAME 2]] = "", "", IF(_xlfn.XLOOKUP(C_1[[#This Row],[OWNER NAME 2]],OWNER_LIST[Owner Name], OWNER_LIST[Email], "") = "", "", _xlfn.XLOOKUP(C_1[[#This Row],[OWNER NAME 2]], OWNER_LIST[Owner Name], OWNER_LIST[Email], ""))) | W89: =$A$37 -> C1 | X89: =IF( OR( AND( NOT(ISBLANK(C_1[[#This Row],[DESCRIPTION - INFORMATION LOG]])), C_1[[#This Row],[DESCRIPTION - INFORMATION LOG]] <> "DESCRIPTION - INFORMATION LOG" ), NOT(ISBLANK(C_1[[#This Row],[ACTION REQUIRED]])) ), "Y", "N" ) -> Y
A90: L00 | B90: PRESS BAR - Cingria mockup | C90: ACTION | D90: OPEN | E90: 26.08: RPN to present a mockup (corner detail by VIGANO) + 1st installation as prototype 17.09: RPN to confirm 24.09: mock up to be presented 10.10. 22.10: RPN to confirm mock up presentation 14.01: RPN to confirm mock up presentation 18.02: no date provided by RPN | F90: 28.01: Mockup is planned for the 9-10.02 18.02: SHP will request a visit to Vigano 25.02: Mockup to be presented 04.03. 09.03: Cingria is expected for Monday 16.03. | G90: High | H90: 45965 | I90: {=IFERROR(_xlfn.TEXTJOIN(" / ", TRUE, IF(OWNER_LIST[Owner Name]=C_1[[#This Row],[OWNER NAME 1]], OWNER_LIST[Owner ORG], ""), IF(OWNER_LIST[Owner Name]=C_1[[#This Row],[OWNER NAME 2]], OWNER_LIST[Owner ORG], "")), "")} -> RPN / RPN | J90: Matteo Naldi | K90: Chiara Re Depaolini | R90: =_xlfn.CONCAT(C_1[[#This Row],[ESCALATE]], "-",C_1[[#This Row],[Row_PM]]) -> - | S90: =_xlfn.CONCAT(C_1[[#This Row],[ESCALATE]], "-",C_1[[#This Row],[Notify_PM]]) -> -- | T90: =ROW() -> 90 | U90: =IF(C_1[[#This Row],[OWNER NAME 1]] = "", "", IF(_xlfn.XLOOKUP(C_1[[#This Row],[OWNER NAME 1]],OWNER_LIST[Owner Name], OWNER_LIST[Email], "") = "", "", _xlfn.XLOOKUP(C_1[[#This Row],[OWNER NAME 1]], OWNER_LIST[Owner Name], OWNER_LIST[Email], ""))) -> matteo.naldi@cmbcarpi.it | V90: =IF(C_1[[#This Row],[OWNER NAME 2]] = "", "", IF(_xlfn.XLOOKUP(C_1[[#This Row],[OWNER NAME 2]],OWNER_LIST[Owner Name], OWNER_LIST[Email], "") = "", "", _xlfn.XLOOKUP(C_1[[#This Row],[OWNER NAME 2]], OWNER_LIST[Owner Name], OWNER_LIST[Email], ""))) -> chiara.redepaolini@rpn-sa.ch | W90: =$A$37 -> C1 | X90: =IF( OR( AND( NOT(ISBLANK(C_1[[#This Row],[DESCRIPTION - INFORMATION LOG]])), C_1[[#This Row],[DESCRIPTION - INFORMATION LOG]] <> "DESCRIPTION - INFORMATION LOG" ), NOT(ISBLANK(C_1[[#This Row],[ACTION REQUIRED]])) ), "Y", "N" ) -> Y
A91: L00 | B91: PRESS BAR - Kitchen equipment | C91: ACTION | D91: OPEN | E91: 01.10: Equipment to be delivered mid November 15.12: delivery of Kitchen equipment has been posponed BAR will be delivered at the last minutes 28.01: Installation of equipment have not started | F91: 07.01: ceramic tiles under installation. Kitchen equipment instalation to start before end of Jan => 16.02 | G91: Medium | H91: 45976 | I91: {=IFERROR(_xlfn.TEXTJOIN(" / ", TRUE, IF(OWNER_LIST[Owner Name]=C_1[[#This Row],[OWNER NAME 1]], OWNER_LIST[Owner ORG], ""), IF(OWNER_LIST[Owner Name]=C_1[[#This Row],[OWNER NAME 2]], OWNER_LIST[Owner ORG], "")), "")} -> RPN | J91: Matteo Naldi | R91: =_xlfn.CONCAT(C_1[[#This Row],[ESCALATE]], "-",C_1[[#This Row],[Row_PM]]) -> - | S91: =_xlfn.CONCAT(C_1[[#This Row],[ESCALATE]], "-",C_1[[#This Row],[Notify_PM]]) -> -- | T91: =ROW() -> 91 | U91: =IF(C_1[[#This Row],[OWNER NAME 1]] = "", "", IF(_xlfn.XLOOKUP(C_1[[#This Row],[OWNER NAME 1]],OWNER_LIST[Owner Name], OWNER_LIST[Email], "") = "", "", _xlfn.XLOOKUP(C_1[[#This Row],[OWNER NAME 1]], OWNER_LIST[Owner Name], OWNER_LIST[Email], ""))) -> matteo.naldi@cmbcarpi.it | V91: =IF(C_1[[#This Row],[OWNER NAME 2]] = "", "", IF(_xlfn.XLOOKUP(C_1[[#This Row],[OWNER NAME 2]],OWNER_LIST[Owner Name], OWNER_LIST[Email], "") = "", "", _xlfn.XLOOKUP(C_1[[#This Row],[OWNER NAME 2]], OWNER_LIST[Owner Name], OWNER_LIST[Email], ""))) | W91: =$A$37 -> C1 | X91: =IF( OR( AND( NOT(ISBLANK(C_1[[#This Row],[DESCRIPTION - INFORMATION LOG]])), C_1[[#This Row],[DESCRIPTION - INFORMATION LOG]] <> "DESCRIPTION - INFORMATION LOG" ), NOT(ISBLANK(C_1[[#This Row],[ACTION REQUIRED]])) ), "Y", "N" ) -> Y
A92: L00 | B92: PRESS BAR - Furnitures | C92: INFO | D92: OPEN | E92: 08.12: Enamelled CP tables to be restored (surface repair), heightened (leg extension?) + protective glass to be added on top 19.01: Dwg approved as noted | G92: Medium | R92: =_xlfn.CONCAT(C_1[[#This Row],[ESCALATE]], "-",C_1[[#This Row],[Row_PM]]) -> - | S92: =_xlfn.CONCAT(C_1[[#This Row],[ESCALATE]], "-",C_1[[#This Row],[Notify_PM]]) -> -- | T92: =ROW() -> 92 | U92: =IF(C_1[[#This Row],[OWNER NAME 1]] = "", "", IF(_xlfn.XLOOKUP(C_1[[#This Row],[OWNER NAME 1]],OWNER_LIST[Owner Name], OWNER_LIST[Email], "") = "", "", _xlfn.XLOOKUP(C_1[[#This Row],[OWNER NAME 1]], OWNER_LIST[Owner Name], OWNER_LIST[Email], ""))) | V92: =IF(C_1[[#This Row],[OWNER NAME 2]] = "", "", IF(_xlfn.XLOOKUP(C_1[[#This Row],[OWNER NAME 2]],OWNER_LIST[Owner Name], OWNER_LIST[Email], "") = "", "", _xlfn.XLOOKUP(C_1[[#This Row],[OWNER NAME 2]], OWNER_LIST[Owner Name], OWNER_LIST[Email], ""))) | W92: =$A$37 -> C1 | X92: =IF( OR( AND( NOT(ISBLANK(C_1[[#This Row],[DESCRIPTION - INFORMATION LOG]])), C_1[[#This Row],[DESCRIPTION - INFORMATION LOG]] <> "DESCRIPTION - INFORMATION LOG" ), NOT(ISBLANK(C_1[[#This Row],[ACTION REQUIRED]])) ), "Y", "N" ) -> Y
A93: L00 | B93: PRESS BAR - Toilets | C93: ACTION | D93: OPEN | E93: 01.10: Toilets have been completed with C status. | F93: 01.10: RPN/ SOMBP to inspect | G93: Medium | H93: 45933 | I93: {=IFERROR(_xlfn.TEXTJOIN(" / ", TRUE, IF(OWNER_LIST[Owner Name]=C_1[[#This Row],[OWNER NAME 1]], OWNER_LIST[Owner ORG], ""), IF(OWNER_LIST[Owner Name]=C_1[[#This Row],[OWNER NAME 2]], OWNER_LIST[Owner ORG], "")), "")} -> RPN / SOMBP | J93: Matteo Naldi | K93: Lucille Treille de Grandsaigne | R93: =_xlfn.CONCAT(C_1[[#This Row],[ESCALATE]], "-",C_1[[#This Row],[Row_PM]]) -> - | S93: =_xlfn.CONCAT(C_1[[#This Row],[ESCALATE]], "-",C_1[[#This Row],[Notify_PM]]) -> -- | T93: =ROW() -> 93 | U93: =IF(C_1[[#This Row],[OWNER NAME 1]] = "", "", IF(_xlfn.XLOOKUP(C_1[[#This Row],[OWNER NAME 1]],OWNER_LIST[Owner Name], OWNER_LIST[Email], "") = "", "", _xlfn.XLOOKUP(C_1[[#This Row],[OWNER NAME 1]], OWNER_LIST[Owner Name], OWNER_LIST[Email], ""))) -> matteo.naldi@cmbcarpi.it | V93: =IF(C_1[[#This Row],[OWNER NAME 2]] = "", "", IF(_xlfn.XLOOKUP(C_1[[#This Row],[OWNER NAME 2]],OWNER_LIST[Owner Name], OWNER_LIST[Email], "") = "", "", _xlfn.XLOOKUP(C_1[[#This Row],[OWNER NAME 2]], OWNER_LIST[Owner Name], OWNER_LIST[Email], ""))) -> lucille.treilledegrandsaigne@burckhardt.swiss | W93: =$A$37 -> C1 | X93: =IF( OR( AND( NOT(ISBLANK(C_1[[#This Row],[DESCRIPTION - INFORMATION LOG]])), C_1[[#This Row],[DESCRIPTION - INFORMATION LOG]] <> "DESCRIPTION - INFORMATION LOG" ), NOT(ISBLANK(C_1[[#This Row],[ACTION REQUIRED]])) ), "Y", "N" ) -> Y
A94: L00 | B94: PRESS BAR - VAR 569 Water Fountain | C94: ACTION | D94: OPEN | E94: 21.10: Step 4 has been issued 04.03: No water fountain to be installed | G94: High | R94: =_xlfn.CONCAT(C_1[[#This Row],[ESCALATE]], "-",C_1[[#This Row],[Row_PM]]) -> - | S94: =_xlfn.CONCAT(C_1[[#This Row],[ESCALATE]], "-",C_1[[#This Row],[Notify_PM]]) -> -- | T94: =ROW() -> 94 | U94: =IF(C_1[[#This Row],[OWNER NAME 1]] = "", "", IF(_xlfn.XLOOKUP(C_1[[#This Row],[OWNER NAME 1]],OWNER_LIST[Owner Name], OWNER_LIST[Email], "") = "", "", _xlfn.XLOOKUP(C_1[[#This Row],[OWNER NAME 1]], OWNER_LIST[Owner Name], OWNER_LIST[Email], ""))) | V94: =IF(C_1[[#This Row],[OWNER NAME 2]] = "", "", IF(_xlfn.XLOOKUP(C_1[[#This Row],[OWNER NAME 2]],OWNER_LIST[Owner Name], OWNER_LIST[Email], "") = "", "", _xlfn.XLOOKUP(C_1[[#This Row],[OWNER NAME 2]], OWNER_LIST[Owner Name], OWNER_LIST[Email], ""))) | W94: =$A$37 -> C1 | X94: =IF( OR( AND( NOT(ISBLANK(C_1[[#This Row],[DESCRIPTION - INFORMATION LOG]])), C_1[[#This Row],[DESCRIPTION - INFORMATION LOG]] <> "DESCRIPTION - INFORMATION LOG" ), NOT(ISBLANK(C_1[[#This Row],[ACTION REQUIRED]])) ), "Y", "N" ) -> Y
A95: L00 | B95: UBS - Autorization to operate | C95: INFO | D95: OPEN | E95: 08.05: UBS asked if they could officially be in the building right after Substantial completion | F95: 08.05: SHP to confirm if UBS can start pperation after substantial completion | G95: Low | H95: 45807 | I95: {=IFERROR(_xlfn.TEXTJOIN(" / ", TRUE, IF(OWNER_LIST[Owner Name]=C_1[[#This Row],[OWNER NAME 1]], OWNER_LIST[Owner ORG], ""), IF(OWNER_LIST[Owner Name]=C_1[[#This Row],[OWNER NAME 2]], OWNER_LIST[Owner ORG], "")), "")} -> SHP | J95: Didier Chessel | R95: =_xlfn.CONCAT(C_1[[#This Row],[ESCALATE]], "-",C_1[[#This Row],[Row_PM]]) -> - | S95: =_xlfn.CONCAT(C_1[[#This Row],[ESCALATE]], "-",C_1[[#This Row],[Notify_PM]]) -> -- | T95: =ROW() -> 95 | U95: =IF(C_1[[#This Row],[OWNER NAME 1]] = "", "", IF(_xlfn.XLOOKUP(C_1[[#This Row],[OWNER NAME 1]],OWNER_LIST[Owner Name], OWNER_LIST[Email], "") = "", "", _xlfn.XLOOKUP(C_1[[#This Row],[OWNER NAME 1]], OWNER_LIST[Owner Name], OWNER_LIST[Email], ""))) -> didier.chessel@un.org | V95: =IF(C_1[[#This Row],[OWNER NAME 2]] = "", "", IF(_xlfn.XLOOKUP(C_1[[#This Row],[OWNER NAME 2]],OWNER_LIST[Owner Name], OWNER_LIST[Email], "") = "", "", _xlfn.XLOOKUP(C_1[[#This Row],[OWNER NAME 2]], OWNER_LIST[Owner Name], OWNER_LIST[Email], ""))) | W95: =$A$37 -> C1 | X95: =IF( OR( AND( NOT(ISBLANK(C_1[[#This Row],[DESCRIPTION - INFORMATION LOG]])), C_1[[#This Row],[DESCRIPTION - INFORMATION LOG]] <> "DESCRIPTION - INFORMATION LOG" ), NOT(ISBLANK(C_1[[#This Row],[ACTION REQUIRED]])) ), "Y", "N" ) -> Y
A96: L00 | B96: UBS - Remaining works | C96: INFO | D96: OPEN | E96: 09.10: UBS to come back on site by the end of February 04.03: DI cables have been installed 04.03: PA cable will be pulled this week. | F96: 09.10: SHP to confirm date when site condition will allow UBS to start completing works. | G96: High | H96: 45962 | I96: {=IFERROR(_xlfn.TEXTJOIN(" / ", TRUE, IF(OWNER_LIST[Owner Name]=C_1[[#This Row],[OWNER NAME 1]], OWNER_LIST[Owner ORG], ""), IF(OWNER_LIST[Owner Name]=C_1[[#This Row],[OWNER NAME 2]], OWNER_LIST[Owner ORG], "")), "")} -> RPN | J96: Leonardo Valentinotti | R96: =_xlfn.CONCAT(C_1[[#This Row],[ESCALATE]], "-",C_1[[#This Row],[Row_PM]]) -> - | S96: =_xlfn.CONCAT(C_1[[#This Row],[ESCALATE]], "-",C_1[[#This Row],[Notify_PM]]) -> -- | T96: =ROW() -> 96 | U96: =IF(C_1[[#This Row],[OWNER NAME 1]] = "", "", IF(_xlfn.XLOOKUP(C_1[[#This Row],[OWNER NAME 1]],OWNER_LIST[Owner Name], OWNER_LIST[Email], "") = "", "", _xlfn.XLOOKUP(C_1[[#This Row],[OWNER NAME 1]], OWNER_LIST[Owner Name], OWNER_LIST[Email], ""))) -> leonardo.valentinotti@rpn-sa.ch | V96: =IF(C_1[[#This Row],[OWNER NAME 2]] = "", "", IF(_xlfn.XLOOKUP(C_1[[#This Row],[OWNER NAME 2]],OWNER_LIST[Owner Name], OWNER_LIST[Email], "") = "", "", _xlfn.XLOOKUP(C_1[[#This Row],[OWNER NAME 2]], OWNER_LIST[Owner Name], OWNER_LIST[Email], ""))) | W96: =$A$37 -> C1 | X96: =IF( OR( AND( NOT(ISBLANK(C_1[[#This Row],[DESCRIPTION - INFORMATION LOG]])), C_1[[#This Row],[DESCRIPTION - INFORMATION LOG]] <> "DESCRIPTION - INFORMATION LOG" ), NOT(ISBLANK(C_1[[#This Row],[ACTION REQUIRED]])) ), "Y", "N" ) -> Y
A97: L00 | B97: UBS - Dedicated FIBER | C97: ACTION | D97: OPEN | E97: 15.10: Federica email has been answered 10.11: UBS will have its own Fiber with dedicated provider (from T.17) 03.12: RPN is blocking the execution | F97: 10.11: SHP/ RPN to check UBS IT dwg. In case unforeseen complication, alternative to be found. 03.12: RPN to clarify commercial position | G97: Medium | H97: 45962 | I97: {=IFERROR(_xlfn.TEXTJOIN(" / ", TRUE, IF(OWNER_LIST[Owner Name]=C_1[[#This Row],[OWNER NAME 1]], OWNER_LIST[Owner ORG], ""), IF(OWNER_LIST[Owner Name]=C_1[[#This Row],[OWNER NAME 2]], OWNER_LIST[Owner ORG], "")), "")} -> SHP | J97: Jean-Mathieu Ferre | R97: =_xlfn.CONCAT(C_1[[#This Row],[ESCALATE]], "-",C_1[[#This Row],[Row_PM]]) -> - | S97: =_xlfn.CONCAT(C_1[[#This Row],[ESCALATE]], "-",C_1[[#This Row],[Notify_PM]]) -> -- | T97: =ROW() -> 97 | U97: =IF(C_1[[#This Row],[OWNER NAME 1]] = "", "", IF(_xlfn.XLOOKUP(C_1[[#This Row],[OWNER NAME 1]],OWNER_LIST[Owner Name], OWNER_LIST[Email], "") = "", "", _xlfn.XLOOKUP(C_1[[#This Row],[OWNER NAME 1]], OWNER_LIST[Owner Name], OWNER_LIST[Email], ""))) -> jean.ferre@un.org | V97: =IF(C_1[[#This Row],[OWNER NAME 2]] = "", "", IF(_xlfn.XLOOKUP(C_1[[#This Row],[OWNER NAME 2]],OWNER_LIST[Owner Name], OWNER_LIST[Email], "") = "", "", _xlfn.XLOOKUP(C_1[[#This Row],[OWNER NAME 2]], OWNER_LIST[Owner Name], OWNER_LIST[Email], ""))) | W97: =$A$37 -> C1 | X97: =IF( OR( AND( NOT(ISBLANK(C_1[[#This Row],[DESCRIPTION - INFORMATION LOG]])), C_1[[#This Row],[DESCRIPTION - INFORMATION LOG]] <> "DESCRIPTION - INFORMATION LOG" ), NOT(ISBLANK(C_1[[#This Row],[ACTION REQUIRED]])) ), "Y", "N" ) -> Y
A98: L00 | B98: UBS - Automated windows | C98: ACTION | D98: OPEN | E98: 25.11: UBS equiped with double flow ventilation. UBS required all windows to be locked. | F98: 25.11: RPN to ensure windows can not be opened Windows are linked to smoke exhaust? | G98: Medium | H98: 45978 | I98: {=IFERROR(_xlfn.TEXTJOIN(" / ", TRUE, IF(OWNER_LIST[Owner Name]=C_1[[#This Row],[OWNER NAME 1]], OWNER_LIST[Owner ORG], ""), IF(OWNER_LIST[Owner Name]=C_1[[#This Row],[OWNER NAME 2]], OWNER_LIST[Owner ORG], "")), "")} -> RPN | J98: Hacir Degirmencioglu | R98: =_xlfn.CONCAT(C_1[[#This Row],[ESCALATE]], "-",C_1[[#This Row],[Row_PM]]) -> - | S98: =_xlfn.CONCAT(C_1[[#This Row],[ESCALATE]], "-",C_1[[#This Row],[Notify_PM]]) -> -- | T98: =ROW() -> 98 | U98: =IF(C_1[[#This Row],[OWNER NAME 1]] = "", "", IF(_xlfn.XLOOKUP(C_1[[#This Row],[OWNER NAME 1]],OWNER_LIST[Owner Name], OWNER_LIST[Email], "") = "", "", _xlfn.XLOOKUP(C_1[[#This Row],[OWNER NAME 1]], OWNER_LIST[Owner Name], OWNER_LIST[Email], ""))) -> hacir.degirmencioglu@rpn-sa.ch | V98: =IF(C_1[[#This Row],[OWNER NAME 2]] = "", "", IF(_xlfn.XLOOKUP(C_1[[#This Row],[OWNER NAME 2]],OWNER_LIST[Owner Name], OWNER_LIST[Email], "") = "", "", _xlfn.XLOOKUP(C_1[[#This Row],[OWNER NAME 2]], OWNER_LIST[Owner Name], OWNER_LIST[Email], ""))) | W98: =$A$37 -> C1 | X98: =IF( OR( AND( NOT(ISBLANK(C_1[[#This Row],[DESCRIPTION - INFORMATION LOG]])), C_1[[#This Row],[DESCRIPTION - INFORMATION LOG]] <> "DESCRIPTION - INFORMATION LOG" ), NOT(ISBLANK(C_1[[#This Row],[ACTION REQUIRED]])) ), "Y", "N" ) -> Y
A99: L00 | B99: INS 512 - TC3 storage partition | C99: ACTION | D99: OPEN | E99: 11.02: INS has been canceled. 11.02: specialist to confirm potential normative issues if wall is not compliant. wall to be demolished. | F99: 11.02: RPN to submit RFI if any normative issue | G99: High | H99: 46071 | I99: {=IFERROR(_xlfn.TEXTJOIN(" / ", TRUE, IF(OWNER_LIST[Owner Name]=C_1[[#This Row],[OWNER NAME 1]], OWNER_LIST[Owner ORG], ""), IF(OWNER_LIST[Owner Name]=C_1[[#This Row],[OWNER NAME 2]], OWNER_LIST[Owner ORG], "")), "")} -> RPN / RPN | J99: Hacir Degirmencioglu | K99: Matteo Naldi | R99: =_xlfn.CONCAT(C_1[[#This Row],[ESCALATE]], "-",C_1[[#This Row],[Row_PM]]) -> - | S99: =_xlfn.CONCAT(C_1[[#This Row],[ESCALATE]], "-",C_1[[#This Row],[Notify_PM]]) -> -- | T99: =ROW() -> 99 | U99: =IF(C_1[[#This Row],[OWNER NAME 1]] = "", "", IF(_xlfn.XLOOKUP(C_1[[#This Row],[OWNER NAME 1]],OWNER_LIST[Owner Name], OWNER_LIST[Email], "") = "", "", _xlfn.XLOOKUP(C_1[[#This Row],[OWNER NAME 1]], OWNER_LIST[Owner Name], OWNER_LIST[Email], ""))) -> hacir.degirmencioglu@rpn-sa.ch | V99: =IF(C_1[[#This Row],[OWNER NAME 2]] = "", "", IF(_xlfn.XLOOKUP(C_1[[#This Row],[OWNER NAME 2]],OWNER_LIST[Owner Name], OWNER_LIST[Email], "") = "", "", _xlfn.XLOOKUP(C_1[[#This Row],[OWNER NAME 2]], OWNER_LIST[Owner Name], OWNER_LIST[Email], ""))) -> matteo.naldi@cmbcarpi.it | W99: =$A$37 -> C1 | X99: =IF( OR( AND( NOT(ISBLANK(C_1[[#This Row],[DESCRIPTION - INFORMATION LOG]])), C_1[[#This Row],[DESCRIPTION - INFORMATION LOG]] <> "DESCRIPTION - INFORMATION LOG" ), NOT(ISBLANK(C_1[[#This Row],[ACTION REQUIRED]])) ), "Y", "N" ) -> Y
A100: LB01 | B100: SALLE C6 - Interpretor booth | C100: ACTION | D100: OPEN | E100: 11.02: Vibrasto installation started 18.02: Ceiling to be completed next week | F100: 18.02: Acoustic test to be launched as soon the doors have been installed | G100: TOP | I100: {=IFERROR(_xlfn.TEXTJOIN(" / ", TRUE, IF(OWNER_LIST[Owner Name]=C_1[[#This Row],[OWNER NAME 1]], OWNER_LIST[Owner ORG], ""), IF(OWNER_LIST[Owner Name]=C_1[[#This Row],[OWNER NAME 2]], OWNER_LIST[Owner ORG], "")), "")} | R100: =_xlfn.CONCAT(C_1[[#This Row],[ESCALATE]], "-",C_1[[#This Row],[Row_PM]]) -> - | S100: =_xlfn.CONCAT(C_1[[#This Row],[ESCALATE]], "-",C_1[[#This Row],[Notify_PM]]) -> -- | T100: =ROW() -> 100 | U100: =IF(C_1[[#This Row],[OWNER NAME 1]] = "", "", IF(_xlfn.XLOOKUP(C_1[[#This Row],[OWNER NAME 1]],OWNER_LIST[Owner Name], OWNER_LIST[Email], "") = "", "", _xlfn.XLOOKUP(C_1[[#This Row],[OWNER NAME 1]], OWNER_LIST[Owner Name], OWNER_LIST[Email], ""))) | V100: =IF(C_1[[#This Row],[OWNER NAME 2]] = "", "", IF(_xlfn.XLOOKUP(C_1[[#This Row],[OWNER NAME 2]],OWNER_LIST[Owner Name], OWNER_LIST[Email], "") = "", "", _xlfn.XLOOKUP(C_1[[#This Row],[OWNER NAME 2]], OWNER_LIST[Owner Name], OWNER_LIST[Email], ""))) | W100: =$A$37 -> C1 | X100: =IF( OR( AND( NOT(ISBLANK(C_1[[#This Row],[DESCRIPTION - INFORMATION LOG]])), C_1[[#This Row],[DESCRIPTION - INFORMATION LOG]] <> "DESCRIPTION - INFORMATION LOG" ), NOT(ISBLANK(C_1[[#This Row],[ACTION REQUIRED]])) ), "Y", "N" ) -> Y
A101: LB01 | B101: SALLE C6 - Furniture | C101: ACTION | D101: OPEN | E101: 11.02: Furniture supplier to arrive begining of march | F101: 25.02: Benchmark to be presented +/- 04.03. | G101: Medium | H101: 46085 | I101: {=IFERROR(_xlfn.TEXTJOIN(" / ", TRUE, IF(OWNER_LIST[Owner Name]=C_1[[#This Row],[OWNER NAME 1]], OWNER_LIST[Owner ORG], ""), IF(OWNER_LIST[Owner Name]=C_1[[#This Row],[OWNER NAME 2]], OWNER_LIST[Owner ORG], "")), "")} -> RPN | J101: Matteo Naldi | R101: =_xlfn.CONCAT(C_1[[#This Row],[ESCALATE]], "-",C_1[[#This Row],[Row_PM]]) -> - | S101: =_xlfn.CONCAT(C_1[[#This Row],[ESCALATE]], "-",C_1[[#This Row],[Notify_PM]]) -> -- | T101: =ROW() -> 101 | U101: =IF(C_1[[#This Row],[OWNER NAME 1]] = "", "", IF(_xlfn.XLOOKUP(C_1[[#This Row],[OWNER NAME 1]],OWNER_LIST[Owner Name], OWNER_LIST[Email], "") = "", "", _xlfn.XLOOKUP(C_1[[#This Row],[OWNER NAME 1]], OWNER_LIST[Owner Name], OWNER_LIST[Email], ""))) -> matteo.naldi@cmbcarpi.it | V101: =IF(C_1[[#This Row],[OWNER NAME 2]] = "", "", IF(_xlfn.XLOOKUP(C_1[[#This Row],[OWNER NAME 2]],OWNER_LIST[Owner Name], OWNER_LIST[Email], "") = "", "", _xlfn.XLOOKUP(C_1[[#This Row],[OWNER NAME 2]], OWNER_LIST[Owner Name], OWNER_LIST[Email], ""))) | W101: =$A$37 -> C1 | X101: =IF( OR( AND( NOT(ISBLANK(C_1[[#This Row],[DESCRIPTION - INFORMATION LOG]])), C_1[[#This Row],[DESCRIPTION - INFORMATION LOG]] <> "DESCRIPTION - INFORMATION LOG" ), NOT(ISBLANK(C_1[[#This Row],[ACTION REQUIRED]])) ), "Y", "N" ) -> Y
A102: LB01 | B102: SALLE C6 - Chinese donation delivery | C102: ACTION | D102: OPEN | E102: 14.01: Shipment of lighting and mosaic is foreseen early feb. delivery mid-end of february | F102: 14.01: RPN to schedule installation of lightings | G102: High | H102: 46082 | I102: {=IFERROR(_xlfn.TEXTJOIN(" / ", TRUE, IF(OWNER_LIST[Owner Name]=C_1[[#This Row],[OWNER NAME 1]], OWNER_LIST[Owner ORG], ""), IF(OWNER_LIST[Owner Name]=C_1[[#This Row],[OWNER NAME 2]], OWNER_LIST[Owner ORG], "")), "")} -> SHP | J102: Jean-Mathieu Ferre | R102: =_xlfn.CONCAT(C_1[[#This Row],[ESCALATE]], "-",C_1[[#This Row],[Row_PM]]) -> - | S102: =_xlfn.CONCAT(C_1[[#This Row],[ESCALATE]], "-",C_1[[#This Row],[Notify_PM]]) -> -- | T102: =ROW() -> 102 | U102: =IF(C_1[[#This Row],[OWNER NAME 1]] = "", "", IF(_xlfn.XLOOKUP(C_1[[#This Row],[OWNER NAME 1]],OWNER_LIST[Owner Name], OWNER_LIST[Email], "") = "", "", _xlfn.XLOOKUP(C_1[[#This Row],[OWNER NAME 1]], OWNER_LIST[Owner Name], OWNER_LIST[Email], ""))) -> jean.ferre@un.org | V102: =IF(C_1[[#This Row],[OWNER NAME 2]] = "", "", IF(_xlfn.XLOOKUP(C_1[[#This Row],[OWNER NAME 2]],OWNER_LIST[Owner Name], OWNER_LIST[Email], "") = "", "", _xlfn.XLOOKUP(C_1[[#This Row],[OWNER NAME 2]], OWNER_LIST[Owner Name], OWNER_LIST[Email], ""))) | W102: =$A$37 -> C1 | X102: =IF( OR( AND( NOT(ISBLANK(C_1[[#This Row],[DESCRIPTION - INFORMATION LOG]])), C_1[[#This Row],[DESCRIPTION - INFORMATION LOG]] <> "DESCRIPTION - INFORMATION LOG" ), NOT(ISBLANK(C_1[[#This Row],[ACTION REQUIRED]])) ), "Y", "N" ) -> Y
A103: LB01 | B103: SALLE C6 - Implementation of Chinese donation electrical devices | C103: ACTION | D103: OPEN | E103: 04.03: SHP wonder that ELECTRICAL dwg have not been updated with chinese donation devices | F103: 04.03: | R103: =_xlfn.CONCAT(C_1[[#This Row],[ESCALATE]], "-",C_1[[#This Row],[Row_PM]]) -> - | S103: =_xlfn.CONCAT(C_1[[#This Row],[ESCALATE]], "-",C_1[[#This Row],[Notify_PM]]) -> -- | T103: =ROW() -> 103 | U103: =IF(C_1[[#This Row],[OWNER NAME 1]] = "", "", IF(_xlfn.XLOOKUP(C_1[[#This Row],[OWNER NAME 1]],OWNER_LIST[Owner Name], OWNER_LIST[Email], "") = "", "", _xlfn.XLOOKUP(C_1[[#This Row],[OWNER NAME 1]], OWNER_LIST[Owner Name], OWNER_LIST[Email], ""))) | V103: =IF(C_1[[#This Row],[OWNER NAME 2]] = "", "", IF(_xlfn.XLOOKUP(C_1[[#This Row],[OWNER NAME 2]],OWNER_LIST[Owner Name], OWNER_LIST[Email], "") = "", "", _xlfn.XLOOKUP(C_1[[#This Row],[OWNER NAME 2]], OWNER_LIST[Owner Name], OWNER_LIST[Email], ""))) | W103: =$A$37 -> C1 | X103: =IF( OR( AND( NOT(ISBLANK(C_1[[#This Row],[DESCRIPTION - INFORMATION LOG]])), C_1[[#This Row],[DESCRIPTION - INFORMATION LOG]] <> "DESCRIPTION - INFORMATION LOG" ), NOT(ISBLANK(C_1[[#This Row],[ACTION REQUIRED]])) ), "Y", "N" ) -> Y
A104: LB01 | B104: SALLE C6 - Stretch Ceiling in staircase | C104: ACTION | D104: OPEN | E104: 24.02: VAR 568 Salle C6 - access stair Emergency Lighting is on the way | F104: 21.01: SHP to send an email to RPN confirming to go ahead with TD SHP to issue INS confirming new position of emergency light | G104: High | H104: 46071 | I104: {=IFERROR(_xlfn.TEXTJOIN(" / ", TRUE, IF(OWNER_LIST[Owner Name]=C_1[[#This Row],[OWNER NAME 1]], OWNER_LIST[Owner ORG], ""), IF(OWNER_LIST[Owner Name]=C_1[[#This Row],[OWNER NAME 2]], OWNER_LIST[Owner ORG], "")), "")} -> SHP | J104: Jean-Mathieu Ferre | R104: =_xlfn.CONCAT(C_1[[#This Row],[ESCALATE]], "-",C_1[[#This Row],[Row_PM]]) -> - | S104: =_xlfn.CONCAT(C_1[[#This Row],[ESCALATE]], "-",C_1[[#This Row],[Notify_PM]]) -> -- | T104: =ROW() -> 104 | U104: =IF(C_1[[#This Row],[OWNER NAME 1]] = "", "", IF(_xlfn.XLOOKUP(C_1[[#This Row],[OWNER NAME 1]],OWNER_LIST[Owner Name], OWNER_LIST[Email], "") = "", "", _xlfn.XLOOKUP(C_1[[#This Row],[OWNER NAME 1]], OWNER_LIST[Owner Name], OWNER_LIST[Email], ""))) -> jean.ferre@un.org | V104: =IF(C_1[[#This Row],[OWNER NAME 2]] = "", "", IF(_xlfn.XLOOKUP(C_1[[#This Row],[OWNER NAME 2]],OWNER_LIST[Owner Name], OWNER_LIST[Email], "") = "", "", _xlfn.XLOOKUP(C_1[[#This Row],[OWNER NAME 2]], OWNER_LIST[Owner Name], OWNER_LIST[Email], ""))) | W104: =$A$37 -> C1 | X104: =IF( OR( AND( NOT(ISBLANK(C_1[[#This Row],[DESCRIPTION - INFORMATION LOG]])), C_1[[#This Row],[DESCRIPTION - INFORMATION LOG]] <> "DESCRIPTION - INFORMATION LOG" ), NOT(ISBLANK(C_1[[#This Row],[ACTION REQUIRED]])) ), "Y", "N" ) -> Y
A105: LB01 | B105: Salle C6 - VAR 658 - Emergency light in staircase | C105: ACTION | D105: OPEN | E105: 25.02: 3 additional Emergency lights have to be modified | F105: 25.02: SHP to issue VAR 09.03: APROTEC to propose new model | G105: High | H105: 46092 | I105: {=IFERROR(_xlfn.TEXTJOIN(" / ", TRUE, IF(OWNER_LIST[Owner Name]=C_1[[#This Row],[OWNER NAME 1]], OWNER_LIST[Owner ORG], ""), IF(OWNER_LIST[Owner Name]=C_1[[#This Row],[OWNER NAME 2]], OWNER_LIST[Owner ORG], "")), "")} -> SHP | J105: Kateryna Starykova | R105: =_xlfn.CONCAT(C_1[[#This Row],[ESCALATE]], "-",C_1[[#This Row],[Row_PM]]) -> - | S105: =_xlfn.CONCAT(C_1[[#This Row],[ESCALATE]], "-",C_1[[#This Row],[Notify_PM]]) -> -- | T105: =ROW() -> 105 | U105: =IF(C_1[[#This Row],[OWNER NAME 1]] = "", "", IF(_xlfn.XLOOKUP(C_1[[#This Row],[OWNER NAME 1]],OWNER_LIST[Owner Name], OWNER_LIST[Email], "") = "", "", _xlfn.XLOOKUP(C_1[[#This Row],[OWNER NAME 1]], OWNER_LIST[Owner Name], OWNER_LIST[Email], ""))) -> kateryna.starykova@un.org | V105: =IF(C_1[[#This Row],[OWNER NAME 2]] = "", "", IF(_xlfn.XLOOKUP(C_1[[#This Row],[OWNER NAME 2]],OWNER_LIST[Owner Name], OWNER_LIST[Email], "") = "", "", _xlfn.XLOOKUP(C_1[[#This Row],[OWNER NAME 2]], OWNER_LIST[Owner Name], OWNER_LIST[Email], ""))) | W105: =$A$37 -> C1 | X105: =IF( OR( AND( NOT(ISBLANK(C_1[[#This Row],[DESCRIPTION - INFORMATION LOG]])), C_1[[#This Row],[DESCRIPTION - INFORMATION LOG]] <> "DESCRIPTION - INFORMATION LOG" ), NOT(ISBLANK(C_1[[#This Row],[ACTION REQUIRED]])) ), "Y", "N" ) -> Y
A106: LB01 | B106: Salle C6 - F. Brunome querries | C106: ACTION | D106: OPEN | E106: 26.02: T23 / T13 sockets / RJ45 / KNX push buton. | F106: 26.02: SHP to assess | G106: High | H106: 46087 | I106: {=IFERROR(_xlfn.TEXTJOIN(" / ", TRUE, IF(OWNER_LIST[Owner Name]=C_1[[#This Row],[OWNER NAME 1]], OWNER_LIST[Owner ORG], ""), IF(OWNER_LIST[Owner Name]=C_1[[#This Row],[OWNER NAME 2]], OWNER_LIST[Owner ORG], "")), "")} -> SHP / SHP | J106: Cedric Kusendova | K106: Patrick Vogelsang | R106: =_xlfn.CONCAT(C_1[[#This Row],[ESCALATE]], "-",C_1[[#This Row],[Row_PM]]) -> - | S106: =_xlfn.CONCAT(C_1[[#This Row],[ESCALATE]], "-",C_1[[#This Row],[Notify_PM]]) -> -- | T106: =ROW() -> 106 | U106: =IF(C_1[[#This Row],[OWNER NAME 1]] = "", "", IF(_xlfn.XLOOKUP(C_1[[#This Row],[OWNER NAME 1]],OWNER_LIST[Owner Name], OWNER_LIST[Email], "") = "", "", _xlfn.XLOOKUP(C_1[[#This Row],[OWNER NAME 1]], OWNER_LIST[Owner Name], OWNER_LIST[Email], ""))) -> cedric.kusendova@un.org | V106: =IF(C_1[[#This Row],[OWNER NAME 2]] = "", "", IF(_xlfn.XLOOKUP(C_1[[#This Row],[OWNER NAME 2]],OWNER_LIST[Owner Name], OWNER_LIST[Email], "") = "", "", _xlfn.XLOOKUP(C_1[[#This Row],[OWNER NAME 2]], OWNER_LIST[Owner Name], OWNER_LIST[Email], ""))) -> patrick.vogelsang@un.org | W106: =$A$37 -> C1 | X106: =IF( OR( AND( NOT(ISBLANK(C_1[[#This Row],[DESCRIPTION - INFORMATION LOG]])), C_1[[#This Row],[DESCRIPTION - INFORMATION LOG]] <> "DESCRIPTION - INFORMATION LOG" ), NOT(ISBLANK(C_1[[#This Row],[ACTION REQUIRED]])) ), "Y", "N" ) -> Y
A107: LB01 | B107: BMS - RFI 1421-C, panel TC.1.04 | C107: ACTION | D107: OPEN | E107: 29.10: RFI 1421-A, B, C have been rejected | F107: 29.10: RPN to submit RFI 1421-D | G107: TOP | H107: 45959 | I107: {=IFERROR(_xlfn.TEXTJOIN(" / ", TRUE, IF(OWNER_LIST[Owner Name]=C_1[[#This Row],[OWNER NAME 1]], OWNER_LIST[Owner ORG], ""), IF(OWNER_LIST[Owner Name]=C_1[[#This Row],[OWNER NAME 2]], OWNER_LIST[Owner ORG], "")), "")} -> RPN / SOMBP | J107: Matteo Naldi | K107: Cedric Erard | R107: =_xlfn.CONCAT(C_1[[#This Row],[ESCALATE]], "-",C_1[[#This Row],[Row_PM]]) -> - | S107: =_xlfn.CONCAT(C_1[[#This Row],[ESCALATE]], "-",C_1[[#This Row],[Notify_PM]]) -> -- | T107: =ROW() -> 107 | U107: =IF(C_1[[#This Row],[OWNER NAME 1]] = "", "", IF(_xlfn.XLOOKUP(C_1[[#This Row],[OWNER NAME 1]],OWNER_LIST[Owner Name], OWNER_LIST[Email], "") = "", "", _xlfn.XLOOKUP(C_1[[#This Row],[OWNER NAME 1]], OWNER_LIST[Owner Name], OWNER_LIST[Email], ""))) -> matteo.naldi@cmbcarpi.it | V107: =IF(C_1[[#This Row],[OWNER NAME 2]] = "", "", IF(_xlfn.XLOOKUP(C_1[[#This Row],[OWNER NAME 2]],OWNER_LIST[Owner Name], OWNER_LIST[Email], "") = "", "", _xlfn.XLOOKUP(C_1[[#This Row],[OWNER NAME 2]], OWNER_LIST[Owner Name], OWNER_LIST[Email], ""))) -> ce@erard.biz | W107: =$A$37 -> C1 | X107: =IF( OR( AND( NOT(ISBLANK(C_1[[#This Row],[DESCRIPTION - INFORMATION LOG]])), C_1[[#This Row],[DESCRIPTION - INFORMATION LOG]] <> "DESCRIPTION - INFORMATION LOG" ), NOT(ISBLANK(C_1[[#This Row],[ACTION REQUIRED]])) ), "Y", "N" ) -> Y
A108: LB02 | B108: BMS - Funccional Analisis - Wiring Diagram - Schematic | C108: ACTION | D108: OPEN | E108: 08.10: Commercial issue Between Energie Management & RPN 22.10: Funccional analisis have been confidentially shared. 30.10: SHP submitted comments. 19.11: SHP commented dwgs 26.11: Johnson control ready to restart 03.12: Commercial issues with ENERGY MANAGEMENT have been solved. 03.12: RPN submitted functional analysis | F108: 07.01: RPN to resubmit the wiring diagram | G108: TOP | H108: 45996 | I108: {=IFERROR(_xlfn.TEXTJOIN(" / ", TRUE, IF(OWNER_LIST[Owner Name]=C_1[[#This Row],[OWNER NAME 1]], OWNER_LIST[Owner ORG], ""), IF(OWNER_LIST[Owner Name]=C_1[[#This Row],[OWNER NAME 2]], OWNER_LIST[Owner ORG], "")), "")} -> RPN | J108: Hacir Degirmencioglu | R108: =_xlfn.CONCAT(C_1[[#This Row],[ESCALATE]], "-",C_1[[#This Row],[Row_PM]]) -> - | S108: =_xlfn.CONCAT(C_1[[#This Row],[ESCALATE]], "-",C_1[[#This Row],[Notify_PM]]) -> -- | T108: =ROW() -> 108 | U108: =IF(C_1[[#This Row],[OWNER NAME 1]] = "", "", IF(_xlfn.XLOOKUP(C_1[[#This Row],[OWNER NAME 1]],OWNER_LIST[Owner Name], OWNER_LIST[Email], "") = "", "", _xlfn.XLOOKUP(C_1[[#This Row],[OWNER NAME 1]], OWNER_LIST[Owner Name], OWNER_LIST[Email], ""))) -> hacir.degirmencioglu@rpn-sa.ch | V108: =IF(C_1[[#This Row],[OWNER NAME 2]] = "", "", IF(_xlfn.XLOOKUP(C_1[[#This Row],[OWNER NAME 2]],OWNER_LIST[Owner Name], OWNER_LIST[Email], "") = "", "", _xlfn.XLOOKUP(C_1[[#This Row],[OWNER NAME 2]], OWNER_LIST[Owner Name], OWNER_LIST[Email], ""))) | W108: =$A$37 -> C1 | X108: =IF( OR( AND( NOT(ISBLANK(C_1[[#This Row],[DESCRIPTION - INFORMATION LOG]])), C_1[[#This Row],[DESCRIPTION - INFORMATION LOG]] <> "DESCRIPTION - INFORMATION LOG" ), NOT(ISBLANK(C_1[[#This Row],[ACTION REQUIRED]])) ), "Y", "N" ) -> Y
A109: LB02 | B109: BMS - Planning | C109: INFO | D109: OPEN | E109: 03.12: EGGTELSA face commercial issues with ENERGY MANAGEMENT Schematic will be submited in January => Bdg. C S.C., postponed to +/- June 10.12: EGGTELSA proceeding w/o ENERGY MANAGEMENT 07.01: EGGTELSA submitted planing => 15.09.26! 11.02: EGGTELSA has all documents in hand | F109: 26.02: Works ongoing | G109: TOP | H109: 45996 | I109: {=IFERROR(_xlfn.TEXTJOIN(" / ", TRUE, IF(OWNER_LIST[Owner Name]=C_1[[#This Row],[OWNER NAME 1]], OWNER_LIST[Owner ORG], ""), IF(OWNER_LIST[Owner Name]=C_1[[#This Row],[OWNER NAME 2]], OWNER_LIST[Owner ORG], "")), "")} -> RPN / RPN | J109: Simone Conti | K109: Matteo Naldi | R109: =_xlfn.CONCAT(C_1[[#This Row],[ESCALATE]], "-",C_1[[#This Row],[Row_PM]]) -> - | S109: =_xlfn.CONCAT(C_1[[#This Row],[ESCALATE]], "-",C_1[[#This Row],[Notify_PM]]) -> -- | T109: =ROW() -> 109 | U109: =IF(C_1[[#This Row],[OWNER NAME 1]] = "", "", IF(_xlfn.XLOOKUP(C_1[[#This Row],[OWNER NAME 1]],OWNER_LIST[Owner Name], OWNER_LIST[Email], "") = "", "", _xlfn.XLOOKUP(C_1[[#This Row],[OWNER NAME 1]], OWNER_LIST[Owner Name], OWNER_LIST[Email], ""))) -> simone.conti@cmbcarpi.it | V109: =IF(C_1[[#This Row],[OWNER NAME 2]] = "", "", IF(_xlfn.XLOOKUP(C_1[[#This Row],[OWNER NAME 2]],OWNER_LIST[Owner Name], OWNER_LIST[Email], "") = "", "", _xlfn.XLOOKUP(C_1[[#This Row],[OWNER NAME 2]], OWNER_LIST[Owner Name], OWNER_LIST[Email], ""))) -> matteo.naldi@cmbcarpi.it | W109: =$A$37 -> C1 | X109: =IF( OR( AND( NOT(ISBLANK(C_1[[#This Row],[DESCRIPTION - INFORMATION LOG]])), C_1[[#This Row],[DESCRIPTION - INFORMATION LOG]] <> "DESCRIPTION - INFORMATION LOG" ), NOT(ISBLANK(C_1[[#This Row],[ACTION REQUIRED]])) ), "Y", "N" ) -> Y
A110: LB02 | B110: BMS PANELS - Procurement | C110: INFO | D110: OPEN | E110: 03.12: [Lucille email] 5 are missing, including the most critical ones for ventilation and smoke extraction. 10.12: 1 Panel to be received in december, 4 panels in January 17.12: 1 Panel to be received in december, 1 panel begining of January, 2 panels in february, 1 panel by the begining of march. 17.12: Last panel (smoke exhaust) to be received by the end of March. | G110: TOP | H110: 45959 | I110: {=IFERROR(_xlfn.TEXTJOIN(" / ", TRUE, IF(OWNER_LIST[Owner Name]=C_1[[#This Row],[OWNER NAME 1]], OWNER_LIST[Owner ORG], ""), IF(OWNER_LIST[Owner Name]=C_1[[#This Row],[OWNER NAME 2]], OWNER_LIST[Owner ORG], "")), "")} -> RPN / RPN | J110: Matteo Naldi | K110: Lorenzo Barnini | R110: =_xlfn.CONCAT(C_1[[#This Row],[ESCALATE]], "-",C_1[[#This Row],[Row_PM]]) -> - | S110: =_xlfn.CONCAT(C_1[[#This Row],[ESCALATE]], "-",C_1[[#This Row],[Notify_PM]]) -> -- | T110: =ROW() -> 110 | U110: =IF(C_1[[#This Row],[OWNER NAME 1]] = "", "", IF(_xlfn.XLOOKUP(C_1[[#This Row],[OWNER NAME 1]],OWNER_LIST[Owner Name], OWNER_LIST[Email], "") = "", "", _xlfn.XLOOKUP(C_1[[#This Row],[OWNER NAME 1]], OWNER_LIST[Owner Name], OWNER_LIST[Email], ""))) -> matteo.naldi@cmbcarpi.it | V110: =IF(C_1[[#This Row],[OWNER NAME 2]] = "", "", IF(_xlfn.XLOOKUP(C_1[[#This Row],[OWNER NAME 2]],OWNER_LIST[Owner Name], OWNER_LIST[Email], "") = "", "", _xlfn.XLOOKUP(C_1[[#This Row],[OWNER NAME 2]], OWNER_LIST[Owner Name], OWNER_LIST[Email], ""))) -> lorenzo.barnini@cmbcarpi.it | W110: =$A$37 -> C1 | X110: =IF( OR( AND( NOT(ISBLANK(C_1[[#This Row],[DESCRIPTION - INFORMATION LOG]])), C_1[[#This Row],[DESCRIPTION - INFORMATION LOG]] <> "DESCRIPTION - INFORMATION LOG" ), NOT(ISBLANK(C_1[[#This Row],[ACTION REQUIRED]])) ), "Y", "N" ) -> Y
A111: LB02 | B111: Permanent Fire closure INS 541 | C111: INFO | D111: OPEN | E111: 12.02: Inspection are ongoing | F111: 12.02: RPN to involve SBIS in the inspections | G111: High | H111: 46072 | I111: {=IFERROR(_xlfn.TEXTJOIN(" / ", TRUE, IF(OWNER_LIST[Owner Name]=C_1[[#This Row],[OWNER NAME 1]], OWNER_LIST[Owner ORG], ""), IF(OWNER_LIST[Owner Name]=C_1[[#This Row],[OWNER NAME 2]], OWNER_LIST[Owner ORG], "")), "")} -> RPN / SBIS | J111: Matteo Naldi | K111: Olivier Zuercher | R111: =_xlfn.CONCAT(C_1[[#This Row],[ESCALATE]], "-",C_1[[#This Row],[Row_PM]]) -> - | S111: =_xlfn.CONCAT(C_1[[#This Row],[ESCALATE]], "-",C_1[[#This Row],[Notify_PM]]) -> -- | T111: =ROW() -> 111 | U111: =IF(C_1[[#This Row],[OWNER NAME 1]] = "", "", IF(_xlfn.XLOOKUP(C_1[[#This Row],[OWNER NAME 1]],OWNER_LIST[Owner Name], OWNER_LIST[Email], "") = "", "", _xlfn.XLOOKUP(C_1[[#This Row],[OWNER NAME 1]], OWNER_LIST[Owner Name], OWNER_LIST[Email], ""))) -> matteo.naldi@cmbcarpi.it | V111: =IF(C_1[[#This Row],[OWNER NAME 2]] = "", "", IF(_xlfn.XLOOKUP(C_1[[#This Row],[OWNER NAME 2]],OWNER_LIST[Owner Name], OWNER_LIST[Email], "") = "", "", _xlfn.XLOOKUP(C_1[[#This Row],[OWNER NAME 2]], OWNER_LIST[Owner Name], OWNER_LIST[Email], ""))) -> olivier.zuercher@sbis.ch | W111: =$A$37 -> C1 | X111: =IF( OR( AND( NOT(ISBLANK(C_1[[#This Row],[DESCRIPTION - INFORMATION LOG]])), C_1[[#This Row],[DESCRIPTION - INFORMATION LOG]] <> "DESCRIPTION - INFORMATION LOG" ), NOT(ISBLANK(C_1[[#This Row],[ACTION REQUIRED]])) ), "Y", "N" ) -> Y
A112: LB02 | B112: Temporary Fire closure INS 545 - RPN temp. High Voltage cable is on future escape route | C112: ACTION | D112: OPEN | E112: 11.12: temporary Fire compartition required before SC 26.01: Step 1 has been issued 06.02: Step 2 has been issued. VAR is requested. | F112: 12.02: as per Schedule 3 Chapter 17 – Business Continuity Part 3, Paragraph 3.1.C., | G112: TOP | H112: 46043 | I112: {=IFERROR(_xlfn.TEXTJOIN(" / ", TRUE, IF(OWNER_LIST[Owner Name]=C_1[[#This Row],[OWNER NAME 1]], OWNER_LIST[Owner ORG], ""), IF(OWNER_LIST[Owner Name]=C_1[[#This Row],[OWNER NAME 2]], OWNER_LIST[Owner ORG], "")), "")} -> RPN | J112: Matteo Naldi | R112: =_xlfn.CONCAT(C_1[[#This Row],[ESCALATE]], "-",C_1[[#This Row],[Row_PM]]) -> - | S112: =_xlfn.CONCAT(C_1[[#This Row],[ESCALATE]], "-",C_1[[#This Row],[Notify_PM]]) -> -- | T112: =ROW() -> 112 | U112: =IF(C_1[[#This Row],[OWNER NAME 1]] = "", "", IF(_xlfn.XLOOKUP(C_1[[#This Row],[OWNER NAME 1]],OWNER_LIST[Owner Name], OWNER_LIST[Email], "") = "", "", _xlfn.XLOOKUP(C_1[[#This Row],[OWNER NAME 1]], OWNER_LIST[Owner Name], OWNER_LIST[Email], ""))) -> matteo.naldi@cmbcarpi.it | V112: =IF(C_1[[#This Row],[OWNER NAME 2]] = "", "", IF(_xlfn.XLOOKUP(C_1[[#This Row],[OWNER NAME 2]],OWNER_LIST[Owner Name], OWNER_LIST[Email], "") = "", "", _xlfn.XLOOKUP(C_1[[#This Row],[OWNER NAME 2]], OWNER_LIST[Owner Name], OWNER_LIST[Email], ""))) | W112: =$A$37 -> C1 | X112: =IF( OR( AND( NOT(ISBLANK(C_1[[#This Row],[DESCRIPTION - INFORMATION LOG]])), C_1[[#This Row],[DESCRIPTION - INFORMATION LOG]] <> "DESCRIPTION - INFORMATION LOG" ), NOT(ISBLANK(C_1[[#This Row],[ACTION REQUIRED]])) ), "Y", "N" ) -> Y
...

Sheet VARIATIONS
A1: Variation # | B1: Variation Name | C1: Section | D1: Administrative Status of the Variations (Agreed / Determined, Cancelled, In Progress, To be issued) | E1: Critical
A2: R-VAR-0017 | B2: SECURITY REVOLVING DOORS AND LOCKDOWN (PMI 026-027) | C2: ALL | D2: Agreed / Detemined
A3: R-VAR-0025 | B3: POSTAL SMART LOCKERS (PMI 031) (SSet 344) | C3: S1/C/AC/B | D3: Agreed / Detemined
A4: R-VAR-0031 | B4: GLAZED PARTITIONS FIRE RESISTANCE (SSet 327) | C4: ALL | D4: Agreed / Detemined
A5: R-VAR-0034 | B5: DOOR UPDATE BUILDINGS AC, B, S (SSet 323) | C5: ALL | D5: Agreed / Detemined
A6: R-VAR-0040 | B6: RESTAURATION OF HERITAGE FURNITURE (prov sum release) | C6: ALL | D6: Agreed / Detemined
A7: R-VAR-0051 | B7: FIRE SUPPRESSION SYSTEM (prov sum adjustement) | C7: ALL | D7: Agreed / Detemined
A8: R-VAR-0062 | B8: REPLACEMENT OF ASCENDER BY AQUILON | C8: ALL | D8: Agreed / Detemined
A9: R-VAR-0063 | B9: AH Interpreter Booth Changes - Equipment | C9: ALL | D9: Agreed / Detemined
A10: R-VAR-0072 | B10: AV BC INFRASTR OPTIMISATION (PMI 030) | C10: ALL | D10: Agreed / Detemined
A11: R-VAR-0077 | B11: AV MODIFS FOR SECTION C | C11: C | D11: Agreed / Detemined
A12: R-VAR-0084 | B12: NEW GENERATION BADGE READERS | C12: ALL | D12: Agreed / Detemined
A13: R-VAR-0089 | B13: HVAC CHANGES SALLE C6, TV STUDIO AND ATTENUATORS | C13: C | D13: Agreed / Detemined
... A101: R-VAR-0604 | B101: BLDG C PRESS BAR COUNTER TOP | C101: C | D101: Delay
A102: R-VAR-0611 | B102: BLDS A, AB, B & C WINDOW FRAMES | C102: AB/B/C | D102: To be issued | E102: Critical
A103: R-VAR-0612 | B103: VAR 173 revision Overall Broadcast (broadcast, lighting and services included) | C103: B/C | D103: To be issued
A104: R-VAR-0618 | B104: Bldg C Salle 1 Emergency Lighting | C104: C | D104: Delay
A105: R-VAR-0624 | B105: Bldg C Electrical panel board F15/2 | C105: C | D105: To be issued
A106: R-VAR-0625 | B106: Bldg C Electrical panel board F15 and cabling replacing | C106: C | D106: In Progress
A107: R-VAR-0628 | B107: Council Chamber AV - to check if eligible | C107: C | D107: To be issued
A108: R-VAR-0629 | B108: Door C5 cafeteria logistic adjustment (Bldg E catering BC) | C108: C | D108: To be issued
A109: R-VAR-0631 | B109: BLDG C – L00 – Existing Windows Wooden Frame | C109: C | D109: To be issued

Sheet Bldg C - UBS
A1: # | B1: MEETING AGENDA
A2: A | B2: MEETING DETAILS
B3: MEETING. | E3: PRODUCTION
B4: WEEK NO. | E4: =WEEKNUM(E6) -> 28
B5: SECTION | E5: C
B6: DATE | E6: 45850
B7: TIME | E7: 0.45833333
B8: LOCATION | E8: Building C : C-300
B9: PURPOSE | E9: - To support and protect the Production Plan - To strive for improved Production Plan stability and predictability.
B10: NEXT MEETING | E10: =E6+7 -> 45857
A12: B | B12: STAKEHOLDERS | C12: Org. | D12: In Attendance | E12: Name | F12: Column1
B13: =IF(ISBLANK(E13), "", INDEX(OWNER_LIST[Role], MATCH(E13,OWNER_LIST[Owner Name], 0))) -> Senior Architect | C13: =IF(ISBLANK(E13), "", INDEX(OWNER_LIST[Owner ORG], MATCH(E13,OWNER_LIST[Owner Name], 0))) -> SHP | D13: Yes | E13: Samuel Wilson
B14: =IF(ISBLANK(E14), "", INDEX(OWNER_LIST[Role], MATCH(E14,OWNER_LIST[Owner Name], 0))) -> Design Manager (DM) | C14: =IF(ISBLANK(E14), "", INDEX(OWNER_LIST[Owner ORG], MATCH(E14,OWNER_LIST[Owner Name], 0))) -> SHP | D14: Yes | E14: Jean-Mathieu Ferre
B15: =IF(ISBLANK(E15), "", INDEX(OWNER_LIST[Role], MATCH(E15,OWNER_LIST[Owner Name], 0))) -> Security Site Construction Management | C15: =IF(ISBLANK(E15), "", INDEX(OWNER_LIST[Owner ORG], MATCH(E15,OWNER_LIST[Owner Name], 0))) -> SHP | D15: Yes | E15: Cinzia Porracin
B16: =IF(ISBLANK(E16), "", INDEX(OWNER_LIST[Role], MATCH(E16,OWNER_LIST[Owner Name], 0))) -> Move Specialist / Doc Controller | C16: =IF(ISBLANK(E16), "", INDEX(OWNER_LIST[Owner ORG], MATCH(E16,OWNER_LIST[Owner Name], 0))) -> RPN | D16: No | E16: Martina Maffioletti | F16: Agathe
B17: =IF(ISBLANK(E17), "", INDEX(OWNER_LIST[Role], MATCH(E17,OWNER_LIST[Owner Name], 0))) | C17: =IF(ISBLANK(E17), "", INDEX(OWNER_LIST[Owner ORG], MATCH(E17,OWNER_LIST[Owner Name], 0))) | D17: No | F17: Arnaud | H17: ºº
B18: =IF(ISBLANK(E18), "", INDEX(OWNER_LIST[Role], MATCH(E18,OWNER_LIST[Owner Name], 0))) | C18: =IF(ISBLANK(E18), "", INDEX(OWNER_LIST[Owner ORG], MATCH(E18,OWNER_LIST[Owner Name], 0))) | D18: No | F18: arnaud
B19: =IF(ISBLANK(E19), "", INDEX(OWNER_LIST[Role], MATCH(E19,OWNER_LIST[Owner Name], 0))) | C19: =IF(ISBLANK(E19), "", INDEX(OWNER_LIST[Owner ORG], MATCH(E19,OWNER_LIST[Owner Name], 0))) | D19: No
B20: =IF(ISBLANK(E20), "", INDEX(OWNER_LIST[Role], MATCH(E20,OWNER_LIST[Owner Name], 0))) | C20: =IF(ISBLANK(E20), "", INDEX(OWNER_LIST[Owner ORG], MATCH(E20,OWNER_LIST[Owner Name], 0))) | D20: No
B21: =IF(ISBLANK(E21), "", INDEX(OWNER_LIST[Role], MATCH(E21,OWNER_LIST[Owner Name], 0))) | C21: =IF(ISBLANK(E21), "", INDEX(OWNER_LIST[Owner ORG], MATCH(E21,OWNER_LIST[Owner Name], 0))) | D21: No
B22: =IF(ISBLANK(E22), "", INDEX(OWNER_LIST[Role], MATCH(E22,OWNER_LIST[Owner Name], 0))) | C22: =IF(ISBLANK(E22), "", INDEX(OWNER_LIST[Owner ORG], MATCH(E22,OWNER_LIST[Owner Name], 0))) | D22: No
B23: =IF(ISBLANK(E23), "", INDEX(OWNER_LIST[Role], MATCH(E23,OWNER_LIST[Owner Name], 0))) | C23: =IF(ISBLANK(E23), "", INDEX(OWNER_LIST[Owner ORG], MATCH(E23,OWNER_LIST[Owner Name], 0))) | D23: No
A25: C1 | B25: MEETING TOPIC | C25: ACTION - INFO | D25: STATUS | E25: DESCRIPTION - INFORMATION LOG | F25: ACTION REQUIRED | G25: PRIORITY | H25: DUE DATE | I25: OWNER ORG. | J25: OWNER NAME 1 | K25: OWNER NAME 2 | L25: DISCIPLINE | M25: DATE LOGGED | N25: DATE CLOSED | O25: ESCALATE | P25: Note | Q25: Row_PM | R25: Notify_PM | S25: Condition_PM | T25: ROW | U25: Email_Name_1 | V25: Email_Name_2 | W25: SECTION | X25: Nonull
A26: C_1 | B26: HEALTH & SAFETY | R26: =_xlfn.CONCAT(C_1_6[[#This Row],[ESCALATE]], "-",C_1_6[[#This Row],[Row_PM]]) -> - | S26: =_xlfn.CONCAT(C_1_6[[#This Row],[ESCALATE]], "-",C_1_6[[#This Row],[Notify_PM]]) -> - - | T26: =ROW() -> 26 | U26: =IF(C_1_6[[#This Row],[OWNER NAME 1]] = "", "", IF(_xlfn.XLOOKUP(C_1_6[[#This Row],[OWNER NAME 1]],OWNER_LIST[Owner Name], OWNER_LIST[Email], "") = "", "", _xlfn.XLOOKUP(C_1_6[[#This Row],[OWNER NAME 1]], OWNER_LIST[Owner Name], OWNER_LIST[Email], ""))) | V26: =IF(C_1_6[[#This Row],[OWNER NAME 2]] = "", "", IF(_xlfn.XLOOKUP(C_1_6[[#This Row],[OWNER NAME 2]],OWNER_LIST[Owner Name], OWNER_LIST[Email], "") = "", "", _xlfn.XLOOKUP(C_1_6[[#This Row],[OWNER NAME 2]], OWNER_LIST[Owner Name], OWNER_LIST[Email], ""))) | W26: =$A$25 -> C1 | X26: =IF(AND(NOT(ISBLANK(C_1_6[[#This Row],[ACTION - INFO]])),C_1_6[[#This Row],[ACTION - INFO]] <> "ACTION - INFO"),"Y","N") -> N
I27: {=IFERROR(_xlfn.TEXTJOIN(" / ", TRUE, IF(OWNER_LIST[Owner Name]=C_1_6[[#This Row],[OWNER NAME 1]], OWNER_LIST[Owner ORG], ""), IF(OWNER_LIST[Owner Name]=C_1_6[[#This Row],[OWNER NAME 2]], OWNER_LIST[Owner ORG], "")), "")} | R27: =_xlfn.CONCAT(C_1_6[[#This Row],[ESCALATE]], "-",C_1_6[[#This Row],[Row_PM]]) -> - | S27: =_xlfn.CONCAT(C_1_6[[#This Row],[ESCALATE]], "-",C_1_6[[#This Row],[Notify_PM]]) -> -- | T27: =ROW() -> 27 | U27: =IF(C_1_6[[#This Row],[OWNER NAME 1]] = "", "", IF(_xlfn.XLOOKUP(C_1_6[[#This Row],[OWNER NAME 1]],OWNER_LIST[Owner Name], OWNER_LIST[Email], "") = "", "", _xlfn.XLOOKUP(C_1_6[[#This Row],[OWNER NAME 1]], OWNER_LIST[Owner Name], OWNER_LIST[Email], ""))) | V27: =IF(C_1_6[[#This Row],[OWNER NAME 2]] = "", "", IF(_xlfn.XLOOKUP(C_1_6[[#This Row],[OWNER NAME 2]],OWNER_LIST[Owner Name], OWNER_LIST[Email], "") = "", "", _xlfn.XLOOKUP(C_1_6[[#This Row],[OWNER NAME 2]], OWNER_LIST[Owner Name], OWNER_LIST[Email], ""))) | W27: =$A$25 -> C1 | X27: =IF(AND(NOT(ISBLANK(C_1_6[[#This Row],[ACTION - INFO]])),C_1_6[[#This Row],[ACTION - INFO]] <> "ACTION - INFO"),"Y","N") -> N
I28: {=IFERROR(_xlfn.TEXTJOIN(" / ", TRUE, IF(OWNER_LIST[Owner Name]=C_1_6[[#This Row],[OWNER NAME 1]], OWNER_LIST[Owner ORG], ""), IF(OWNER_LIST[Owner Name]=C_1_6[[#This Row],[OWNER NAME 2]], OWNER_LIST[Owner ORG], "")), "")} | R28: =_xlfn.CONCAT(C_1_6[[#This Row],[ESCALATE]], "-",C_1_6[[#This Row],[Row_PM]]) -> - | S28: =_xlfn.CONCAT(C_1_6[[#This Row],[ESCALATE]], "-",C_1_6[[#This Row],[Notify_PM]]) -> -- | T28: =ROW() -> 28 | U28: =IF(C_1_6[[#This Row],[OWNER NAME 1]] = "", "", IF(_xlfn.XLOOKUP(C_1_6[[#This Row],[OWNER NAME 1]],OWNER_LIST[Owner Name], OWNER_LIST[Email], "") = "", "", _xlfn.XLOOKUP(C_1_6[[#This Row],[OWNER NAME 1]], OWNER_LIST[Owner Name], OWNER_LIST[Email], ""))) | V28: =IF(C_1_6[[#This Row],[OWNER NAME 2]] = "", "", IF(_xlfn.XLOOKUP(C_1_6[[#This Row],[OWNER NAME 2]],OWNER_LIST[Owner Name], OWNER_LIST[Email], "") = "", "", _xlfn.XLOOKUP(C_1_6[[#This Row],[OWNER NAME 2]], OWNER_LIST[Owner Name], OWNER_LIST[Email], ""))) | W28: =$A$25 -> C1 | X28: =IF(AND(NOT(ISBLANK(C_1_6[[#This Row],[ACTION - INFO]])),C_1_6[[#This Row],[ACTION - INFO]] <> "ACTION - INFO"),"Y","N") -> N
A29: C_2 | B29: PRODUCTION | R29: =_xlfn.CONCAT(C_1_6[[#This Row],[ESCALATE]], "-",C_1_6[[#This Row],[Row_PM]]) -> - | S29: =_xlfn.CONCAT(C_1_6[[#This Row],[ESCALATE]], "-",C_1_6[[#This Row],[Notify_PM]]) -> - - | T29: =ROW() -> 29 | U29: =IF(C_1_6[[#This Row],[OWNER NAME 1]] = "", "", IF(_xlfn.XLOOKUP(C_1_6[[#This Row],[OWNER NAME 1]],OWNER_LIST[Owner Name], OWNER_LIST[Email], "") = "", "", _xlfn.XLOOKUP(C_1_6[[#This Row],[OWNER NAME 1]], OWNER_LIST[Owner Name], OWNER_LIST[Email], ""))) | V29: =IF(C_1_6[[#This Row],[OWNER NAME 2]] = "", "", IF(_xlfn.XLOOKUP(C_1_6[[#This Row],[OWNER NAME 2]],OWNER_LIST[Owner Name], OWNER_LIST[Email], "") = "", "", _xlfn.XLOOKUP(C_1_6[[#This Row],[OWNER NAME 2]], OWNER_LIST[Owner Name], OWNER_LIST[Email], ""))) | W29: =$A$25 -> C1 | X29: =IF(AND(NOT(ISBLANK(C_1_6[[#This Row],[ACTION - INFO]])),C_1_6[[#This Row],[ACTION - INFO]] <> "ACTION - INFO"),"Y","N") -> N
B30: UBS start of finishing works | C30: ACTION | D30: OPEN | E30: 12.07: By mid january, UBS to start finishes works by mid January. +/- 2 months | G30: Medium | H30: 45887 | I30: {=IFERROR(_xlfn.TEXTJOIN(" / ", TRUE, IF(OWNER_LIST[Owner Name]=C_1_6[[#This Row],[OWNER NAME 1]], OWNER_LIST[Owner ORG], ""), IF(OWNER_LIST[Owner Name]=C_1_6[[#This Row],[OWNER NAME 2]], OWNER_LIST[Owner ORG], "")), "")} | R30: =_xlfn.CONCAT(C_1_6[[#This Row],[ESCALATE]], "-",C_1_6[[#This Row],[Row_PM]]) -> - | S30: =_xlfn.CONCAT(C_1_6[[#This Row],[ESCALATE]], "-",C_1_6[[#This Row],[Notify_PM]]) -> -- | T30: =ROW() -> 30 | U30: =IF(C_1_6[[#This Row],[OWNER NAME 1]] = "", "", IF(_xlfn.XLOOKUP(C_1_6[[#This Row],[OWNER NAME 1]],OWNER_LIST[Owner Name], OWNER_LIST[Email], "") = "", "", _xlfn.XLOOKUP(C_1_6[[#This Row],[OWNER NAME 1]], OWNER_LIST[Owner Name], OWNER_LIST[Email], ""))) | V30: =IF(C_1_6[[#This Row],[OWNER NAME 2]] = "", "", IF(_xlfn.XLOOKUP(C_1_6[[#This Row],[OWNER NAME 2]],OWNER_LIST[Owner Name], OWNER_LIST[Email], "") = "", "", _xlfn.XLOOKUP(C_1_6[[#This Row],[OWNER NAME 2]], OWNER_LIST[Owner Name], OWNER_LIST[Email], ""))) | W30: =$A$25 -> C1 | X30: =IF(AND(NOT(ISBLANK(C_1_6[[#This Row],[ACTION - INFO]])),C_1_6[[#This Row],[ACTION - INFO]] <> "ACTION - INFO"),"Y","N") -> Y
B31: UBS operation | C31: ACTION | D31: OPEN | E31: 12.07: By 16.03.2026. Worth case 01.07.2026 | G31: Medium | I31: {=IFERROR(_xlfn.TEXTJOIN(" / ", TRUE, IF(OWNER_LIST[Owner Name]=C_1_6[[#This Row],[OWNER NAME 1]], OWNER_LIST[Owner ORG], ""), IF(OWNER_LIST[Owner Name]=C_1_6[[#This Row],[OWNER NAME 2]], OWNER_LIST[Owner ORG], "")), "")} | R31: =_xlfn.CONCAT(C_1_6[[#This Row],[ESCALATE]], "-",C_1_6[[#This Row],[Row_PM]]) -> - | S31: =_xlfn.CONCAT(C_1_6[[#This Row],[ESCALATE]], "-",C_1_6[[#This Row],[Notify_PM]]) -> -- | T31: =ROW() -> 31 | U31: =IF(C_1_6[[#This Row],[OWNER NAME 1]] = "", "", IF(_xlfn.XLOOKUP(C_1_6[[#This Row],[OWNER NAME 1]],OWNER_LIST[Owner Name], OWNER_LIST[Email], "") = "", "", _xlfn.XLOOKUP(C_1_6[[#This Row],[OWNER NAME 1]], OWNER_LIST[Owner Name], OWNER_LIST[Email], ""))) | V31: =IF(C_1_6[[#This Row],[OWNER NAME 2]] = "", "", IF(_xlfn.XLOOKUP(C_1_6[[#This Row],[OWNER NAME 2]],OWNER_LIST[Owner Name], OWNER_LIST[Email], "") = "", "", _xlfn.XLOOKUP(C_1_6[[#This Row],[OWNER NAME 2]], OWNER_LIST[Owner Name], OWNER_LIST[Email], ""))) | W31: =$A$25 -> C1 | X31: =IF(AND(NOT(ISBLANK(C_1_6[[#This Row],[ACTION - INFO]])),C_1_6[[#This Row],[ACTION - INFO]] <> "ACTION - INFO"),"Y","N") -> Y
B32: OPEN HOUSE | E32: 12.07: Their will be an Open House day, UBS will not be invited | G32: Medium | H32: 45853 | I32: {=IFERROR(_xlfn.TEXTJOIN(" / ", TRUE, IF(OWNER_LIST[Owner Name]=C_1_6[[#This Row],[OWNER NAME 1]], OWNER_LIST[Owner ORG], ""), IF(OWNER_LIST[Owner Name]=C_1_6[[#This Row],[OWNER NAME 2]], OWNER_LIST[Owner ORG], "")), "")} -> RPN / RPN | J32: Matteo Naldi | K32: Simone Conti | R32: =_xlfn.CONCAT(C_1_6[[#This Row],[ESCALATE]], "-",C_1_6[[#This Row],[Row_PM]]) -> - | S32: =_xlfn.CONCAT(C_1_6[[#This Row],[ESCALATE]], "-",C_1_6[[#This Row],[Notify_PM]]) -> -- | T32: =ROW() -> 32 | U32: =IF(C_1_6[[#This Row],[OWNER NAME 1]] = "", "", IF(_xlfn.XLOOKUP(C_1_6[[#This Row],[OWNER NAME 1]],OWNER_LIST[Owner Name], OWNER_LIST[Email], "") = "", "", _xlfn.XLOOKUP(C_1_6[[#This Row],[OWNER NAME 1]], OWNER_LIST[Owner Name], OWNER_LIST[Email], ""))) -> matteo.naldi@cmbcarpi.it | V32: =IF(C_1_6[[#This Row],[OWNER NAME 2]] = "", "", IF(_xlfn.XLOOKUP(C_1_6[[#This Row],[OWNER NAME 2]],OWNER_LIST[Owner Name], OWNER_LIST[Email], "") = "", "", _xlfn.XLOOKUP(C_1_6[[#This Row],[OWNER NAME 2]], OWNER_LIST[Owner Name], OWNER_LIST[Email], ""))) -> simone.conti@cmbcarpi.it | W32: =$A$25 -> C1 | X32: =IF(AND(NOT(ISBLANK(C_1_6[[#This Row],[ACTION - INFO]])),C_1_6[[#This Row],[ACTION - INFO]] <> "ACTION - INFO"),"Y","N") -> N
B33: Next meeting | E33: 12.07: Friday 26.09 | G33: Medium | H33: 45811 | I33: {=IFERROR(_xlfn.TEXTJOIN(" / ", TRUE, IF(OWNER_LIST[Owner Name]=C_1_6[[#This Row],[OWNER NAME 1]], OWNER_LIST[Owner ORG], ""), IF(OWNER_LIST[Owner Name]=C_1_6[[#This Row],[OWNER NAME 2]], OWNER_LIST[Owner ORG], "")), "")} -> RPN / SHP | J33: Davide Cirillo | K33: Didier Dequatre | R33: =_xlfn.CONCAT(C_1_6[[#This Row],[ESCALATE]], "-",C_1_6[[#This Row],[Row_PM]]) -> - | S33: =_xlfn.CONCAT(C_1_6[[#This Row],[ESCALATE]], "-",C_1_6[[#This Row],[Notify_PM]]) -> -- | T33: =ROW() -> 33 | U33: =IF(C_1_6[[#This Row],[OWNER NAME 1]] = "", "", IF(_xlfn.XLOOKUP(C_1_6[[#This Row],[OWNER NAME 1]],OWNER_LIST[Owner Name], OWNER_LIST[Email], "") = "", "", _xlfn.XLOOKUP(C_1_6[[#This Row],[OWNER NAME 1]], OWNER_LIST[Owner Name], OWNER_LIST[Email], ""))) -> davide.cirillo@cmbcarpi.it | V33: =IF(C_1_6[[#This Row],[OWNER NAME 2]] = "", "", IF(_xlfn.XLOOKUP(C_1_6[[#This Row],[OWNER NAME 2]],OWNER_LIST[Owner Name], OWNER_LIST[Email], "") = "", "", _xlfn.XLOOKUP(C_1_6[[#This Row],[OWNER NAME 2]], OWNER_LIST[Owner Name], OWNER_LIST[Email], ""))) -> didier.dequatre@un.org | W33: =$A$25 -> C1 | X33: =IF(AND(NOT(ISBLANK(C_1_6[[#This Row],[ACTION - INFO]])),C_1_6[[#This Row],[ACTION - INFO]] <> "ACTION - INFO"),"Y","N") -> N
G34: High | H34: 45855 | I34: {=IFERROR(_xlfn.TEXTJOIN(" / ", TRUE, IF(OWNER_LIST[Owner Name]=C_1_6[[#This Row],[OWNER NAME 1]], OWNER_LIST[Owner ORG], ""), IF(OWNER_LIST[Owner Name]=C_1_6[[#This Row],[OWNER NAME 2]], OWNER_LIST[Owner ORG], "")), "")} -> RPN | J34: Jessica Donatelli | R34: =_xlfn.CONCAT(C_1_6[[#This Row],[ESCALATE]], "-",C_1_6[[#This Row],[Row_PM]]) -> - | S34: =_xlfn.CONCAT(C_1_6[[#This Row],[ESCALATE]], "-",C_1_6[[#This Row],[Notify_PM]]) -> -- | T34: =ROW() -> 34 | U34: =IF(C_1_6[[#This Row],[OWNER NAME 1]] = "", "", IF(_xlfn.XLOOKUP(C_1_6[[#This Row],[OWNER NAME 1]],OWNER_LIST[Owner Name], OWNER_LIST[Email], "") = "", "", _xlfn.XLOOKUP(C_1_6[[#This Row],[OWNER NAME 1]], OWNER_LIST[Owner Name], OWNER_LIST[Email], ""))) -> jessica.donatelli@cmbcarpi.it | V34: =IF(C_1_6[[#This Row],[OWNER NAME 2]] = "", "", IF(_xlfn.XLOOKUP(C_1_6[[#This Row],[OWNER NAME 2]],OWNER_LIST[Owner Name], OWNER_LIST[Email], "") = "", "", _xlfn.XLOOKUP(C_1_6[[#This Row],[OWNER NAME 2]], OWNER_LIST[Owner Name], OWNER_LIST[Email], ""))) | W34: =$A$25 -> C1 | X34: =IF(AND(NOT(ISBLANK(C_1_6[[#This Row],[ACTION - INFO]])),C_1_6[[#This Row],[ACTION - INFO]] <> "ACTION - INFO"),"Y","N") -> N
G35: High | I35: {=IFERROR(_xlfn.TEXTJOIN(" / ", TRUE, IF(OWNER_LIST[Owner Name]=C_1_6[[#This Row],[OWNER NAME 1]], OWNER_LIST[Owner ORG], ""), IF(OWNER_LIST[Owner Name]=C_1_6[[#This Row],[OWNER NAME 2]], OWNER_LIST[Owner ORG], "")), "")} -> RPN | J35: Matteo Naldi | R35: =_xlfn.CONCAT(C_1_6[[#This Row],[ESCALATE]], "-",C_1_6[[#This Row],[Row_PM]]) -> - | S35: =_xlfn.CONCAT(C_1_6[[#This Row],[ESCALATE]], "-",C_1_6[[#This Row],[Notify_PM]]) -> -- | T35: =ROW() -> 35 | U35: =IF(C_1_6[[#This Row],[OWNER NAME 1]] = "", "", IF(_xlfn.XLOOKUP(C_1_6[[#This Row],[OWNER NAME 1]],OWNER_LIST[Owner Name], OWNER_LIST[Email], "") = "", "", _xlfn.XLOOKUP(C_1_6[[#This Row],[OWNER NAME 1]], OWNER_LIST[Owner Name], OWNER_LIST[Email], ""))) -> matteo.naldi@cmbcarpi.it | V35: =IF(C_1_6[[#This Row],[OWNER NAME 2]] = "", "", IF(_xlfn.XLOOKUP(C_1_6[[#This Row],[OWNER NAME 2]],OWNER_LIST[Owner Name], OWNER_LIST[Email], "") = "", "", _xlfn.XLOOKUP(C_1_6[[#This Row],[OWNER NAME 2]], OWNER_LIST[Owner Name], OWNER_LIST[Email], ""))) | W35: =$A$25 -> C1 | X35: =IF(AND(NOT(ISBLANK(C_1_6[[#This Row],[ACTION - INFO]])),C_1_6[[#This Row],[ACTION - INFO]] <> "ACTION - INFO"),"Y","N") -> N
R36: =_xlfn.CONCAT(C_1_6[[#This Row],[ESCALATE]], "-",C_1_6[[#This Row],[Row_PM]]) -> - | S36: =_xlfn.CONCAT(C_1_6[[#This Row],[ESCALATE]], "-",C_1_6[[#This Row],[Notify_PM]]) -> -- | T36: =ROW() -> 36 | U36: =IF(C_1_6[[#This Row],[OWNER NAME 1]] = "", "", IF(_xlfn.XLOOKUP(C_1_6[[#This Row],[OWNER NAME 1]],OWNER_LIST[Owner Name], OWNER_LIST[Email], "") = "", "", _xlfn.XLOOKUP(C_1_6[[#This Row],[OWNER NAME 1]], OWNER_LIST[Owner Name], OWNER_LIST[Email], ""))) | V36: =IF(C_1_6[[#This Row],[OWNER NAME 2]] = "", "", IF(_xlfn.XLOOKUP(C_1_6[[#This Row],[OWNER NAME 2]],OWNER_LIST[Owner Name], OWNER_LIST[Email], "") = "", "", _xlfn.XLOOKUP(C_1_6[[#This Row],[OWNER NAME 2]], OWNER_LIST[Owner Name], OWNER_LIST[Email], ""))) | W36: =$A$25 -> C1 | X36: =IF(AND(NOT(ISBLANK(C_1_6[[#This Row],[ACTION - INFO]])),C_1_6[[#This Row],[ACTION - INFO]] <> "ACTION - INFO"),"Y","N") -> N
R37: =_xlfn.CONCAT(C_1_6[[#This Row],[ESCALATE]], "-",C_1_6[[#This Row],[Row_PM]]) -> - | S37: =_xlfn.CONCAT(C_1_6[[#This Row],[ESCALATE]], "-",C_1_6[[#This Row],[Notify_PM]]) -> -- | T37: =ROW() -> 37 | U37: =IF(C_1_6[[#This Row],[OWNER NAME 1]] = "", "", IF(_xlfn.XLOOKUP(C_1_6[[#This Row],[OWNER NAME 1]],OWNER_LIST[Owner Name], OWNER_LIST[Email], "") = "", "", _xlfn.XLOOKUP(C_1_6[[#This Row],[OWNER NAME 1]], OWNER_LIST[Owner Name], OWNER_LIST[Email], ""))) | V37: =IF(C_1_6[[#This Row],[OWNER NAME 2]] = "", "", IF(_xlfn.XLOOKUP(C_1_6[[#This Row],[OWNER NAME 2]],OWNER_LIST[Owner Name], OWNER_LIST[Email], "") = "", "", _xlfn.XLOOKUP(C_1_6[[#This Row],[OWNER NAME 2]], OWNER_LIST[Owner Name], OWNER_LIST[Email], ""))) | W37: =$A$25 -> C1 | X37: =IF(AND(NOT(ISBLANK(C_1_6[[#This Row],[ACTION - INFO]])),C_1_6[[#This Row],[ACTION - INFO]] <> "ACTION - INFO"),"Y","N") -> N
A38: C_3 | B38: ING & COMMISSIONING | I38: {=IFERROR(_xlfn.TEXTJOIN(" / ", TRUE, IF(OWNER_LIST[Owner Name]=C_1_6[[#This Row],[OWNER NAME 1]], OWNER_LIST[Owner ORG], ""), IF(OWNER_LIST[Owner Name]=C_1_6[[#This Row],[OWNER NAME 2]], OWNER_LIST[Owner ORG], "")), "")} | R38: =_xlfn.CONCAT(C_1_6[[#This Row],[ESCALATE]], "-",C_1_6[[#This Row],[Row_PM]]) -> - | S38: =_xlfn.CONCAT(C_1_6[[#This Row],[ESCALATE]], "-",C_1_6[[#This Row],[Notify_PM]]) -> - - | T38: =ROW() -> 38 | U38: =IF(C_1_6[[#This Row],[OWNER NAME 1]] = "", "", IF(_xlfn.XLOOKUP(C_1_6[[#This Row],[OWNER NAME 1]],OWNER_LIST[Owner Name], OWNER_LIST[Email], "") = "", "", _xlfn.XLOOKUP(C_1_6[[#This Row],[OWNER NAME 1]], OWNER_LIST[Owner Name], OWNER_LIST[Email], ""))) | V38: =IF(C_1_6[[#This Row],[OWNER NAME 2]] = "", "", IF(_xlfn.XLOOKUP(C_1_6[[#This Row],[OWNER NAME 2]],OWNER_LIST[Owner Name], OWNER_LIST[Email], "") = "", "", _xlfn.XLOOKUP(C_1_6[[#This Row],[OWNER NAME 2]], OWNER_LIST[Owner Name], OWNER_LIST[Email], ""))) | W38: =$A$25 -> C1 | X38: =IF(AND(NOT(ISBLANK(C_1_6[[#This Row],[ACTION - INFO]])),C_1_6[[#This Row],[ACTION - INFO]] <> "ACTION - INFO"),"Y","N") -> N
I42: {=IFERROR(_xlfn.TEXTJOIN(" / ", TRUE, IF(OWNER_LIST[Owner Name]=C_1_6[[#This Row],[OWNER NAME 1]], OWNER_LIST[Owner ORG], ""), IF(OWNER_LIST[Owner Name]=C_1_6[[#This Row],[OWNER NAME 2]], OWNER_LIST[Owner ORG], "")), "")} | R42: =_xlfn.CONCAT(C_1_6[[#This Row],[ESCALATE]], "-",C_1_6[[#This Row],[Row_PM]]) -> - | S42: =_xlfn.CONCAT(C_1_6[[#This Row],[ESCALATE]], "-",C_1_6[[#This Row],[Notify_PM]]) -> -- | T42: =ROW() -> 42 | U42: =IF(C_1_6[[#This Row],[OWNER NAME 1]] = "", "", IF(_xlfn.XLOOKUP(C_1_6[[#This Row],[OWNER NAME 1]],OWNER_LIST[Owner Name], OWNER_LIST[Email], "") = "", "", _xlfn.XLOOKUP(C_1_6[[#This Row],[OWNER NAME 1]], OWNER_LIST[Owner Name], OWNER_LIST[Email], ""))) | V42: =IF(C_1_6[[#This Row],[OWNER NAME 2]] = "", "", IF(_xlfn.XLOOKUP(C_1_6[[#This Row],[OWNER NAME 2]],OWNER_LIST[Owner Name], OWNER_LIST[Email], "") = "", "", _xlfn.XLOOKUP(C_1_6[[#This Row],[OWNER NAME 2]], OWNER_LIST[Owner Name], OWNER_LIST[Email], ""))) | W42: =$A$25 -> C1 | X42: =IF(AND(NOT(ISBLANK(C_1_6[[#This Row],[ACTION - INFO]])),C_1_6[[#This Row],[ACTION - INFO]] <> "ACTION - INFO"),"Y","N") -> N
I43: {=IFERROR(_xlfn.TEXTJOIN(" / ", TRUE, IF(OWNER_LIST[Owner Name]=C_1_6[[#This Row],[OWNER NAME 1]], OWNER_LIST[Owner ORG], ""), IF(OWNER_LIST[Owner Name]=C_1_6[[#This Row],[OWNER NAME 2]], OWNER_LIST[Owner ORG], "")), "")} | R43: =_xlfn.CONCAT(C_1_6[[#This Row],[ESCALATE]], "-",C_1_6[[#This Row],[Row_PM]]) -> - | S43: =_xlfn.CONCAT(C_1_6[[#This Row],[ESCALATE]], "-",C_1_6[[#This Row],[Notify_PM]]) -> -- | T43: =ROW() -> 43 | U43: =IF(C_1_6[[#This Row],[OWNER NAME 1]] = "", "", IF(_xlfn.XLOOKUP(C_1_6[[#This Row],[OWNER NAME 1]],OWNER_LIST[Owner Name], OWNER_LIST[Email], "") = "", "", _xlfn.XLOOKUP(C_1_6[[#This Row],[OWNER NAME 1]], OWNER_LIST[Owner Name], OWNER_LIST[Email], ""))) | V43: =IF(C_1_6[[#This Row],[OWNER NAME 2]] = "", "", IF(_xlfn.XLOOKUP(C_1_6[[#This Row],[OWNER NAME 2]],OWNER_LIST[Owner Name], OWNER_LIST[Email], "") = "", "", _xlfn.XLOOKUP(C_1_6[[#This Row],[OWNER NAME 2]], OWNER_LIST[Owner Name], OWNER_LIST[Email], ""))) | W43: =$A$25 -> C1 | X43: =IF(AND(NOT(ISBLANK(C_1_6[[#This Row],[ACTION - INFO]])),C_1_6[[#This Row],[ACTION - INFO]] <> "ACTION - INFO"),"Y","N") -> N
I44: {=IFERROR(_xlfn.TEXTJOIN(" / ", TRUE, IF(OWNER_LIST[Owner Name]=C_1_6[[#This Row],[OWNER NAME 1]], OWNER_LIST[Owner ORG], ""), IF(OWNER_LIST[Owner Name]=C_1_6[[#This Row],[OWNER NAME 2]], OWNER_LIST[Owner ORG], "")), "")} | R44: =_xlfn.CONCAT(C_1_6[[#This Row],[ESCALATE]], "-",C_1_6[[#This Row],[Row_PM]]) -> - | S44: =_xlfn.CONCAT(C_1_6[[#This Row],[ESCALATE]], "-",C_1_6[[#This Row],[Notify_PM]]) -> -- | T44: =ROW() -> 44 | U44: =IF(C_1_6[[#This Row],[OWNER NAME 1]] = "", "", IF(_xlfn.XLOOKUP(C_1_6[[#This Row],[OWNER NAME 1]],OWNER_LIST[Owner Name], OWNER_LIST[Email], "") = "", "", _xlfn.XLOOKUP(C_1_6[[#This Row],[OWNER NAME 1]], OWNER_LIST[Owner Name], OWNER_LIST[Email], ""))) | V44: =IF(C_1_6[[#This Row],[OWNER NAME 2]] = "", "", IF(_xlfn.XLOOKUP(C_1_6[[#This Row],[OWNER NAME 2]],OWNER_LIST[Owner Name], OWNER_LIST[Email], "") = "", "", _xlfn.XLOOKUP(C_1_6[[#This Row],[OWNER NAME 2]], OWNER_LIST[Owner Name], OWNER_LIST[Email], ""))) | W44: =$A$25 -> C1 | X44: =IF(AND(NOT(ISBLANK(C_1_6[[#This Row],[ACTION - INFO]])),C_1_6[[#This Row],[ACTION - INFO]] <> "ACTION - INFO"),"Y","N") -> N
I45: {=IFERROR(_xlfn.TEXTJOIN(" / ", TRUE, IF(OWNER_LIST[Owner Name]=C_1_6[[#This Row],[OWNER NAME 1]], OWNER_LIST[Owner ORG], ""), IF(OWNER_LIST[Owner Name]=C_1_6[[#This Row],[OWNER NAME 2]], OWNER_LIST[Owner ORG], "")), "")} | R45: =_xlfn.CONCAT(C_1_6[[#This Row],[ESCALATE]], "-",C_1_6[[#This Row],[Row_PM]]) -> - | S45: =_xlfn.CONCAT(C_1_6[[#This Row],[ESCALATE]], "-",C_1_6[[#This Row],[Notify_PM]]) -> -- | T45: =ROW() -> 45 | U45: =IF(C_1_6[[#This Row],[OWNER NAME 1]] = "", "", IF(_xlfn.XLOOKUP(C_1_6[[#This Row],[OWNER NAME 1]],OWNER_LIST[Owner Name], OWNER_LIST[Email], "") = "", "", _xlfn.XLOOKUP(C_1_6[[#This Row],[OWNER NAME 1]], OWNER_LIST[Owner Name], OWNER_LIST[Email], ""))) | V45: =IF(C_1_6[[#This Row],[OWNER NAME 2]] = "", "", IF(_xlfn.XLOOKUP(C_1_6[[#This Row],[OWNER NAME 2]],OWNER_LIST[Owner Name], OWNER_LIST[Email], "") = "", "", _xlfn.XLOOKUP(C_1_6[[#This Row],[OWNER NAME 2]], OWNER_LIST[Owner Name], OWNER_LIST[Email], ""))) | W45: =$A$25 -> C1 | X45: =IF(AND(NOT(ISBLANK(C_1_6[[#This Row],[ACTION - INFO]])),C_1_6[[#This Row],[ACTION - INFO]] <> "ACTION - INFO"),"Y","N") -> N
A46: C_5 | B46: DESIGN | I46: {=IFERROR(_xlfn.TEXTJOIN(" / ", TRUE, IF(OWNER_LIST[Owner Name]=C_1_6[[#This Row],[OWNER NAME 1]], OWNER_LIST[Owner ORG], ""), IF(OWNER_LIST[Owner Name]=C_1_6[[#This Row],[OWNER NAME 2]], OWNER_LIST[Owner ORG], "")), "")} | R46: =_xlfn.CONCAT(C_1_6[[#This Row],[ESCALATE]], "-",C_1_6[[#This Row],[Row_PM]]) -> - | S46: =_xlfn.CONCAT(C_1_6[[#This Row],[ESCALATE]], "-",C_1_6[[#This Row],[Notify_PM]]) -> - - | T46: =ROW() -> 46 | U46: =IF(C_1_6[[#This Row],[OWNER NAME 1]] = "", "", IF(_xlfn.XLOOKUP(C_1_6[[#This Row],[OWNER NAME 1]],OWNER_LIST[Owner Name], OWNER_LIST[Email], "") = "", "", _xlfn.XLOOKUP(C_1_6[[#This Row],[OWNER NAME 1]], OWNER_LIST[Owner Name], OWNER_LIST[Email], ""))) | V46: =IF(C_1_6[[#This Row],[OWNER NAME 2]] = "", "", IF(_xlfn.XLOOKUP(C_1_6[[#This Row],[OWNER NAME 2]],OWNER_LIST[Owner Name], OWNER_LIST[Email], "") = "", "", _xlfn.XLOOKUP(C_1_6[[#This Row],[OWNER NAME 2]], OWNER_LIST[Owner Name], OWNER_LIST[Email], ""))) | W46: =$A$25 -> C1 | X46: =IF(AND(NOT(ISBLANK(C_1_6[[#This Row],[ACTION - INFO]])),C_1_6[[#This Row],[ACTION - INFO]] <> "ACTION - INFO"),"Y","N") -> N
I47: {=IFERROR(_xlfn.TEXTJOIN(" / ", TRUE, IF(OWNER_LIST[Owner Name]=C_1_6[[#This Row],[OWNER NAME 1]], OWNER_LIST[Owner ORG], ""), IF(OWNER_LIST[Owner Name]=C_1_6[[#This Row],[OWNER NAME 2]], OWNER_LIST[Owner ORG], "")), "")} | R47: =_xlfn.CONCAT(C_1_6[[#This Row],[ESCALATE]], "-",C_1_6[[#This Row],[Row_PM]]) -> - | S47: =_xlfn.CONCAT(C_1_6[[#This Row],[ESCALATE]], "-",C_1_6[[#This Row],[Notify_PM]]) -> -- | T47: =ROW() -> 47 | U47: =IF(C_1_6[[#This Row],[OWNER NAME 1]] = "", "", IF(_xlfn.XLOOKUP(C_1_6[[#This Row],[OWNER NAME 1]],OWNER_LIST[Owner Name], OWNER_LIST[Email], "") = "", "", _xlfn.XLOOKUP(C_1_6[[#This Row],[OWNER NAME 1]], OWNER_LIST[Owner Name], OWNER_LIST[Email], ""))) | V47: =IF(C_1_6[[#This Row],[OWNER NAME 2]] = "", "", IF(_xlfn.XLOOKUP(C_1_6[[#This Row],[OWNER NAME 2]],OWNER_LIST[Owner Name], OWNER_LIST[Email], "") = "", "", _xlfn.XLOOKUP(C_1_6[[#This Row],[OWNER NAME 2]], OWNER_LIST[Owner Name], OWNER_LIST[Email], ""))) | W47: =$A$25 -> C1 | X47: =IF(AND(NOT(ISBLANK(C_1_6[[#This Row],[ACTION - INFO]])),C_1_6[[#This Row],[ACTION - INFO]] <> "ACTION - INFO"),"Y","N") -> N
I48: {=IFERROR(_xlfn.TEXTJOIN(" / ", TRUE, IF(OWNER_LIST[Owner Name]=C_1_6[[#This Row],[OWNER NAME 1]], OWNER_LIST[Owner ORG], ""), IF(OWNER_LIST[Owner Name]=C_1_6[[#This Row],[OWNER NAME 2]], OWNER_LIST[Owner ORG], "")), "")} | R48: =_xlfn.CONCAT(C_1_6[[#This Row],[ESCALATE]], "-",C_1_6[[#This Row],[Row_PM]]) -> - | S48: =_xlfn.CONCAT(C_1_6[[#This Row],[ESCALATE]], "-",C_1_6[[#This Row],[Notify_PM]]) -> -- | T48: =ROW() -> 48 | U48: =IF(C_1_6[[#This Row],[OWNER NAME 1]] = "", "", IF(_xlfn.XLOOKUP(C_1_6[[#This Row],[OWNER NAME 1]],OWNER_LIST[Owner Name], OWNER_LIST[Email], "") = "", "", _xlfn.XLOOKUP(C_1_6[[#This Row],[OWNER NAME 1]], OWNER_LIST[Owner Name], OWNER_LIST[Email], ""))) | V48: =IF(C_1_6[[#This Row],[OWNER NAME 2]] = "", "", IF(_xlfn.XLOOKUP(C_1_6[[#This Row],[OWNER NAME 2]],OWNER_LIST[Owner Name], OWNER_LIST[Email], "") = "", "", _xlfn.XLOOKUP(C_1_6[[#This Row],[OWNER NAME 2]], OWNER_LIST[Owner Name], OWNER_LIST[Email], ""))) | W48: =$A$25 -> C1 | X48: =IF(AND(NOT(ISBLANK(C_1_6[[#This Row],[ACTION - INFO]])),C_1_6[[#This Row],[ACTION - INFO]] <> "ACTION - INFO"),"Y","N") -> N
I49: {=IFERROR(_xlfn.TEXTJOIN(" / ", TRUE, IF(OWNER_LIST[Owner Name]=C_1_6[[#This Row],[OWNER NAME 1]], OWNER_LIST[Owner ORG], ""), IF(OWNER_LIST[Owner Name]=C_1_6[[#This Row],[OWNER NAME 2]], OWNER_LIST[Owner ORG], "")), "")} | R49: =_xlfn.CONCAT(C_1_6[[#This Row],[ESCALATE]], "-",C_1_6[[#This Row],[Row_PM]]) -> - | S49: =_xlfn.CONCAT(C_1_6[[#This Row],[ESCALATE]], "-",C_1_6[[#This Row],[Notify_PM]]) -> -- | T49: =ROW() -> 49 | U49: =IF(C_1_6[[#This Row],[OWNER NAME 1]] = "", "", IF(_xlfn.XLOOKUP(C_1_6[[#This Row],[OWNER NAME 1]],OWNER_LIST[Owner Name], OWNER_LIST[Email], "") = "", "", _xlfn.XLOOKUP(C_1_6[[#This Row],[OWNER NAME 1]], OWNER_LIST[Owner Name], OWNER_LIST[Email], ""))) | V49: =IF(C_1_6[[#This Row],[OWNER NAME 2]] = "", "", IF(_xlfn.XLOOKUP(C_1_6[[#This Row],[OWNER NAME 2]],OWNER_LIST[Owner Name], OWNER_LIST[Email], "") = "", "", _xlfn.XLOOKUP(C_1_6[[#This Row],[OWNER NAME 2]], OWNER_LIST[Owner Name], OWNER_LIST[Email], ""))) | W49: =$A$25 -> C1 | X49: =IF(AND(NOT(ISBLANK(C_1_6[[#This Row],[ACTION - INFO]])),C_1_6[[#This Row],[ACTION - INFO]] <> "ACTION - INFO"),"Y","N") -> N
I50: {=IFERROR(_xlfn.TEXTJOIN(" / ", TRUE, IF(OWNER_LIST[Owner Name]=C_1_6[[#This Row],[OWNER NAME 1]], OWNER_LIST[Owner ORG], ""), IF(OWNER_LIST[Owner Name]=C_1_6[[#This Row],[OWNER NAME 2]], OWNER_LIST[Owner ORG], "")), "")} | R50: =_xlfn.CONCAT(C_1_6[[#This Row],[ESCALATE]], "-",C_1_6[[#This Row],[Row_PM]]) -> - | S50: =_xlfn.CONCAT(C_1_6[[#This Row],[ESCALATE]], "-",C_1_6[[#This Row],[Notify_PM]]) -> -- | T50: =ROW() -> 50 | U50: =IF(C_1_6[[#This Row],[OWNER NAME 1]] = "", "", IF(_xlfn.XLOOKUP(C_1_6[[#This Row],[OWNER NAME 1]],OWNER_LIST[Owner Name], OWNER_LIST[Email], "") = "", "", _xlfn.XLOOKUP(C_1_6[[#This Row],[OWNER NAME 1]], OWNER_LIST[Owner Name], OWNER_LIST[Email], ""))) | V50: =IF(C_1_6[[#This Row],[OWNER NAME 2]] = "", "", IF(_xlfn.XLOOKUP(C_1_6[[#This Row],[OWNER NAME 2]],OWNER_LIST[Owner Name], OWNER_LIST[Email], "") = "", "", _xlfn.XLOOKUP(C_1_6[[#This Row],[OWNER NAME 2]], OWNER_LIST[Owner Name], OWNER_LIST[Email], ""))) | W50: =$A$25 -> C1 | X50: =IF(AND(NOT(ISBLANK(C_1_6[[#This Row],[ACTION - INFO]])),C_1_6[[#This Row],[ACTION - INFO]] <> "ACTION - INFO"),"Y","N") -> N
I51: {=IFERROR(_xlfn.TEXTJOIN(" / ", TRUE, IF(OWNER_LIST[Owner Name]=C_1_6[[#This Row],[OWNER NAME 1]], OWNER_LIST[Owner ORG], ""), IF(OWNER_LIST[Owner Name]=C_1_6[[#This Row],[OWNER NAME 2]], OWNER_LIST[Owner ORG], "")), "")} | R51: =_xlfn.CONCAT(C_1_6[[#This Row],[ESCALATE]], "-",C_1_6[[#This Row],[Row_PM]]) -> - | S51: =_xlfn.CONCAT(C_1_6[[#This Row],[ESCALATE]], "-",C_1_6[[#This Row],[Notify_PM]]) -> -- | T51: =ROW() -> 51 | U51: =IF(C_1_6[[#This Row],[OWNER NAME 1]] = "", "", IF(_xlfn.XLOOKUP(C_1_6[[#This Row],[OWNER NAME 1]],OWNER_LIST[Owner Name], OWNER_LIST[Email], "") = "", "", _xlfn.XLOOKUP(C_1_6[[#This Row],[OWNER NAME 1]], OWNER_LIST[Owner Name], OWNER_LIST[Email], ""))) | V51: =IF(C_1_6[[#This Row],[OWNER NAME 2]] = "", "", IF(_xlfn.XLOOKUP(C_1_6[[#This Row],[OWNER NAME 2]],OWNER_LIST[Owner Name], OWNER_LIST[Email], "") = "", "", _xlfn.XLOOKUP(C_1_6[[#This Row],[OWNER NAME 2]], OWNER_LIST[Owner Name], OWNER_LIST[Email], ""))) | W51: =$A$25 -> C1 | X51: =IF(AND(NOT(ISBLANK(C_1_6[[#This Row],[ACTION - INFO]])),C_1_6[[#This Row],[ACTION - INFO]] <> "ACTION - INFO"),"Y","N") -> N
B53: CHANGE MANAGEMENT

Sheet IT_Network_elevation
A1: Prerequisites to handover the switches: | C1: Action
A2: 1 | B2: Rack elevations are approved in PMWeb;
A3: 2 | B3: All works inside the TRs are finalized (except for the installation of the switches);
A4: 3 | B4: The TRs are cleaned and dust free;
A5: 4 | B5: If there are works generating dust in areas close to the TRs, the TRs have to be protected against the dust;
A6: 5 | B6: The TRs’ doors have temporary locks (until the access control is activated).
A8: Prerequisites to turn on the switches:
A9: 1 | B9: All switches provided to RPN are installed according to the rack elevation provided by RPN;
A10: 2 | B10: TRs are clean. The cleanliness has to be assessed by ICTS during a site visit.
A11: 3 | B11: Keys of the TRs are provided to ICTS;
A12: 4 | B12: The HVAC of the TRs is turned on;
A13: 5 | B13: The protected electricity (UPS) is available in the racks;
A14: 6 | B14: The certification of the optical fibers is approved in PMWeb;
A15: 7 | B15: Optical fiber patch cables are provided to ICTS to connect the switches to the UNOG LAN;

Sheet CLOSED
A1: 6 | B1: CLOSED
A2: C1 | B2: MEETING TOPIC | C2: ACTION - INFO | D2: STATUS | E2: DESCRIPTION - INFORMATION LOG | F2: ACTION REQUIRED | G2: PRIORITY | H2: DUE DATE | I2: OWNER ORG. | J2: OWNER NAME 1 | K2: OWNER NAME 2 | L2: DISCIPLINE | M2: DATE LOGGED | N2: DATE CLOSED | O2: ESCALATE | P2: Note | Q2: Row_PM | R2: Notify_PM | S2: Condition_PM | T2: Row | U2: Email_Name_1 | V2: Email_Name_2 | W2: SECTION | X2: Nonull
A3: VAR 106 | B3: BLDG C ARCHIVE FIRE PROTECTION | D3: CLOSED | E3: - | G3: 0 | N3: 18.07.2024 | S3: - | T3: 118 | U3: 0 | V3: 0 | W3: ActionClosed | X3: N
A4: VAR 138 | B4: BLDG C - ARCHIVES VENTILATION - BASEMENT | D4: CLOSED | E4: C: 12/06/23 | G4: 0 | N4: 18.07.2024 | S4: - | T4: 119 | U4: 0 | V4: 0 | W4: ActionClosed | X4: N
A5: VAR 167 | B5: UPPER WINDOW MOTORIZATION | D5: CLOSED | E5: - | G5: INS 268, INS 326 | N5: 18.07.2024 | S5: - | T5: 120 | U5: 0 | V5: 0 | W5: ActionClosed | X5: N
A6: VAR 180 | B6: BDLG C LB2 PLANTROOM C.0014 | D6: CLOSED | E6: C: 28-Jul-23 | G6: 0 | N6: 18.07.2024 | S6: - | T6: 121 | U6: 0 | V6: 0 | W6: ActionClosed | X6: N
A7: VAR 221 | B7: EMERGENCY SIGNAGE AND LIGHTING UPDATE C | D7: CLOSED | E7: No Info | G7: INS 348 | N7: 45498 | S7: - | T7: 122 | U7: 0 | V7: 0 | W7: ActionClosed | X7: N
A8: VAR 243 | B8: FIRE DETECTION SKYLIGHTS BLDG B and C | D8: CLOSED | E8: - | G8: 0 | S8: - | T8: 123 | U8: 0 | V8: 0 | W8: ActionClosed | X8: N
A9: VAR 249 | B9: Bldg C- SKYLIGHT SECURITY AND LIGHTING CONTROL | D9: CLOSED | E9: - | G9: 0 | S9: - | T9: 124 | U9: 0 | V9: 0 | W9: ActionClosed | X9: N
A10: VAR 260 | B10: BLDGS A / AB / C - INTERPRETER BOOTHS ACOUSTICS | D10: CLOSED | E10: AB: 21/05/2024 C: 23/04/2024 | G10: INS 311 | S10: - | T10: 125 | U10: 0 | V10: 0 | W10: ActionClosed | X10: N
A11: INS 341 | B11: Bldg C fire dampers VAR 138 - Rev 1 | D11: CLOSED | E11: 0 | G11: #N/A | N11: 18.07.2024 | S11: - | T11: 126 | U11: 0 | V11: 0 | W11: ActionClosed | X11: N
A12: VAR 387 | B12: BLDG C BLIND AND MOTORIZED WINDOW BOXES | D12: CLOSED | E12: - | G12: 0 | S12: - | T12: 127 | V12: 0 | W12: ActionClosed | X12: N
A13: VAR 395 | B13: BLDG C - COUNCIL CHAMBER AV RACKS RELOCATION | D13: CLOSED | E13: C: 16-Apr-25 | G13: 0 | N13: 45498 | S13: - | T13: 128 | U13: 0 | V13: 0 | W13: ActionClosed | X13: N
A14: VAR 399 | B14: BLDG C L02 COUNCIL CHAMBER GALLERY EXIT | D14: CLOSED | E14: - | G14: 0 | N14: 18.07.2024 | S14: - | T14: 129 | U14: 0 | V14: 0 | W14: ActionClosed | X14: N
A15: INS 408 | B15: Bldg C - PA speakers L01-L02 - Open Aera Council Chamber - PA speakers | D15: CLOSED | E15: 0 | G15: #N/A | S15: - | T15: 130 | U15: 0 | V15: 0 | W15: ActionClosed | X15: N
A16: VAR 416 | B16: BLDG C EXISTING OPENINGS IN BASEMENTS | D16: CLOSED | E16: - | G16: 0 | N16: 18.07.2024 | S16: - | T16: 131 | U16: 0 | V16: 0 | W16: ActionClosed | X16: N
A17: VAR 426 | B17: BLDG C - IT CABLING | D17: CLOSED | E17: - | G17: 0 | N17: 18.07.2024 | S17: - | T17: 132 | U17: 0 | V17: 0 | W17: ActionClosed | X17: N
A18: INS 409 | B18: Bldg C stair 5 corridors changes | D18: CLOSED | E18: 0 | G18: #N/A | N18: 45498 | S18: - | T18: 133 | U18: 0 | V18: 0 | W18: ActionClosed | X18: N
A19: VAR 449 | B19: BLDG C SENSITIVE ROOMS - SALON RUSSE + LOBBY | D19: CLOSED | E19: No Info | G19: 0 | S19: - | T19: 134 | U19: 0 | V19: 0 | W19: ActionClosed | X19: N
A20: VAR 450 | B20: BLDG C SENSITIVE ROOMS - SALLE 1 AND 2 | D20: CLOSED | E20: - | G20: 0 | M20: 01.10.2024 | S20: - | T20: 135 | U20: 0 | V20: 0 | W20: ActionClosed | X20: N
A21: VAR 474 | B21: BLDG C - ENTRANCE AND PRESS BAR NEW STONE LAYOUT | D21: CLOSED | E21: - | G21: 0 | N21: 18.07.2024 | S21: - | T21: 136 | U21: 0 | V21: 0 | W21: ActionClosed | X21: N
A22: VAR 493 | B22: BLDG C - UNTV DOORS | D22: CLOSED | E22: - | G22: 0 | N22: 6.11.2024 | S22: - | T22: 137 | U22: neil.bradley@un.org | V22: 0 | W22: ActionClosed | X22: N
A23: VAR 494 | B23: BLDG C - UNTV BLINDS | D23: CLOSED | E23: - | G23: 0 | N23: 6.11.2024 | S23: - | T23: 138 | U23: jessica.donatelli@cmbcarpi.it | V23: 0 | W23: ActionClosed | X23: N
A24: VAR 504 | B24: Access control IT room LB1 S1 | D24: CLOSED | E24: No Info | G24: 0 | S24: - | T24: 139 | U24: 0 | V24: 0 | W24: ActionClosed | X24: N
A25: VAR 506 | B25: BDLG C ADDITIONAL FIRE DETECTION DEVICES (CDP) | D25: CLOSED | E25: No Info | G25: 0 | S25: - | T25: 140 | U25: 0 | V25: 0 | W25: ActionClosed | X25: N
B26: Final EL installation for Skylight RFI-0930-b | D26: CLOSED | N26: 18.07.2024 | S26: - | T26: 141 | U26: 0 | V26: 0 | W26: ActionClosed | X26: N
B27: MAG 5.1 - MEP Installation blocked by archives presence | D27: CLOSED | N27: 18.07.2024 | S27: - | T27: 142 | U27: 0 | V27: 0 | W27: ActionClosed | X27: N
B28: Opening for electrical elements to be validated | D28: CLOSED | N28: 18.07.2024 | S28: - | T28: 143 | U28: 0 | V28: 0 | W28: ActionClosed | X28: N
D29: CLOSED | F29: VAR 527 has been issued | S29: - | T29: 144 | U29: 0 | V29: 0 | W29: ActionClosed | X29: N
D30: CLOSED | F30: RPN subcontract to update documents | S30: - | T30: 145 | U30: 0 | V30: 0 | W30: ActionClosed | X30: N
D31: CLOSED | F31: RPN to issue design | S31: - | T31: 146 | U31: 0 | V31: 0 | W31: ActionClosed | X31: N
D32: CLOSED | F32: Subcontractor of roller shutter (Rieder) to provide missing technical informations (dimension & position of motor) | S32: - | T32: 147 | U32: 0 | V32: 0 | W32: ActionClosed | X32: N
D33: CLOSED | F33: RPN to provide the List of equipment. To be confirmed by UNTV | S33: - | T33: 148 | U33: 0 | V33: 0 | W33: ActionClosed | X33: N
D34: CLOSED | F34: Check with UNTV stakeholders whether vision panel in door type C_WD104 can be ommited | M34: 45480 | S34: - | T34: 149 | U34: 0 | V34: 0 | W34: ActionClosed | X34: N
D35: CLOSED | F35: SOMBP to provide sketch | M35: 45510 | S35: - | T35: 150 | U35: 0 | V35: 0 | W35: ActionClosed | X35: N
D36: CLOSED | F36: RPN to fill the gap with bricks, will be considered as exisiting | M36: 45510 | S36: - | T36: 151 | U36: 0 | V36: 0 | W36: ActionClosed | X36: N
D37: CLOSED | F37: RPN confirmed the marble has been stored and will be reinstalled | M37: 45510 | S37: - | T37: 152 | U37: 0 | V37: 0 | W37: ActionClosed | X37: N
D38: CLOSED | F38: 27.11 cost agreed, step 4 to be issued | G38: 1 | S38: - | T38: 153 | U38: 0 | V38: 0 | W38: ActionClosed | X38: N
D39: CLOSED | F39: 27.11 cost agreed, step 4 to be issued | G39: 3 | S39: - | T39: 154 | U39: 0 | V39: 0 | W39: ActionClosed | X39: N
D40: CLOSED | F40: 27.11, cost agreed SHP to issue step 4 | G40: TOP | S40: - | T40: 155 | U40: 0 | V40: 0 | W40: ActionClosed | X40: N
B41: Planning updates | C41: INFO (New) | D41: CLOSED | E41: 10.12: Visual board have been updated | G41: Red | O41: Planning updates | S41: Planning updates- | T41: 156 | U41: matteo.naldi@cmbcarpi.it | V41: simone.conti@cmbcarpi.it | W41: ActionClosed | X41: Y
B42: SALLE 1 & 2 | C42: INFO (New) | D42: CLOSED | E42: 03.12: EGGTELSA refuse the VAR 450 split (FLS updates) - VAR was determined on 19th of sept 2024. 11.12: EGGTELSA validated the cost and is proceeding | G42: Red | O42: SALLE 1 & 2 | S42: SALLE 1 & 2- | T42: 157 | U42: jessica.donatelli@cmbcarpi.it | W42: ActionClosed | X42: Y
B43: PRESS KITCHEN | C43: INFO | D43: CLOSED | E43: Metal structure to support Chillers above cold room will be installed week 01.12 | O43: PRESS KITCHEN | S43: PRESS KITCHEN- | T43: 158 | W43: ActionClosed | X43: Y
B44: VAR 385 toilet | C44: INFO | D44: CLOSED | E44: Works on going at leve 1 & 4 | O44: VAR 385 toilet | S44: VAR 385 toilet- | T44: 159 | W44: ActionClosed | X44: Y
B45: Revolving doors entrance C6 | C45: INFO | D45: CLOSED | E45: 06.11: Dormakaba already came on site to take measurement of doors. Doors will be delivered +/- end of January | S45: - | T45: 160 | W45: ActionClosed | X45: Y
B46: Insulation around Windows at level 5 | C46: INFO (New) | D46: CLOSED | E46: 05.12: site visit, RPN raised an issue regarding colocation of insulating material around new windows that will damage the heritage marble in toilets | F46: 11.12: SOMBP to assess whether insulation is required or can be omitted. 18.12: issue closed, see weekly Technical meeting #193 | S46: - | T46: 161 | W46: ActionClosed | X46: Y
S47: - | T47: 162 | U47: 0 | V47: 0 | W47: ActionClosed | X47: N
S48: - | T48: 163 | U48: 0 | V48: 0 | W48: ActionClosed | X48: N
S49: - | T49: 164 | U49: 0 | V49: 0 | W49: ActionClosed | X49: N
B50: RADIATOR PEDESTAL | C50: ACTION | D50: CLOSED | E50: 12.02: sample have been approved 19.02: MAS have been submitted 26.02: MAS have been approved | F50: -
B51: SALLE 1 - unexpected RJ45 | C51: ACTION | D51: CLOSED | E51: 12.02: during Sensitive room site viste (11.02) unexpected new RJ45 in floor box was noticed 19.02: unexpected RJ45 is accepted as it is in floor box | F51: 12.02: Sensitive room site viste notice unexpected new RJ45 in floor box. SHP to confirm if NCF/ TCI / RFI is to be raised
B52: TC5 | C52: INFO | D52: CLOSED | E52: 10.02: 2 AV rack are to be removed from TC5 to perform activities | F52: 18.02: SHP/ FMS will remove AV rack dedicated to salle 1. RPN/ 3P will remove AV rack deicated to Council chamber. 26.02: SHP/ FMS to remove AV rack dedicated to salle 1. | G52: Medium
B53: UNTV - Works | C53: INFO | D53: CLOSED | E53: [Records have been copied in commnents, refer to xls sheet for details] 19.02: Ecophon Ceiling haven't been installed and Electrical terminal haven't been installed in UNTV - does not affect Cleansite. | G53: Low
B54: MEETING ROOM - AV | C54: INFO | D54: CLOSED | E54: 12.02: VAR 299 show sound bar bellow TV. sockets are in conflict with the sokets. Overseen by VAR 478 19.03: INS received | F54: 12.02: SMW (Ben Lang) to update VAR 299 including Roomba above TV. 19.02: SHP to clarify CISCOBAR and support detail | G54: Medium
B55: SALLE C6 - Coordination | C55: INFO | D55: CLOSED | E55: 19.02: Design includes AV conection and furniture in Mural 19.02: Position of cameras and speakers conflict with emergency signage | F55: 19.02 Raise to architectural meeting | G55: Medium
B56: UNTV - edit & Control room + touchdown | C56: ACTION (New) | D56: CLOSED | E56: 12.03: False ceiling will be ready to install +/- 20.03 19.03: ELEC & Mechanical inspection have been run No Major issues | F56: 26.03: RPN to issue MOM regarding last week site walks - cable tray mokeup - floor detail passage cables/ door | G56: Medium
B57: PRESS BAR Cold room | C57: INFO | D57: CLOSED | E57: 26.02: Cold room will be installed after all dusty works is completed | G57: Low
B58: COUNCIL CHAMBER - Ceiling finishes | C58: INFO | D58: CLOSED | E58: 02.04: no changes have been noted from the condition report. | F58: 12.03: +/- 20m false marble ceiling @L0 and mezzanine to be repared. => RPN to propose cost | G58: Low
B59: COUNCIL CHAMBER - Cameras | C59: ACTION | D59: CLOSED | F59: 12.02 [AV focus meeting]: RPN to provide details of cameras for Historic architects approval. | G59: Low
B60: UNTV - Colour of furnitures in Edit room | C60: ACTION (New) | D60: CLOSED | E60: 26.03: SHP confirm that colour of furnitures in edit room is: STANDARD 7043 (dark grey) as per supplier's catalogue. | F60: 26.03: RPN to order desks | G60: Medium
B61: PRESS BAR INS 353 descope of shutter | C61: ACTION | D61: CLOSED | G61: High
B62: SALLE 2 | C62: INFO | D62: CLOSED | E62: [Records have been copied in commnents, refer to xls sheet for details] 12.03: Library is ready to move from Bldg. A to Bldg. C & AC 19.03: Hazard materious is preasent in flooring. Works will be proceed from bellow. RPN to inform SHP. | F62: 26.03: RPN will raise RFI Daywork for ceiling restauration | G62: Low
B63: UNTV - NCF | C63: ACTION | D63: CLOSED | E63: 09.04: 2 NCF are open | F63: 09.04: NCF were closed by dismantling the studio Administartive works to be completed | G63: Medium
B64: UNTV - Contract for AV instalation | C64: INFO | D64: CLOSED | E64: 09.04: Contract with VISUAL has been signed | G64: TOP
B65: Door updates | C65: ACTION (New) | D65: CLOSED | E65: 08.04: very urgent variation | F65: 08.04: SHP to issue step 1 (on signature). | G65: High
B66: ARCHIVES - MAG 6 | C66: INFO | D66: CLOSED | E66: VAR 106 fire encasement of steel beams, only need paints 28.01 : UN Archive requires a plan to have this room back. 02.04: Pelichet is installing the shelves. 09.04: works completed, | F66: 09.04: SHP to organise moves of the archives | G66: Medium
B67: FLS design issues | C67: INFO | D67: CLOSED | E67: 15.01: Leson learned from other sections to be implemented on site | G67: Medium
B68: L0 | C68: INFO | D68: CLOSED | E68: 05.02 Instalation of cable trays proceeding | G68: Low
B69: L02 | C69: INFO | D69: CLOSED | E69: 05.02 : Eggtelsa pooling cables | F69: 19.03: Insulation behind radiator to be done | G69: Low
B70: L03 | C70: INFO | D70: CLOSED | E70: 19.02: Eggtelsa is proceeding | F70: 19.03: Insulation behind radiator to be done | G70: Low
B71: L04 | C71: INFO | D71: CLOSED | E71: 22.01: ISOSUISSE to start ceiling installation 19.03: Insulation behind radiator has been done. | G71: Low
B72: L05 | C72: INFO | D72: CLOSED | E72: 22.01: Ceiling completed by ISO SUISSE first layer of painting completed. Carpet installed Linoleum to be installed at the last moment 19.03: Insulation behind radiator has been done. | G72: Low
B73: COUNCIL CHAMBER - Fire curtains | C73: INFO | D73: CLOSED | F73: 19.02: SHP to confirm architectural finishes 26.02: Consorcio Auro to propose matching color | G73: Low
B74: COUNCIL CHAMBER | C74: INFO | D74: CLOSED | E74: 22.01: 3P made a survey, all equipments are in place. Inventory to be submitted after Bldg. A & AB inventory is agreed. 19.02: Strip out started | F74: 05.02: Preparatory work to start next week. 12.02: Strip out of old cables started (EGGTELSA) | G74: Low
B75: Meeting room AV - INS 430 | C75: ACTION | D75: CLOSED | E75: 02.04: RPN is requesting daywork | F75: 02.04: SHP to issue step 3 | G75: Medium
B76: SALON FRANCAIS - Leuleu table (shark skin) | C76: ACTION | D76: CLOSED | E76: 09.04: Inspection has been run +/-1.5Y agor. Table is to be repaired 14.05: VIGANO is proceeding to refurbishment | G76: Low
B77: UNTV - Rack elevation | C77: ACTION | D77: CLOSED | E77: 13.05: Rack elevation design rev.6 has been submitted | G77: TOP
B78: UNTV - Vapour barier | C78: ACTION | D78: CLOSED | E78: 16.04: no MAS for the Installed Vapour Barier (yellow) has been approved nor submitted by RPN. installation no not comply with requirements. 30.05: Site adjustment will not affect clean site date. 14.05: ISOSUISSE is proceeding on site | G78: Medium
B79: UNTV - INS 469 Window frame in Corridor | C79: ACTION | D79: CLOSED | E79: 13.05: SOMBP issued INS 469 | F79: 13.05: SHP to issue Step 1 | G79: Medium
B80: UNTV - Doors & window supply | C80: INFO | D80: CLOSED | E80: 19.02: Potential conflict between external windows and internal doors and "Clean site" 30.04: Windows have been received for LB01 and L00 Visual & Treepe site visit organized on 30.04 | F80: 30.04: doors to be delivered.RPN to confirm 30.04: Visual & Treepe to start 05.05 | G80: High
B81: All bldgs - Fire curtain keys VAR 553 | C81: ACTION (New) | D81: CLOSED | E81: 21.05: | F81: 19.03: RPN to issue commercial proposal | G81: Medium
B82: SALON TCHEQUE - Zodiac Artwork | C82: INFO | D82: CLOSED | E82: 16.04: Survey is ongoing Consorcio Auro do recomend comprehensive reparation | F82: 16.04: SHP to raise the issue to Tcheque and Slovak delegation 07.05: SHP confirm that cracks will not be treated | G82: Medium
A83: VAR 600 | B83: SALON FRANCAIS - Kasskoff artwork | C83: ACTION | D83: CLOSED | E83: [Records have been copied in commnents, refer to xls sheet for details] 09.04: Gulia has provided feedback "Peeling is due to natural process". | F83: 13.05: Cost has been approved. SHP to issue VAR | G83: Medium
B84: SENSITIVE ROOM - Doors | C84: ACTION (New) | D84: CLOSED | G84: High
B85: PRESS BAR - Fire closure in ceiling | C85: ACTION | D85: CLOSED | F85: 14.05: [see rosario] RPN to share the schematic diagram of fire | G85: Medium
B86: SALON FRANCAIS - VAR 457 | C86: ACTION | D86: CLOSED | E86: [Records have been copied in commnents, refer to xls sheet for details] 02.03: VAR 457 Step3 rev. 1 has been issued | G86: Medium
B87: ENTRANCE C6 - Fire panel | C87: ACTION | D87: CLOSED | F87: 28.05: SHP to issue step 1
B88: PRESS BAR - Cingria substructure | C88: ACTION | D88: CLOSED | E88: 28.05: EGGTELSA complete the works ISOSUISSE completeing the false ceiling
B89: SALON FRANCAIS - Emergency light in salon Roumain | C89: ACTION | D89: CLOSED | E89: 30.04: Works to be done through Salle IV floor 04.06: path have been confirmed | F89: 21.05: SHP to confirm the path | G89: Low
A90: F | B90: SALLE C6 - Gap around Interpreter booth window - KNAUF diamond to be installed between Booth. | C90: ACTION | D90: CLOSED | E90: 14.05: Discrepencies between approved design and execution 28.05: TCI was open and solution proposed. 06.04: NCF has been raised | F90: 21.05: SOMBP to check with Kopitsis Lucille Treille de Grandsaigne (new email, UN-IT is working on the problem) | G90: Medium
B91: SALLE C6 - Subwoofer | C91: ACTION | D91: CLOSED | E91: 28.05: Subwoofer position is unique. | F91: 14.05: Refer to AV meeting | G91: High
A92: INS 478 | B92: SALON TCHEQUE - Lighting Fixtures | C92: ACTION | D92: CLOSED | E92: 30.04: Outdated fluorescent light to be updated 15.05: RPN proposed LED lighting 10.06: INS 478 has been submitted | G92: Low
B93: SALON FRANCAIS - Void | C93: ACTION | D93: CLOSED | E93: 04.06: The void has been indentified as a ventilation plenum 11.06; confirmed
B94: PRESS BAR - Cingria prototype | C94: ACTION | D94: CLOSED | E94: [Records have been copied in commnents, refer to xls sheet for details] 09.04: Survey has been runed. metal structure is required (big Cingria) Small cingria will be supported by inserts | G94: Medium
B95: Works on Council chamber roof | C95: INFO | D95: CLOSED | F95: 21.05: RPN will issue conditional report in DALUX 21.05: SHP to confirm load | G95: Low
B96: Existing cupboard and internal doors | C96: ACTION | D96: CLOSED | E96: 30.04: SHP/ SOMBP/ RPN have organized site survey ACAPI to start final painting by +/- 05.05. 14.05: RPN submit proposal - x% to RPN - x% fine - 1/3 to be shared - 1/3 to FMS 11.06: Damages are tracked by RPN RPN to paint the cupboard damaged by them only | F96: 30.04: RPN to complete L02 & 03 and issue final site report 21.05 SHP to assess type of intervention (see ROSARIO email) 04.06: SHP/ SOMBP to assess and raise TCI | G96: High
B97: SALON RUSSE - Furnitures | C97: ACTION | D97: CLOSED | F97: 03.06: RPN to confirm that all furniture items included in the excel are in good condition and continue to work as intended. | G97: Low
B98: SALLE 1 - Emergency light | C98: ACTION | D98: CLOSED | E98: [Records have been copied in commnents, refer to xls sheet for details] 19.02: 1 Lux is required.SHP to confirm position 02.04: INS 454 emergency lights have bee received. 15.05: Step1 has been issued | F98: 18.06: RPN to confirm if works can be covered by RFI daywork | G98: Low
B99: WINDOW FRAMES - Plasterboard instead of wood | C99: ACTION | D99: CLOSED | E99: [Records have been copied in commnents, refer to xls sheet for details] 30.05: SOMBP issued the INS 11.06: INS has been submitted 18.06: | F99: 25.06: refer to Pre-Construction meeting | G99: Medium
B100: SALON TCHEQUE - Sample painting | C100: INFO | D100: CLOSED | E100: [Records have been copied in commnents, refer to xls sheet for details] 09.04: Sample painting has been done. 15.04: Colour samples have been presented & rejected. 28.05: New colours samples have been rejected. 27.06: sample colour has been approved "BLANC champigny mat" | G100: Medium
...

Sheet OWNER LIST
A1: Owner Name | B1: Email | C1: Owner ORG | D1: Role | E1: Main ORG | F1: No sharepoint | G1: NameforMondayemail | H1: ACRONYM
A2: Abigail Abraham | B2: donatella.rocca@un.org | C2: MSTEP | D2: TBC | E2: SOMBP | F2: abigail@mstep.co.uk | G2: Abigail
A3: Alan McBryan | B3: alan.mcbryan@aecom.com | C3: AECOM | D3: MEP Manager | E3: SOMBP | G3: Alan
A4: Alastair Wolstenholme | B4: a.wolstenholme@gardiner.com | C4: G&T | D4: Senior Associate - Cost Management and Contract Administration | E4: G&T | G4: Alastair
A5: Alberto Mastrangelo | B5: pme_to.srl@libero.it | C5: PME | D5: TBC | E5: RPN | G5: Alberto
A6: Alex Graham | B6: alexander.graham1@un.org | C6: SHP | D6: Cost Management | E6: SHP | G6: Alex
A7: Alexandre ROUVELET | B7: alexandre.rouvelet@projection-nouvelle.com | D7: Overall System Engineer | G7: Alexandre
A8: Alessandro Manfredi
A9: Alistair Wade | B9: a.wade@gardiner.com | C9: G&T | D9: Cost Management | E9: G&T | G9: Alistair
A10: Amos Anderini | B10: amos.anderini@rpn-sa.ch | C10: RPN | D10: Deputy HSE & Security Manager | E10: RPN | G10: Amos
A11: Andrea Falchi | B11: andrea.falchi@c2be.uno | C11: C2BE | D11: TBC | E11: C2BE | G11: Andrea
A12: Andrea Hoffman | B12: ahoffmann@hoffmannart.ch | C12: SHP | D12: Heritage/Art Expert | E12: SHP | G12: Andrea
A13: Andrea Sigona | B13: bob.wyse@som.com | C13: SOMBP | D13: Senior Architect | E13: SOMBP | G13: Bob
A14: Andrea VANOSSI | B14: a.vanossi@gmail.com | D14: BIM Manager | G14: Andrea
A15: Andrei Misaila | B15: septimiu.misaila@un.org | C15: UN | D15: TBC | E15: UN | G15: Andrei
A16: Barry Poling | B16: barry.poling@aspenglobal.co.uk | C16: ASPEN | D16: Lean Consultant | E16: ASPEN | G16: Barry
A17: Ben Lang | B17: blang@smwllc.com | C17: SMW | D17: TBC | E17: SOMBP | G17: Ben
A18: Benoit Renault | B18: benoit.renault@un.org | C18: SHP | D18: Senior Electrical Engineer | E18: SHP | G18: Benoit
A19: Bernard Mégevand | B19: bernard.megevand@sbis.ch | C19: SBIS | D19: TBC | E19: SOMBP | G19: Bernard
A20: Bhav | B20: bhav@mstep.co.uk | C20: MSTEP | D20: TBC | E20: SOMBP | G20: Bhav
A21: Billy Clayton | B21: b.clayton@Gardiner.com | C21: G&T | D21: Cost Management | E21: G&T | G21: Billy
A22: Blaise BOURGEOIS | B22: bb@oxalis-landscape.ch | D22: Associate Director | G22: Blaise
A23: Bob Wyse | B23: bob.wyse@som.com | C23: SOMBP | D23: Architect | E23: SOMBP | G23: Bob
A24: Calum Redfern | B24: c.redfern@gardiner.com | C24: G&T | D24: Cost Management | E24: G&T | G24: Calum
A25: Catherine Isabella | B25: catherine.isabella@burckhardt.swiss | C25: SOMBP | D25: Architect | E25: SOMBP | G25: Catherine
A26: Cedric Erard | B26: ce@erard.biz | C26: SOMBP | D26: MEP Manager | E26: SOMBP | G26: Cedric
A27: Cedric Kusendova | B27: cedric.kusendova@un.org | C27: SHP | D27: MEP Manager | E27: SHP | G27: Cedric
A28: Charles de Crisenoy | B28: didier.dequatre@un.org | C28: SHP | D28: Quality Manager | E28: SHP | G28: Didier
A29: Chiara Re Depaolini | B29: chiara.redepaolini@rpn-sa.ch | C29: RPN | D29: Arch Design Specialist | E29: RPN | G29: Chiara
A30: Chris Welch | B30: c.welch@gardiner.com | C30: G&T | D30: Cost Management | E30: G&T | G30: Chris
A31: Christian Bona | B31: christian.bona@rpn-sa.ch | C31: RPN | D31: MEP Manager | E31: RPN | G31: Christian
A32: Cinzia Porracin | B32: porracin@un.org | C32: SHP | D32: Security Site Construction Management | E32: SHP | G32: Cinzia
A33: Clare O'Malley | B33: c.omalley@gardiner.com | C33: G&T | D33: Cost Management | E33: G&T | G33: Clare
A34: Consuelo Crespi | B34: consuelo.crespi@csc-sa.ch | C34: C2BE | D34: H&S Manager | E34: C2BE | G34: Consuelo
... A42: David Heison | B42: david.heison@un.org | C42: SHP | D42: Handover and Commissioning Management | E42: SHP | G42: David
A43: David R. HARVEY | B43: david@hmb-a.com | D43: Associate | G43: David
A44: Davide Cirillo | B44: davide.cirillo@cmbcarpi.it | C44: RPN | D44: Quality Manager | E44: RPN | G44: Davide
A45: Deán de Klerk | B45: dean.deklerk@un.org | C45: SHP | D45: Project Schedule Manager | E45: SHP | G45: Deán
A46: Didier Chessel | B46: didier.chessel@un.org | C46: SHP | D46: Health and Security Coordinator | E46: SHP | G46: Didier
A47: Didier Dequatre | B47: didier.dequatre@un.org | C47: SHP | D47: Quality Manager | E47: SHP | G47: Didier
A48: Dima Khoury | B48: dima.khoury@un.org | C48: UN | D48: TBC | E48: UN | G48: Dima
A49: Dominic Walther | B49: dominic.walther@burckhardt.swiss | C49: SOMBP | D49: Design and Construction Director | E49: SOMBP | G49: Dominic
A50: Dominique Hirigoyen | B50: dominique.hirigoyen@un.org | C50: UN | D50: electronic engineering technician | E50: UN | G50: Dominique
A51: Donatella Rocca | B51: donatella.rocca@un.org | C51: SHP | D51: Documents Manager | E51: SHP | G51: Donatella
A52: DOR_D | B52: donatella.rocca@un.org | C52: SHP | D52: TBC | E52: SHP | G52: Donatella
A53: DOR_N | B53: donatella.rocca@un.org | C53: SHP | D53: TBC | E53: SHP | G53: Donatella
A54: DOR_M | B54: donatella.rocca@un.org | C54: SHP | D54: TBC | E54: SHP | G54: Donatella
A55: DOR_P | B55: donatella.rocca@un.org | C55: SHP | D55: TBC | E55: SHP | G55: Donatella
... A77: Francesco Sambucini | B77: francesco.sambucini@rpn-sa.ch | C77: RPN | D77: HSE Deputy Manager | E77: RPN | G77: Francesco
A78: Franck Reynaud | C78: Visuals | D78: TBC | E78: RPN | F78: franck@visuals.ch | G78: Frank
A79: Frank Lambelet | B79: lambelet@bcs-facades.ch | C79: Bcs facades | D79: TBC | E79: SOMBP | G79: Frank
A80: Frederic Solda | B80: frederic.solda@csc-sa.ch | C80: C2BE | D80: Planner Manager | E80: C2BE | G80: Frederic
A81: Gabriele Provenzale | B81: gabriele.provenzale@csc-sa.ch | C81: C2BE | D81: Design/Construction Manager CSA | E81: C2BE | G81: Gabriele
A82: Gary Thornton | B82: gary@nultylighting.co.uk | C82: Lighting | D82: Lighting | E82: SOMBP | G82: Gary
A83: Geoffrey Pillitteri | B83: geoffrey.pillitteri@un.org | C83: UN | D83: TBC | E83: UN | G83: Geoffrey
A84: Gerald Robinson | B84: gerald@aspenglobal.co.uk | C84: ASPEN | D84: Lean Consultant | E84: ASPEN | G84: Gerald
A85: Giada Savini | B85: giada.savini@rpn-sa.ch | C85: RPN | D85: Senior Architect | E85: RPN | G85: Giada
A86: Gianluca Crippa | B86: gianluca.crippa@rpn-sa.ch | C86: RPN | D86: Construction Manager | E86: RPN | G86: Gianluca
A87: Giulia Amendola | B87: giulia.amendola@rpn-sa.ch | C87: RPN | D87: TBC | E87: RPN | G87: Giulia
A88: Giulia Putaturo | B88: g.putaturo@fratellinavarra.it | C88: RPN | D88: Heritage/Art Expert | E88: RPN | G88: Giulia
A89: Goran Josipovic | B89: goran.josipovic@wsp.com | C89: Lift | D89: TBC | E89: SOMBP | G89: Goran
A90: Gregory Baubiet | B90: lucille.treilledegrandsaigne@burckhardt.swiss | C90: SOMBP | D90: Architect | E90: SOMBP | G90: Gregory
A91: Guillermo Garcia | B91: guillermo.garcia@afry.com | C91: AFRY | E91: SOMBP | G91: Guillermo
A92: Hacir Degirmencioglu | B92: hacir.degirmencioglu@rpn-sa.ch | C92: RPN | D92: Electrical Engineer | E92: RPN | G92: Hacir
A93: Hamza Haouass | B93: hamza.haouass@csc-sa.ch | C93: C2BE | D93: TBC | E93: RPN | G93: Hamza
A94: Helen Shreeve | B94: h.shreeve@gardiner.com | C94: G&T | D94: Cost Management | E94: G&T | G94: Helen
A95: Ibtisam Naym | B95: ibtisam.naym@rpn-sa.ch | C95: RPN | D95: Documents Manager | E95: RPN | G95: Ibtisam
A96: Ishac Koussa | B96: ishac.koussa@som.com | C96: SOMBP | D96: TBC | E96: SOMBP | G96: Ishac
A97: Jaime Gutierrez | B97: jaime.gutierrez@burckhardt.swiss | C97: SOMBP | D97: Architect | E97: SOMBP | G97: Jaime
A98: James Staunton | B98: james.staunton@aecom.com | C98: AECOM | D98: TBC | E98: SOMBP | G98: James
A99: Jean-Marc Glinz | B99: jean-marc.glinz@un.org | C99: UNTV | D99: Chief of unit, Public information | E99: UN | G99: Jean-Marc
A100: Jean-Mathieu Ferre | B100: jean.ferre@un.org | C100: SHP | D100: Design Manager (DM) | E100: SHP | G100: Jean-Mathieu
A101: Jeremy Theniere | B101: jeremy.theniere1@un.org | C101: SHP | D101: Move expert | E101: SHP | G101: Jeremy
A102: Jérôme Colder | B102: j.colder@jdrenergies.ch | C102: AECOM | D102: TBC | E102: SOMBP | G102: Jérôme
A103: Jérome MATRINGE | B103: jerome.matringe@projection-nouvelle.com | D103: Technical on-site Manager | G103: Jérome
A104: Jérôme POCHAT | B104: jerome.pochat@ingeni.ch | D104: Partner | G104: Jérôme
A105: Jessica Donatelli | B105: jessica.donatelli@cmbcarpi.it | C105: RPN | D105: Cost Control Manager | E105: RPN | G105: Jessica
A106: Joachim de Roquefeuil | B106: joachim.deroquefeuil@sbis.ch | C106: SBIS | D106: TBC | E106: SOMBP | G106: Joachim
A107: Joe Gul | B107: j.gul@gardiner.com | C107: G&T | D107: Assistant Cost Management and Contract Administration | E107: G&T | G107: Joe
A108: Joel Benghiat | B108: joel.benghiat@nembrini.com | C108: NEMB | D108: TBC | E108: RPN | G108: Joel
A109: John Rutter | B109: john@aspenglobal.co.uk | C109: ASPEN | D109: Lean Consultant | E109: ASPEN | G109: John
A110: Joseph Christi | B110: jchristi@smwllc.com | C110: SMW | D110: TBC | E110: SOMBP | G110: Joseph
A111: Josiah Abraham | B111: josiah@mstep.co.uk | C111: MSTEP | D111: Mechanical Engineer | E111: SOMBP | G111: Josiah
A112: Julia Skeete | B112: julia.skeete@som.com | C112: SOMBP | D112: Project Director (PD) | E112: SOMBP | G112: Julia
A113: Kateryna Starykova | B113: kateryna.starykova@un.org | C113: SHP | D113: Senior Electrical Engineer | E113: SHP | G113: Kateryna
A114: Katherine Pink | B114: katherine.pink@som.com | C114: SOMBP | D114: Design and Construction Director | E114: SOMBP | G114: Katherine
A115: Kayci BROWNE | B115: kbrowne@un.org | D115: Transition Program. Manag. Officer | G115: Kayci
A116: Kenneth Potgieter | B116: k.potgieter@gardiner.com | C116: G&T | D116: Cost Management | E116: G&T | G116: Kenneth
A117: Laetitia Menin | B117: laetitia.menin@un.org | D117: Engineer, Buildings Unit, Facility Management Section | G117: Laetitia
A118: Laurent Sailler | B118: laurent.sailler@rapp.ch | C118: RAPP | D118: TBC | G118: Laurent
A119: Leonardo Castellani | B119: leonardo.castellani@trepi.it | C119: 3PI | D119: AV and Broadcast Expert | E119: RPN | G119: Leonardo
A120: Leonardo Deliaj | B120: sldeliaj@dallmanagement.com | C120: RPN | D120: MEP Manager | E120: RPN | G120: Leonardo
A121: Leonardo Valentinotti | B121: leonardo.valentinotti@rpn-sa.ch | C121: RPN | D121: Deputy Quality Manager | E121: RPN | G121: Leonardo
A122: Liliana Sanches Le Saux | B122: liliana.lesaux@gmail.com | C122: SOMBP | D122: Architect / Accessibility | E122: SOMBP | G122: Liliana
A123: Lionel Perrin | B123: lionel.perrin@csc-sa.ch | C123: C2BE | D123: Project Control Manager | E123: C2BE | G123: Lionel
A124: Loice Mhuru | B124: l.mhuru@gardiner.com | C124: G&T | D124: Cost Management | E124: G&T | G124: Loice
A125: Lorenzo Barnini | B125: lorenzo.barnini@cmbcarpi.it | C125: RPN | D125: Project Manager (PM) | E125: RPN | G125: Lorenzo
A126: Lorenzo Fiorucci | B126: lorenzo.fiorucci@csc-sa.ch | C126: C2BE | D126: Project Manager (PM) | E126: RPN | G126: Lorenzo
A127: Lorenzo Lelli | B127: lorenzo.lelli@ingeni.ch | C127: Structural | D127: TBC | E127: SOMBP | G127: Lorenzo
A128: Lorik Rashica | B128: lrashica@smwllc.com | C128: SOMBP | D128: TBC | E128: SOMBP | G128: Lorik
...

Sheet DELEGATE
A1: ESCALATE | B1: Owner Name
A2: AB+C - 12 WLA AV focus | B2: Jean-Mathieu Ferre
A3: Leadership meeting | B3: Patrick Fowler
A4: Operational Readiness Meeting | B4: Zeynep Onen
A5: PM | B5: Patrick Fowler
A6: R - Architectural meeting | B6: Bob Wyse
A7: UNTV - 12 WLA | B7: Jean-Mathieu Ferre
A8: Site visit

Sheet DISCIPLINE
A1: Discipline | B1: description | C1: RFI / NCF DISCIPLINE | D1: DALUX disciplne | E1: MACRO DISCIPLINE
A2: A | B2: Architecture | C2: A - Architecture | D2: ARCH | E2: ARC
A3: A | B3: Architecture | D3: ARCHITECTURAL | E3: ARC
A4: A | B4: Architecture | D4: HERI | E4: ARC
A5: A | B5: Architecture | D5: HERITAGE | E5: ARC
A6: AI | B6: Architectural Interior | C6: AI - Architectural Interior | E6: ARC
A7: AL | B7: Lighting | C7: AL - Lighting | E7: ARC
A8: BC | B8: Broadcast | C8: BC - Broadcast | D8: AUDIOVISUAL & BROADCAST | E8: TA
A9: BC | B9: Broadcast | D9: AVBC | E9: TA
A10: BIM | B10: BIM | C10: BIM - BIM | E10: ARC
A11: CON | B11: Construction | C11: CON | E11: CON
A12: EL | B12: Electrical | C12: EL - Electrical | D12: ELECTRICAL/SAFETY/SECURITY | E12: MEP
A13: EL | B13: Electrical | D13: ELSS | E13: MEP
A14: ENV | B14: Envelope | C14: ENV - Envelope | E14: ARC
A15: FA | B15: Facade | C15: FA - Facade | E15: ARC
A16: FP | B16: Fire Protection | C16: FP - Fire Protection | E16: ARC
A17: FU | B17: Furniture | C17: FU - Furniture | E17: ARC
A18: HM | B18: Hazardous Material | C18: HM - Hazardous Material | E18: ARC
A19: KC | B19: Kitchen | C19: KC - Kitchen | E19: ARC
A20: LS | B20: Landscape | C20: LS - Landscape | E20: ARC
A21: MEP | B21: Combined Plans | C21: MEP - Combined Plans | E21: MEP
A22: MH | B22: Mechanical HVAC | C22: MH - Mechanical HVAC | D22: MECHANICAL/PLUMBING | E22: MEP
A23: MH | B23: Mechanical HVAC | D23: MHPL | E23: MEP
A24: MH | B24: Mechanical HVAC | D24: MP | E24: MEP
A25: PE | B25: Permit | C25: PE - Permit | E25: PM
A26: PL | B26: Plumbing | C26: PL - Plumbing | D26: MECHANICAL/PLUMBING | E26: MEP
A27: PL | B27: Plumbing | D27: MHPL | E27: MEP
A28: PL | B28: Plumbing | D28: MP | E28: MEP
A29: PM | B29: Project Management | C29: PM - Project Management | E29: PM
A30: QA | B30: Quality Assurance | D30: QA | E30: QUALITY
A31: QC | E31: QUALITY
A32: QM | E32: QUALITY
A33: SE | B33: Structural Existing Buildings | C33: SE - Structural Existing Buildings | D33: STRU | E33: ARC
A34: SE | B34: Structural Existing Buildings | D34: STRUCTURE | E34: ARC
A35: SN | B35: Structural New Building | D35: STRU | E35: ARC
A36: SN | B36: Structural New Building | C36: SN - Structural New Building | D36: STRUCTURE | E36: ARC
A37: STK | B37: Stakeholders Engagement | C37: STK - Stakeholders Engagement | E37: PM
A38: TT | B38: IT | C38: TT - IT | D38: IT | E38: TT
A39: TA | B39: Audiovisuals | C39: TA - Audiovisuals | D39: AUDIOVISUAL | E39: TA
A40: TA | B40: Audiovisuals | D40: AUDIOVISUAL & BROADCAST | E40: TA
A41: TA | B41: Audiovisuals | D41: AVBC | E41: TA
A42: TY | B42: Security | C42: TY - Security | D42: ELECTRICAL/SAFETY/SECURITY | E42: TY
A43: TY | B43: Security | D43: ELSS | E43: TY
A44: VT | B44: Vertical Transportation | C44: VT - Vertical Transportation | E44: VT
A45: HSE | B45: Health, Security and Environment | C45: HSE - Health, Security and Environment | E45: PM
A46: HSE | B46: Health, Security and Environment | D46: ELECTRICAL/SAFETY/SECURITY | E46: PM
